Workbook

Sheet RECAP
B1: Date | C1: Recette Avril 2024 | D1: Recette | E1: Charges | F1: Salaire | G1: Loyer | H1: Net Profit | I1: Nb de jours | K1: Objectif | L1: 45383
A2: Mercredi | B2: 45413 | C2: 74000 | D2: 40000 | I2: 1 | L2: 74000
A3: Jeudi | B3: 45414 | C3: 37000 | D3: 41000 | I3: 1 | L3: 37000 | M3: Bénéfice Moyen par jour | N3: Moyenne | O3: Moyenne salaire | P3: pourcentage du salaire vis à vis la recettte
A4: Vendredi | B4: 45415 | C4: 62000 | D4: 50000 | I4: 1 | L4: 62000 | M4: =H33/I33 -> 3851.4673 | N4: =D33/I33 -> 43290.323 | P4: =O4/N4 -> 0
A5: Samedi | B5: 45416 | C5: 62000 | D5: 35000 | I5: 1 | L5: 62000
A6: Dimanche | B6: 45417 | C6: 21000 | D6: 28000 | I6: 1 | L6: 21000 | M6: Moyenne des charges par jour | N6: Objectif
A7: Lundi | B7: 45418 | C7: 33000 | D7: 40000 | I7: 1 | L7: 33000 | M7: =E33/I33 -> 20843.226 | N7: 100000
A8: Mardi | B8: 45419 | C8: 500000 | D8: 52000 | I8: 1 | L8: 500000 | M8: ²
A9: Mercredi | B9: 45420 | C9: 240000 | D9: 31000 | I9: 1 | L9: 240000
A10: Jeudi | B10: 45421 | C10: 0 | D10: 107000 | I10: 1 | L10: 0 | M10: Cash restant | N10: Magasin | O10: Cash réel | P10: Mes dettes pour le magasin
A11: Vendredi | B11: 45422 | C11: 0 | D11: 85000 | I11: 1 | L11: 0 | M11: =D33+M14-E33-'Salaires '!H31-N11 -> 549360 | N11: 38000 | O11: =O17+P33 -> 776000 | P11: =M11-O11 -> -226640
A12: Samedi | B12: 45423 | C12: 0 | D12: 40000 | I12: 1 | L12: 0
A13: Dimanche | B13: 45424 | C13: 0 | D13: 60000 | I13: 1 | L13: 0 | M13: Fond de Roulement
A14: Lundi | B14: 45425 | C14: 30000 | D14: 50000 | I14: 1 | L14: 30000 | M14: 330000 | P14: Demain je prends de la caisse:14000Da
A15: Mardi | B15: 45426 | C15: 40000 | D15: 50000 | I15: 1 | L15: 40000 | P15: Salim: 7000 Da
A16: Mercredi | B16: 45427 | C16: 45000 | D16: 45000 | I16: 1 | L16: 45000 | O16: Cash chez Moi | P16: Monnie : 8000 Da
A17: Jeudi | B17: 45428 | C17: 45000 | D17: 50000 | I17: 1 | L17: 45000 | O17: 156000 | P17: Khalida: 5000 Da
A18: Vendredi | B18: 45429 | C18: 49000 | D18: 40000 | I18: 1 | L18: 49000 | P18: Hayet: 4000Da
A19: Samedi | B19: 45430 | C19: 85000 | D19: 35000 | I19: 1 | L19: 85000 | M19: Différence mois d'Avril | P19: la vraie caisse: 14000Da
A20: Dimanche | B20: 45431 | C20: 40000 | D20: 30000 | I20: 1 | L20: 40000 | M20: =D33-C33 -> -568000
A21: Lundi | B21: 45432 | C21: 42000 | D21: 37000 | I21: 1 | L21: 42000 | M21: Différence objectif | O21: réparation Tabouna | P21: 1 | Q21: 8800 | R21: =P21*Q21 -> 8800
A22: Mardi | B22: 45433 | C22: 43000 | D22: 40000 | I22: 1 | L22: 43000 | M22: =K36-E36 -> 0 | O22: Torchons | P22: 4 | Q22: 400 | R22: 600
A23: Mercredi | B23: 45434 | C23: 60000 | D23: 23000 | I23: 1 | L23: 60000 | M23: Différence du Totale | O23: poelle | P23: 1 | Q23: 2800 | R23: =P23*Q23 -> 2800
A24: Jeudi | B24: 45435 | C24: 54000 | D24: 48000 | I24: 1 | L24: 54000 | M24: =D33-C33 -> -568000 | R24: =SUM(R21:R23) -> 12200
A25: Vendredi | B25: 45436 | C25: 65000 | D25: 26000 | I25: 1 | L25: 65000 | M25: Les vendredis | O25: Cash chez Sofiane
A26: Samedi | B26: 45437 | C26: 92000 | D26: 25000 | I26: 1 | L26: 92000 | M26: =D9+D16+D23+D30 -> 141000 | O26: 45422 | P26: 200000
A27: Dimanche | B27: 45438 | C27: 26000 | D27: 33000 | I27: 1 | L27: 26000 | O27: 45426 | P27: 200000
A28: Lundi | B28: 45439 | C28: 41000 | D28: 23000 | I28: 1 | L28: 41000 | M28: Cash réel | O28: 45431 | P28: 100000
A29: Mardi | B29: 45440 | C29: 38000 | D29: 30000 | I29: 1 | L29: 38000 | M29: 51000 | O29: 45434 | P29: 25000
A30: Mercredi | B30: 45441 | C30: 40000 | D30: 42000 | I30: 1 | L30: 40000 | M30: rest à payer | O30: 45446 | P30: 95000
A31: Jeudi | B31: 45442 | C31: 46000 | D31: 75000 | I31: 1 | L31: 46000
A32: Vendredi | B32: 45443 | C32: 0 | D32: 31000 | I32: 1 | L32: 0
C33: =SUM(C2:C32) -> 1910000 | D33: =SUM(D2:D32) -> 1342000 | E33: ='Les charges '!G379 -> 646140 | F33: ='Salaires '!G31 -> 436464.52 | G33: 140000 | H33: =D33-E33-F33-G33 -> 119395.49 | I33: =SUM(I2:I32) -> 31 | L33: =SUM(L2:L32) -> 1910000 | P33: =SUM(P26:P32) -> 620000
M35: =M11-M29-M34 -> 498360
D38: -

Sheet Pointage 
B1: Date | C1: Lynda | D1: Hafida | E1: Yasmine Sidi Abd Allah | F1: Nawel | G1: Khadidja | H1: Fouzia | I1: Nadjet | J1: Fatiha | K1: Samira | L1: Zohra | M1: Chiraz | N1: Ilhem | O1: Sarah | P1: Saliha | Q1: Romayessa | R1: Radia
A2: Mercredi | B2: 45413 | C2: 0 | D2: 1 | E2: 0 | F2: 0 | G2: 0 | H2: 0 | I2: 0 | J2: 1 | K2: 1 | L2: 1 | M2: 1 | N2: 1 | O2: 0 | P2: 0 | Q2: 0 | S2: Yasmine dely Brahim
A3: Jeudi | B3: 45414 | C3: 0 | D3: 1 | E3: 1 | F3: 0 | G3: 0 | H3: 0 | I3: 0.5 | J3: 1 | K3: 1 | L3: 0 | M3: 1 | N3: 1 | O3: 0 | P3: 0 | Q3: 0
A4: Vendredi | B4: 45415 | C4: 1 | D4: 1.5 | E4: 1 | F4: 0 | G4: 0 | H4: 0 | I4: 1.5 | J4: 0 | K4: 1 | L4: 0 | M4: 1 | N4: 0 | O4: 0 | P4: 0 | Q4: 0
A5: Samedi | B5: 45416 | C5: 1 | D5: 0 | E5: 1 | F5: 0 | G5: 0 | H5: 0 | I5: 1 | J5: 1 | K5: 1 | L5: 0 | M5: 1 | N5: 1 | O5: 1 | P5: 0 | Q5: 0
A6: Dimanche | B6: 45417 | C6: 0 | D6: 1 | E6: 1 | F6: 0 | G6: 0 | H6: 1 | I6: 0 | J6: 1 | K6: 0 | L6: 0 | M6: 0 | N6: 1 | O6: 1 | P6: 1 | Q6: 0
A7: Lundi | B7: 45418 | C7: 0 | D7: 1 | E7: 1 | F7: 1 | G7: 0 | H7: 1 | I7: 0 | J7: 1 | K7: 1 | L7: 1 | M7: 0.5 | N7: 1 | O7: 1 | P7: 1 | Q7: 0
A8: Mardi | B8: 45419 | C8: 0.5 | D8: 1 | E8: 0 | F8: 1 | G8: 0 | H8: 1 | I8: 1 | J8: 1 | K8: 1 | L8: 0 | M8: 0 | N8: 1 | O8: 1 | P8: 1 | Q8: 1 | R8: 1
A9: Mercredi | B9: 45420 | C9: 0.5 | D9: 1 | E9: 1 | F9: 1 | G9: 0 | H9: 1 | I9: 1 | J9: 1 | K9: 1 | L9: 0 | M9: 1 | N9: 1 | O9: 1 | P9: 1 | Q9: 1 | R9: 1
A10: Jeudi | B10: 45421 | C10: 0 | D10: 1 | E10: 1 | F10: 1 | G10: 0 | H10: 0.5 | I10: 1 | J10: 1 | K10: 1 | L10: 0 | M10: 1 | N10: 1 | O10: 1 | P10: 1 | Q10: 1 | R10: 1
A11: Vendredi | B11: 45422 | C11: 1 | D11: 1 | E11: 1 | F11: 0 | G11: 0 | H11: 0 | I11: 0 | J11: 0 | K11: 1 | L11: 0 | M11: 1 | N11: 1 | O11: 0 | P11: 0 | Q11: 0 | R11: 0
A12: Samedi | B12: 45423 | C12: 0 | D12: 0 | E12: 1 | F12: 1 | G12: 0 | H12: 0.5 | I12: 0 | J12: 1 | K12: 1 | L12: 0 | M12: 0.5 | N12: 1 | O12: 1 | P12: 1 | Q12: 0 | R12: 0
A13: Dimanche | B13: 45424 | C13: 0 | D13: 1 | E13: 1 | F13: 1 | G13: 0 | H13: 1 | I13: 0 | J13: 1 | K13: 1 | L13: 1 | M13: 1 | N13: 1 | O13: 1 | P13: 1 | Q13: 1 | R13: 1
A14: Lundi | B14: 45425 | C14: 0 | D14: 1 | E14: 1 | F14: 1 | G14: 0 | H14: 1 | I14: 0 | J14: 1 | K14: 1 | L14: 0 | M14: 1 | N14: 1 | O14: 1 | P14: 1 | Q14: 1 | R14: 1
A15: Mardi | B15: 45426 | C15: 0 | D15: 1 | E15: 0 | F15: 1 | G15: 0 | H15: 1 | I15: 0 | J15: 1 | K15: 0 | L15: 1 | M15: 0 | N15: 1 | O15: 0 | P15: 1 | Q15: 1 | R15: 1
A16: Mercredi | B16: 45427 | C16: 0 | D16: 1 | E16: 1 | F16: 1 | G16: 0 | H16: 1 | I16: 0 | J16: 1 | K16: 1 | L16: 0 | M16: 1 | N16: 1 | O16: 1 | P16: 1 | Q16: 1 | R16: 1
A17: Jeudi | B17: 45428 | C17: 0 | D17: 1 | E17: 1 | F17: 1 | G17: 1 | H17: 0.5 | I17: 0.5 | J17: 1 | K17: 1 | L17: 1 | M17: 0.5 | N17: 1 | O17: 1 | P17: 1 | Q17: 1 | R17: 1
A18: Vendredi | B18: 45429 | C18: 1 | D18: 1 | E18: 1 | F18: 0 | G18: 0 | H18: 0 | I18: 0 | J18: 0 | K18: 1 | L18: 0 | M18: 1 | N18: 0 | O18: 1 | P18: 1 | Q18: 1 | R18: 0
A19: Samedi | B19: 45430 | C19: 0.5 | D19: 1 | E19: 1 | F19: 1 | G19: 0 | H19: 0 | I19: 0 | J19: 1 | K19: 1 | L19: 0 | M19: 0.5 | N19: 1 | O19: 0.5 | P19: 0 | Q19: 1 | R19: 0.5
... A32: Vendredi | B32: 45443 | C32: 1 | D32: 1 | E32: 1 | F32: 0 | G32: 1 | H32: 0 | I32: 0 | J32: 0 | K32: 1 | L32: 0 | M32: 0 | N32: 0 | O32: 0 | P32: 0 | Q32: 1 | R32: 0
C33: =SUM(C2:C32) -> 8.5 | D33: =SUM(D2:D32) -> 28.5 | E33: =SUM(E2:E32) -> 26.5 | F33: =SUM(F2:F32) -> 22 | G33: =SUM(G2:G32) -> 11 | H33: =SUM(H2:H32) -> 17.25 | I33: =SUM(I2:I32) -> 11 | J33: =SUM(J2:J32) -> 25.25 | K33: =SUM(K2:K32) -> 27 | L33: 15 | M33: =SUM(M2:M32) -> 15 | N33: =SUM(N2:N32) -> 18 | O33: =SUM(O2:O32) -> 22.5 | P33: =SUM(P2:P32) -> 23 | Q33: =SUM(Q2:Q32) -> 21 | R33: =SUM(R2:R32) -> 17
C34: 1384.62 | D34: 1540 | E34: 1153.85 | F34: 1153.85 | G34: 1153.85 | H34: 1384.62 | I34: 1500 | J34: 1076.93 | K34: 1153.85 | L34: 1200 | M34: 1153.85 | N34: 1346 | O34: 1100 | P34: 1153.85 | Q34: 1153.85 | R34: 1100
C35: =C33*C34 -> 11769.27 | D35: =D34*D33 -> 43890 | E35: =E34*E33 -> 30577.025 | F35: =F33*F34 -> 25384.7 | G35: =G34*G33 -> 12692.35 | H35: =H33*H34 -> 23884.695 | I35: =I33*I34 -> 16500 | J35: =J33*J34 -> 27192.482 | K35: =K34*K33 -> 31153.95 | L35: =L34*L33 -> 18000 | M35: =M33*M34 -> 17307.75 | N35: =N33*N34 -> 24228 | O35: =O34*O33 -> 24750 | P35: =P33*P34 -> 26538.55 | Q35: =Q33*Q34 -> 24230.85 | R35: =R33*R34 -> 18700 | S35: =SUM(C32:M32) -> 5
C36: 36000 | D36: 40000 | E36: 30000 | F36: 30000 | G36: 30000 | H36: 36000 | J36: 28000 | K36: 30000 | M36: 30000 | N36: 35000 | O36: 26000 | P36: 26000 | Q36: 30000

Sheet Les charges 
D4: Produit | E4: Quantité | F4: Prix unitaire | G4: Prix | H4: Date d'achat
D5: levure chimique | E5: 150 | F5: 6.5 | G5: =E5*F5 -> 975 | H5: 45383
D6: sachets 5kg blanc | E6: 1 | F6: 1200 | G6: =E6*F6 -> 1200
D7: sachets transparents | E7: 1 | F7: 850 | G7: =E7*F7 -> 850
D8: sac croissant 23 | E8: 1 | F8: 850 | G8: =E8*F8 -> 850
D9: sac croissant 17 | E9: 1 | F9: 650 | G9: =E9*F9 -> 650
D10: Fromage spéciale pizza Napoli | E10: 3 | F10: 350 | G10: =E10*F10 -> 1050
D11: Thon 2kg | E11: 3 | F11: 1800 | G11: =E11*F11 -> 5400
D12: Maiis | E12: 7 | F12: 240 | G12: =E12*F12 -> 1680
D13: Crème liquide Soummam 500cl | E13: 3 | F13: 250 | G13: =E13*F13 -> 750
D14: Tomtate conserve Kingtom 1kg | E14: 20 | F14: 320 | G14: =E14*F14 -> 6400
D15: Maa zehar zahia | E15: 8 | F15: 65 | G15: =E15*F15 -> 520
D16: semoulemoyenne Moula 10 kg | E16: 2 | F16: 1100 | G16: =E16*F16 -> 2200
D17: felefel | E17: 2 | F17: 120 | G17: =E17*F17 -> 240
... D97: Pate Feuilleté | E97: 2 | F97: 400 | G97: =E97*F97 -> 800
D98: Rechta | E98: 5 | F98: 100 | G98: =E98*F98 -> 500 | H98: 45416
D99: poulet haché + blanc de poulet | E99: 2.5 | F99: 800 | G99: =E99*F99 -> 2000
D100: Boite 48/10 | E100: 1 | F100: 1800 | G100: =E100*F100 -> 1800
D101: Boite 48/07 | E101: 1 | F101: 1450 | G101: =E101*F101 -> 1450
D102: Boite 36 | E102: 2 | F102: 1200 | G102: =E102*F102 -> 2400
D103: Boite 24 | E103: 1 | F103: 1100 | G103: =E103*F103 -> 1100
D104: Bessel | E104: 20 | F104: 110 | G104: =E104*F104 -> 2200
D105: chakhechoukhate dhefer | E105: 2 | F105: 250 | G105: =E105*F105 -> 500
D106: Navet+ courgette | E106: 5 | F106: 120 | G106: =E106*F106 -> 600 | H106: 45448
D107: Carotte | E107: 1 | F107: 100 | G107: =E107*F107 -> 100
D108: poivre | E108: 0.5 | F108: 100 | G108: =E108*F108 -> 50
D109: cuisses de poulet | E109: 8 | F109: 150 | G109: =E109*F109 -> 1200
D110: viande morceaux | E110: 1.5 | F110: 1200 | G110: =E110*F110 -> 1800
D111: viande hachée | E111: 0.5 | F111: 1200 | G111: =E111*F111 -> 600
D112: olive noir | E112: 0.5 | F112: 400 | G112: =E112*F112 -> 200
D113: Rechta | E113: 5 | F113: 120 | G113: =E113*F113 -> 600
D114: Bessel | E114: 20 | F114: 110 | G114: =E114*F114 -> 2200
D115: Hamissa | E115: 1 | F115: 220 | G115: =E115*F115 -> 220
D116: fromage slices | E116: 2 | F116: 220 | G116: =E116*F116 -> 440
D117: Crème liquide Soummam 500cl | E117: 1 | F117: 260 | G117: =E117*F117 -> 260
D118: Huile Elio 5 litres | E118: 2 | F118: 650 | G118: =E118*F118 -> 1300
D119: dettes Brahim | E119: 1 | F119: 1200 | G119: =E119*F119 -> 1200
D120: Bessel | E120: 30 | F120: 100 | G120: =E120*F120 -> 3000 | H120: 45478
D121: Bessel | E121: 30 | F121: 50 | G121: =E121*F121 -> 1500
D122: plateaux oeufs | E122: 4 | F122: 400 | G122: =E122*F122 -> 1600
D123: poulet haché + blanc de poulet | E123: 2.5 | F123: 800 | G123: =E123*F123 -> 2000
D124: feuilles de tacos | E124: 1 | F124: 350 | G124: =E124*F124 -> 350
D125: viande morceaux | E125: 1.25 | F125: 1200 | G125: =E125*F125 -> 1500
D126: épinard | E126: 3 | F126: 30 | G126: =E126*F126 -> 90
D127: Deyoul | E127: 2 | F127: 100 | G127: =E127*F127 -> 200
D128: salade | E128: 2 | F128: 80 | G128: =E128*F128 -> 160
D129: Tomate cerise | E129: 1.25 | F129: 200 | G129: =E129*F129 -> 250
D130: poivre | E130: 0.5 | F130: 100 | G130: =E130*F130 -> 50
D131: Navet+ courgette | E131: 1 | F131: 150 | G131: =E131*F131 -> 150
D132: carotte | E132: 1 | F132: 100 | G132: =E132*F132 -> 100
... D139: Rechta | E139: 6 | F139: 130 | G139: =E139*F139 -> 780
D140: plateaux oeufs | E140: 2 | F140: 420 | G140: =E140*F140 -> 840 | H140: 45422
D141: poulet haché + blanc de poulet | E141: 2.5 | F141: 800 | G141: =E141*F141 -> 2000
D142: Gherss | E142: 3 | F142: 220 | G142: =E142*F142 -> 660
D143: célophane | E143: 8 | F143: 130 | G143: =E143*F143 -> 1040
D144: les ataches | E144: 16 | F144: 20 | G144: =E144*F144 -> 320
D145: olive noir | E145: 0.5 | F145: 400 | G145: =E145*F145 -> 200
D146: olive dényauté | E146: 0.5 | F146: 600 | G146: =E146*F146 -> 300
D147: olive éffilet | E147: 0.5 | F147: 600 | G147: =E147*F147 -> 300
D148: Fromage spéciale pizza Napoli | E148: 5 | F148: 200 | G148: =E148*F148 -> 1000
D149: épice poulet | E149: 1 | F149: 200 | G149: =E149*F149 -> 200
D150: poivre noir | E150: 1 | F150: 200 | G150: =E150*F150 -> 200
D151: bessel | E151: 40 | F151: 50 | G151: =E151*F151 -> 2000
D152: Rechta | E152: 15 | F152: 100 | G152: =E152*F152 -> 1500
... D156: crevette | E156: 1 | F156: 1200 | G156: =E156*F156 -> 1200
C157: 1300 | D157: Noix | E157: 1 | F157: 1300 | G157: =E157*F157 -> 1300 | H157: 45421
D158: Amande blanc | E158: 1 | F158: 1750 | G158: =E158*F158 -> 1750
D159: sac 25 kg | E159: 1 | F159: 220 | G159: =E159*F159 -> 220
D160: dentelle Baklawa | E160: 2 | F160: 350 | G160: =E160*F160 -> 700
C161: 1720 | D161: Amande blanc | E161: 5 | F161: 1720 | G161: =E161*F161 -> 8600
C162: 84 | D162: Farine SIM | E162: 26 | F162: 84 | G162: =E162*F162 -> 2184
C163: 30 | D163: Les piles | E163: 24 | F163: 30 | G163: =E163*F163 -> 720
D164: Boites Raib | E164: 50 | F164: 10.5 | G164: =E164*F164 -> 525
D165: Barquette 1065 | E165: 50 | F165: 16 | G165: =E165*F165 -> 800
D166: Fourchette | E166: 2 | F166: 120 | G166: =E166*F166 -> 240
D167: Arome | E167: 1 | F167: 100 | G167: =E167*F167 -> 100
D168: Cannette Coca | E168: 24 | F168: 70 | G168: =E168*F168 -> 1680
D169: coca fanta | E169: 36 | F169: 50 | G169: =E169*F169 -> 1800
D170: hamoud | E170: 24 | F170: 46 | G170: =E170*F170 -> 1104
D171: canette hamoud + shwepes | E171: 18 | F171: 80 | G171: =E171*F171 -> 1440
D172: Rechta | E172: 10 | F172: 100 | G172: =E172*F172 -> 1000 | H172: 45421
D173: bessel | E173: 30 | F173: 100 | G173: =E173*F173 -> 3000
D174: bessel | E174: 30 | F174: 50 | G174: =E174*F174 -> 1500
D175: Tomate Fraiche | E175: 4 | F175: 50 | G175: =E175*F175 -> 200
D176: poulet haché + blanc de poulet | E176: 2.5 | F176: 800 | G176: =E176*F176 -> 2000
D177: 3akeri | E177: 1 | F177: 300 | G177: =E177*F177 -> 300
D178: canelle | E178: 1 | F178: 100 | G178: =E178*F178 -> 100
D179: herbe de provence | E179: 1 | F179: 350 | G179: =E179*F179 -> 350
D180: Crème liquide Soummam 500cl | E180: 1 | F180: 270 | G180: =E180*F180 -> 270
D181: registre des commandes | E181: 1 | F181: 570 | G181: =E181*F181 -> 570
D182: crème liquide maitre culinaire 1 litre | E182: 2 | F182: 450 | G182: =E182*F182 -> 900
D183: poulet haché + blanc de poulet | E183: 2.5 | F183: 800 | G183: =E183*F183 -> 2000
D184: viande hachéé | E184: 0.5 | F184: 2400 | G184: =E184*F184 -> 1200
... D192: boites demie plateau | E192: 5 | F192: 70 | G192: =E192*F192 -> 350
D193: pomme de terre | E193: 20 | F193: 90 | G193: =E193*F193 -> 1800 | H193: 45425
D194: blanc de poulet | E194: 9 | F194: 750 | G194: =E194*F194 -> 6750
D195: plateaux oeufs | E195: 7 | F195: 450 | G195: =E195*F195 -> 3150
D196: Tomate Fraiche | E196: 15 | F196: 70 | G196: =E196*F196 -> 1050
D197: Bessel | E197: 30 | F197: 100 | G197: =E197*F197 -> 3000
D198: Bessel | E198: 30 | F198: 50 | G198: =E198*F198 -> 1500
...

Sheet Salaires 
F12: Nom | G12: Salaire | H12: Avance | I12: Salaire à payer
F13: Sofiane | G13: 30000 | H13: 30000 | I13: =G13-H13 -> 0
F14: Amel | G14: 30000 | H14: 30000 | I14: =G14-H14 -> 0
E15: 1 | F15: Lynda | G15: ='Pointage '!C35 -> 11769.27 | H15: 12000 | I15: =G15-H15 -> -230.73
E16: 2 | F16: Hafida | G16: ='Pointage '!D35 -> 43890 | H16: 44000 | I16: =G16-H16 -> -110
E17: 3 | F17: Yasmine Sidi Abd Allah | G17: 34500 | H17: 34500 | I17: =G17-H17 -> 0 | K17: 30577.03 | L17: 5000
E18: 4 | F18: Nawel | G18: 24300 | H18: 24500 | I18: =G18-H18 -> -200
E19: 5 | F19: khadidja | G19: ='Pointage '!G35 -> 12692.35 | H19: 13000 | I19: =G19-H19 -> -307.65
E20: 6 | F20: Fouzia | G20: ='Pointage '!H35 -> 23884.695 | H20: 24000 | I20: =G20-H20 -> -115.305
E21: 7 | F21: Nadjet | G21: ='Pointage '!I35 -> 16500 | H21: 16500 | I21: =G21-H21 -> 0 | J21: 2000+1000+3000+450+1000
E22: 8 | F22: Fatiha | G22: 27000 | H22: 27000 | I22: =G22-H22 -> 0
E23: 9 | F23: Samira | G23: 30000 | H23: 30000 | I23: =G23-H23 -> 0 | J23: 1000+1000+1000
E24: 10 | F24: Zohra | G24: ='Pointage '!L35 -> 18000 | H24: 18000 | I24: =G24-H24 -> 0
E25: 11 | F25: Chiraz | G25: ='Pointage '!M35 -> 17307.75 | H25: 17500 | I25: =G25-H25 -> -192.25
E26: 12 | F26: Ilhem | G26: ='Pointage '!N35 -> 24228 | H26: 24500 | I26: =G26-H26 -> -272
E27: 13 | F27: Sarah | G27: 24000 | H27: 24000 | I27: =G27-H27 -> 0
E28: 14 | F28: Saliha | G28: 25461.6 | H28: 25500 | I28: =G28-H28 -> -38.4
E29: 15 | F29: Romayessa | G29: ='Pointage '!Q35 -> 24230.85 | H29: 24500 | I29: =G29-H29 -> -269.15
E30: 16 | F30: Radia | G30: ='Pointage '!R35 -> 18700 | H30: 19000 | I30: =G30-H30 -> -300
F31: TOTAL | G31: =SUM(G13:G30) -> 436464.52 | H31: =SUM(H13:H30) -> 438500 | I31: =G31-H31 -> -2035.485
I32: =G32-H32 -> 0

Sheet Feuille 5
D23: Mois de Janvier | E23: Mois de Février | F23: Mois de Mars | G23: Mois d'Avril | H23: Mois de Mai | K23: Mois de Mai
C24: Recette | D24: 1756000 | E24: 2274000 | F24: 1984000 | G24: 1910000 | H24: 1342000 | J24: Recette | K24: 1342000
C25: Charges | D25: 920000 | E25: 914000 | F25: 928000 | G25: 744000 | H25: 646000 | J25: Charges | K25: 646000
C26: Salaires | D26: 349000 | E26: 410000 | F26: 406000 | G26: 344000 | H26: 436000 | J26: Salaires | K26: 436000
C27: Loyer | D27: 140000 | E27: 140000 | F27: 140000 | G27: 140000 | H27: 140000 | J27: Loyer | K27: 140000
C28: Profit Net | D28: =D24-D25-D26-D27 -> 347000 | E28: =E24-E25-E26-E27 -> 810000 | F28: =F24-F25-F26-F27 -> 510000 | G28: 680000 | H28: =H24-H25-H26-H27 -> 120000 | J28: Profit Net | K28: =K24-K25-K26-K27 -> 120000
