Workbook

Sheet RECAP
B1: Date | C1: Recette | D1: Charges | E1: Salaire | F1: Loyer | G1: Net Profit | H1: Nb de jours
A2: mercredi | B2: 44013 | C2: 19000 | H2: 1
A3: jeudi | B3: 44014 | C3: 32000 | H3: 1
A4: vendredi | B4: 44015 | C4: 0 | D4: 0 | E4: 0 | F4: 0 | G4: 0 | H4: 0 | L4: Myenne
A5: samedi | B5: 44016 | C5: 12000 | H5: 1 | L5: =C33/H33 -> 19615.385
A6: dimanche | B6: 44017 | C6: 10000 | H6: 1
A7: lundi | B7: 44018 | C7: 11000 | H7: 1
A8: mardi | B8: 44019 | C8: 12000 | H8: 1
A9: mercredi | B9: 44020 | C9: 8000 | H9: 1
A10: jeudi | B10: 44021 | C10: 16000 | H10: 1
A11: vendredi | B11: 44022 | C11: 0 | D11: 0 | E11: 0 | F11: 0 | G11: 0 | H11: 0
A12: samedi | B12: 44023 | C12: 8000 | H12: 1
A13: dimanche | B13: 44024 | C13: 11000 | H13: 1
A14: lundi | B14: 44025 | C14: 22000 | H14: 1
A15: mardi | B15: 44026 | C15: 17000 | H15: 1 | L15: Cash restant | M15: Magasin | N15: Semid pr mois d'aout
A16: mercredi | B16: 44027 | C16: 27000 | H16: 1 | L16: =C33+Charges!H158-Charges!H157-Salaires!J22 -> 200355 | M16: 7000 | N16: 26200 | O16: =L16-L17-M16-N16 -> 30155
A17: jeudi | B17: 44028 | C17: 17000 | H17: 1 | L17: 137000
A18: vendredi | B18: 44029 | C18: 0 | D18: 0 | E18: 0 | F18: 0 | G18: 0 | H18: 0
A19: samedi | B19: 44030 | C19: 27000 | H19: 1
A20: dimanche | B20: 44031 | C20: 9000 | H20: 1
A21: lundi | B21: 44032 | C21: 13000 | H21: 1
A22: mardi | B22: 44033 | C22: 17000 | H22: 1
A23: mercredi | B23: 44034 | C23: 17000 | H23: 1
A24: jeudi | B24: 44035 | C24: 24000 | H24: 1
A25: vendredi | B25: 44036 | C25: 0 | D25: 0 | E25: 0 | F25: 0 | G25: 0 | H25: 0
A26: Samedi | B26: 44037 | C26: 18000 | H26: 1
A27: Dimanche | B27: 44038 | C27: 23000 | H27: 1
A28: Lundi | B28: 44039 | C28: 16000 | H28: 1
A29: Mardi | B29: 44040 | C29: 11000 | H29: 1
A30: Mercredi | B30: 44041 | C30: 50000 | H30: 1
A31: Jeudi | B31: 44042 | C31: 63000 | H31: 1
A32: Vendredi | B32: 44043 | C32: 0 | D32: 0 | E32: 0 | F32: 0 | G32: 0
A33: TOTAL | C33: =SUM(C2:C32) -> 510000 | D33: =Charges!H157*1 -> 202845 | E33: =Salaires!I22*1 -> 146715 | F33: 77000 | G33: =C33-D33-E33-F33 -> 83440 | H33: =SUM(H2:H32) -> 26
A34: TAUX | C34: 1 | D34: =D33/C33 -> 0.39773529 | E34: =E33/C33 -> 0.28767647 | F34: =F33/C33 -> 0.15098039 | G34: =G33/C33 -> 0.16360784

Sheet Pointage
B1: Date | C1: Zehor | D1: Zoubida | E1: Amel | F1: Karima | G1: Nouara | H1: Zahida | I1: Remarque
A2: Mercredi | B2: 44013 | C2: 1 | D2: 1 | E2: 1 | F2: 1 | G2: 1 | H2: 1
A3: Jeudi | B3: 44014 | C3: 1 | D3: 1 | E3: 1 | F3: 1 | G3: 1 | H3: 1
A4: Vendredi | B4: 44015 | C4: 0 | D4: 0 | E4: 0 | F4: 0 | G4: 0 | H4: 0
A5: Samedi | B5: 44016 | C5: 1 | D5: 1 | E5: 1 | F5: 1 | G5: 1 | H5: 1
A6: Dimanche | B6: 44017 | C6: 1 | D6: 1 | E6: 1 | F6: 1 | G6: 1 | H6: 1
A7: Lundi | B7: 44018 | C7: 1 | D7: 1 | E7: 1 | F7: 1 | G7: 1 | H7: 1
A8: Mardi | B8: 44019 | C8: 1 | D8: 1 | E8: 1 | F8: 1 | G8: 1 | H8: 1
A9: Mercredi | B9: 44020 | C9: 1 | D9: 1 | E9: 1 | F9: 1 | G9: 1 | H9: 1
A10: Jeudi | B10: 44021 | C10: 1 | D10: 1 | E10: 1 | F10: 1 | G10: 1 | H10: 1
A11: Vendredi | B11: 44022 | C11: 0 | D11: 0 | E11: 0 | F11: 0 | G11: 0 | H11: 0
A12: Samedi | B12: 44023 | C12: 1 | D12: 0 | E12: 1 | F12: 1 | G12: 1 | H12: 1
A13: Dimanche | B13: 44024 | C13: 1 | D13: 0 | E13: 0 | F13: 1 | G13: 1 | H13: 1
A14: Lundi | B14: 44025 | C14: 1 | D14: 0 | E14: 1 | F14: 1 | G14: 1 | H14: 0 | N14: Zehor | O14: Zoubida | P14: Amel | Q14: Karima | R14: Nouara | S14: Zahida
A15: Mardi | B15: 44026 | C15: 0 | D15: 1 | E15: 1 | F15: 1 | G15: 0 | H15: 0 | N15: 24 | O15: 22 | P15: 25 | Q15: 26 | R15: 23 | S15: 11
A16: Mercredi | B16: 44027 | C16: 0 | D16: 1 | E16: 1 | F16: 1 | G16: 0 | H16: 0 | N16: 1923 | O16: 1153 | P16: 962 | R16: 962 | S16: 1153
A17: Jeudi | B17: 44028 | C17: 1 | D17: 0 | E17: 1 | F17: 1 | G17: 1 | H17: 0 | N17: =N16*N15 -> 46152 | O17: =O16*O15 -> 25366 | P17: =P16*P15 -> 24050 | Q17: 15000 | R17: =R16*R15 -> 22126 | S17: =S16*S15 -> 12683 | T17: =SUM(N17:S17) -> 145377
A18: Vendredi | B18: 44029 | C18: 0 | D18: 0 | E18: 0 | F18: 0 | G18: 0 | H18: 0 | N18: 46200 | O18: 25400 | P18: 24000 | Q18: 15000 | R18: 22200 | S18: 12700 | T18: =SUM(N18:S18) -> 145500
A19: Samedi | B19: 44030 | C19: 1 | D19: 1 | E19: 1 | F19: 1 | G19: 1 | H19: 1
A20: Dimenche | B20: 44031 | C20: 1 | D20: 1 | E20: 1 | F20: 1 | G20: 0 | H20: 0
A21: Lundi | B21: 44032 | C21: 1 | D21: 1 | E21: 1 | F21: 1 | G21: 1 | H21: 0 | N21: 48000 | O21: 26400 | P21: 24000 | Q21: 15000 | R21: 23000 | S21: 13200 | T21: =SUM(N21:S21) -> 149600
A22: Mardi | B22: 44033 | C22: 1 | D22: 1 | E22: 1 | F22: 1 | G22: 1 | H22: 0
A23: Mercredi | B23: 44034 | C23: 1 | D23: 1 | E23: 1 | F23: 1 | G23: 1 | H23: 0
A24: Jeudi | B24: 44035 | C24: 1 | D24: 1 | E24: 1 | F24: 1 | G24: 1 | H24: 0
A25: Vendredi | B25: 44036 | C25: 0 | D25: 0 | E25: 0 | F25: 0 | G25: 0 | H25: 0
A26: Samedi | B26: 44037 | C26: 1 | D26: 1 | E26: 1 | F26: 1 | G26: 1 | H26: 0
A27: Dimanche | B27: 44038 | C27: 1 | D27: 1 | E27: 1 | F27: 1 | G27: 1 | H27: 0
A28: Lundi | B28: 44039 | C28: 1 | D28: 1 | E28: 1 | F28: 1 | G28: 1 | H28: 0
A29: Mardi | B29: 44040 | C29: 1 | D29: 1 | E29: 1 | F29: 1 | G29: 1 | H29: 0
A30: Mercredi | B30: 44041 | C30: 1 | D30: 1 | E30: 1 | F30: 1 | G30: 1 | H30: 1
A31: Jeudi | B31: 44042 | C31: 1 | D31: 1 | E31: 1 | F31: 0 | G31: 1 | H31: 0
A32: Vendredi | B32: 44043 | C32: 0 | D32: 0 | E32: 0 | F32: 0 | G32: 0 | H32: 0
B33: Total | C33: =SUM(C2:C32) -> 24 | D33: =SUM(D2:D32) -> 22 | E33: =SUM(E2:E32) -> 25 | F33: =SUM(F2:F32) -> 25 | G33: =SUM(G2:G32) -> 23 | H33: =SUM(H2:H32) -> 12
B34: Salaire/jour | C34: 1925 | D34: 1155 | E34: 962 | F34: 600 | G34: 965 | H34: 1155 | I34: =SUM(C34:H34) -> 6762
B35: SALAIRES | C35: =C34*C33 -> 46200 | D35: =D34*D33 -> 25410 | E35: =E34*E33 -> 24050 | F35: =F34*F33 -> 15000 | G35: =G34*G33 -> 22195 | H35: =H33*H34 -> 13860 | I35: =SUM(C35:H35) -> 146715

Sheet Charges
F3: Produit | G3: Quantité | H3: Prix | I3: Date d'achat
F4: Boites 36/07 | G4: 1 carton | H4: 850 | I4: 44013
F5: Boites 36/10 | G5: 1 carton | H5: 1000 | I5: 44013
F6: Boites 48/10 | G6: 2 cartons | H6: 2900 | I6: 44013
F7: Rouiba | G7: 1 fardeau | H7: 520 | I7: 44013
F8: Eau | G8: 5 fardeaux | H8: 775 | I8: 44013
F9: Candia choco | G9: 1 fardeau | H9: 630 | I9: 44013
F10: Coca cannette | G10: 1 | H10: 1450 | I10: 44013
F11: jus Ifruit | G11: 2 | H11: 920 | I11: 44013
F12: Limonade Slim | G12: 4 | H12: 1400 | I12: 44013
F13: Semoule Fine Mama | G13: 21*15kg | H13: 6900 | I13: 01/07/0/2020
F14: Maa ezhar | G14: 12 bouteills | H14: 660 | I14: 44013
F15: Semoule Moyenne Sim | G15: 10kg | H15: 480 | I15: 44013
F16: Fromage spéciale pizza | G16: 12.5kg | H16: 2500 | I16: 44013
F17: Tomate Conserve | G17: 12kg | H17: 2800 | I17: 44013
F18: Semoule Moyenne Sim 2kg | G18: 12kg | H18: 1020 | I18: 44013
F19: 3akeri | G19: 1kg | H19: 750 | I19: 44013
F20: Poivre Noir | G20: / | H20: 100 | I20: 44013
F21: Sanoudj | G21: 500g | H21: 400 | I21: 44013
F22: Fromage Berber | G22: 1 barre de 600g | H22: 350 | I22: 44013
F23: Vinegre | G23: 1 | H23: 100 | I23: 44013
F24: Sel | G24: 1 Fardeau | H24: 330 | I24: 44013
F25: Huile | G25: 9 Bidons de 5 litres | H25: 4815 | I25: 44013
F26: Semoule Fine Baraka 25kg | G26: 5 sachets | H26: 6000 | I26: 44013
F27: Semoule Extra Ben Hamadi Moyenne 25kg | G27: 5 Sachets | H27: 6750 | I27: 44013
F28: Semoule Moyenne Sim 10kg | G28: 10 sachets | H28: 4500 | I28: 44014
F29: Boites en plaqtiques pr Me9iret | G29: 1 fardeau de 50 pièces | H29: 750 | I29: 44014
F30: Semoule Fine Mama 10kg | G30: 5 sachets | H30: 2750 | I30: 44016
F31: Semoule Fine Moula 10kg | G31: 1 sachet | H31: 500 | I31: 44016
F32: Poulet Haché | G32: / | H32: 500 | I32: 44016
F33: Viande hachée | G33: / | H33: 500 | I33: 44016
F34: Transport semoule | G34: 1 | H34: 500 | I34: 44016
F35: Bessel | G35: 322 kg | H35: 8050 | I35: 44017
F36: Alumette | G36: 1 | H36: 50 | I36: 44017
F37: Viande hachée | G37: / | H37: 500 | I37: 44018
F38: Semoule Fine Moula 10kg | G38: 6 sachets | H38: 3000 | I38: 44019
F39: Semoule Fine Mama 10kg | G39: 4 sachets | H39: 2200 | I39: 44019
F40: huile 5 litres | G40: 10 | H40: 5300 | I40: 44020
F41: Détergents | G41: 3 | H41: 500 | I41: 44023
F42: Poulet | G42: 12 maurceaux blanc et cuisse | H42: 1900 | I42: 44024
F43: courgette | G43: 2.5kf | H43: 200 | I43: 44024
F44: carrote | G44: 1.5kg | H44: 150 | I44: 44024
F45: pomme de terre | G45: 1.5kg | H45: 150 | I45: 44024
F46: poids chiche | G46: 1kg | H46: 250 | I46: 44024
F47: Tomate fraiche | G47: 2 kg | H47: 100 | I47: 44024
F48: poivre | G48: 500g | H48: 100 | I48: 44024
F49: Poulet hachée | G49: / | H49: 500 | I49: 44025
F50: Viande hachée | G50: / | H50: 200 | I50: 44025
F51: fromage Gouda | G51: 500g | H51: 600 | I51: 44025
F52: fromage portion | G52: 1 boite de8 | H52: 100 | I52: 44025
F53: ouef | G53: 10 | H53: 100 | I53: 44025
F54: boites | G54: 5 | H54: 350 | I54: 44025
F55: Recheta | G55: 23kg | H55: 1900 | I55: 44025
F56: Bessel | G56: 7kg | H56: 350 | I56: 44025
F57: Bessel | G57: 20kg | H57: 500 | I57: 44025
F58: Sachets de congélation | G58: 50 | H58: 50 | I58: 44025
F59: Poulet hachée | G59: / | H59: 500 | I59: 44026
F60: Viande hachée | G60: / | H60: 500 | I60: 44026
F61: test et eau de javel+Thon | G61: 3 | H61: 450 | I61: 44026
F62: Alumette | G62: 1 | H62: 50 | I62: 44026
F63: Ppier Aluminium | G63: 180m | H63: 1400 | I63: 44027
F64: Viande hachée | G64: / | H64: 500 | I64: 44027
F65: Poulet hachée | G65: / | H65: 500 | I65: 44027
F66: Olive dénoyauté | G66: / | H66: 120 | I66: 44027
F67: paté fromage | G67: / | H67: 50 | I67: 44027
F68: curdent | G68: 1 | H68: 40 | I68: 44027
F69: Transport | G69: 1 | H69: 500 | I69: 44027
F70: Gateaux Souad | G70: 20/06-11/07 | H70: 26000 | I70: 44028
F71: miel | G71: 5kg | H71: 600 | I71: 44028
F72: louche, poche a douille, kessekass | G72: 3 | H72: 1080 | I72: 44028
F73: Semoule fine Mama | G73: 10sachets de 10kg | H73: 5000 | I73: 44028
F74: Transport | G74: 1 | H74: 500 | I74: 44028
F75: chocolat elwedjedane | G75: 2 boites de 250g | H75: 340 | I75: 44029
F76: optella 700g | G76: 1 boite | H76: 280 | I76: 44029
F77: Toffia caramel | G77: 1boite | H77: 200 | I77: 44029
F78: fleurial 250g | G78: 1 | H78: 65 | I78: 44029
F79: farine Sim | G79: 1kg | H79: 80 | I79: 44029
F80: gateau palmaru | G80: 1 | H80: 85 | I80: 44029
F81: gofferette Bimo vanille | G81: 1 | H81: 90 | I81: 44029
F82: Transport | G82: 1 | H82: 500 | I82: 44030
F83: Fanta | G83: 1 fardeau | H83: 500 | I83: 44030
F84: Ifruit jus | G84: 2 fardeaux | H84: 920 | I84: 44030
F85: Coca cannette | G85: 1 | H85: 1430 | I85: 44030
F86: Rouiba | G86: 1 fardeau | H86: 520 | I86: 44030
F87: eau petit | G87: 5 fardeaux | H87: 775 | I87: 44030
F88: eau grand | G88: 10 | H88: 1350 | I88: 44030
F89: Boite 08/06 | G89: 1 carton | H89: 850 | I89: 44030
F90: Boite 18/07 | G90: 1 carton | H90: 1100 | I90: 44030
F91: Boite 36/10 | G91: 1carton | H91: 1100 | I91: 44030
F92: liquissetes | G92: 2 | H92: 100 | I92: 44030
F93: vanille | G93: / | H93: 200 | I93: 44030
F94: Sucre | G94: 1 fardeau 10 | H94: 700 | I94: 44030
F95: farine Sim | G95: 1 fardeau 10 | H95: 580 | I95: 44030
F96: Semen Madina | G96: 3 boites de 1.8kg | H96: 1230 | I96: 44030
F97: Maizina | G97: 2kg | H97: 360 | I97: 44030
F98: Levure chimique | G98: 1 boite | H98: 380 | I98: 44030
F99: Harrissa | G99: un carton de 12 boites 1kg | H99: 2460 | I99: 44030
F100: Margarine Mani | G100: 1 carton de 24 boites | H100: 1150 | I100: 44030
F101: Miel 5kg | G101: 1 | H101: 590 | I101: 44030
F102: cousscouss | G102: 1kg | H102: 135 | I102: 44030
...

Sheet Salaires
H15: Nom | I15: Salaire | J15: Avance
G16: 1 | H16: Zehor | I16: =Pointage!C35*1 -> 46200 | J16: 46200
G17: 2 | H17: Karima | I17: =Pointage!F35*1 -> 15000 | J17: 15000
G18: 3 | H18: Amel | I18: =Pointage!E35*1 -> 24050 | J18: 24000
G19: 4 | H19: Nowara | I19: =Pointage!G35*1 -> 22195 | J19: 22200
G20: 5 | H20: Zoubida | I20: =Pointage!D35*1 -> 25410 | J20: 25400
G21: 6 | H21: Zahida | I21: =Pointage!H35*1 -> 13860 | J21: 14000
H22: TOTAL | I22: =SUM(I16:I21) -> 146715 | J22: =SUM(J16:J21) -> 146800
I23: =I22-J22 -> -85

Sheet Feuille 5
M6: Dette | N6: 77000
M7: Nadjet | N7: 3000
J8: 4 | M8: Islem | N8: 3000
M9: cash | N9: 73000
M10: Amel | N10: =N6-N7-N8-N9 -> -2000
M11: Sofiane | N11: 73000
I16: ;

Sheet Gateaux Souad 
H4: Date | I4: Gateau | J4: Quantité | K4: Prix unitaire | L4: Totale
H5: 44030 | I5: 7alewet taba3 | J5: 60 | K5: 25 | L5: =K5*J5 -> 1500
I6: Na9ache | J6: 45 | K6: 50 | L6: =K6*J6 -> 2250
I7: les amandies | J7: 40 | K7: 70 | L7: =K7*J7 -> 2800
H8: 44037 | I8: 7alwet taba3 | J8: 60 | K8: 25 | L8: 1500
I9: techarak | J9: 44 | K9: 40 | L9: =K9*J9 -> 1760
I10: ka3ek na9ach | J10: 44 | K10: 50 | L10: =J10*K10 -> 2200
I11: ka3ek na9ach | J11: 60 | K11: 50 | L11: 3000
I12: 7alwet taba3 | J12: 60 | K12: 25 | L12: 1500
I13: Makrout | J13: 30 | K13: 50 | L13: 1500
H26: Totale | L26: =SUM(L5:L25) -> 18010
H27: Versé | L27: 18000
H28: Reste à payer | L28: =L26-L27 -> 10
