Workbook

Sheet RECAP
B1: Date | C1: Recette juillet 2023 | D1: Recette | E1: Charges | F1: Salaire | G1: Loyer | H1: Net Profit | I1: Nb de jours | K1: Objectif | L1: juillet | M1: Bénéfice Moyen par jour | N1: Moyenne | O1: Moyenne salaire | P1: pourcentage du salaire vis à vis la recettte
A2: Mardi | B2: 45139 | C2: 20000 | D2: 56000 | I2: 1 | K2: 100000 | L2: 20000 | M2: =H33/I33 -> 5935.0118 | N2: =D33/I33 -> 55352.941 | P2: =O2/N2 -> 0
A3: Mercredi | B3: 45140 | C3: 30000 | D3: 45000 | I3: 1 | K3: 100000 | L3: 30000
A4: Jeudi | B4: 45141 | C4: 45000 | D4: 82000 | I4: 1 | K4: 100000 | L4: 45000 | M4: Moyenne des charges par jour | N4: Objectif
A5: Vendredi | B5: 45142 | C5: 48000 | D5: 50000 | I5: 1 | K5: 100000 | L5: 48000 | M5: =E33/I33 -> 28909.371 | N5: 100000
A6: Samedi | B6: 45143 | C6: 44000 | D6: 35000 | I6: 1 | K6: 100000 | L6: 44000 | M6: ²
A7: Dimanche | B7: 45144 | C7: 100000 | D7: 33000 | I7: 1 | K7: 100000 | L7: 100000
A8: Lundi | B8: 45145 | C8: 40000 | D8: 50000 | I8: 1 | K8: 100000 | L8: 40000 | M8: Cash restant | N8: Magasin
A9: Mardi | B9: 45146 | C9: 42000 | D9: 55000 | I9: 1 | K9: 100000 | L9: 42000 | M9: =D33-N9-E33-Salaire!K24 -> 173540.7 | N9: =O9*1 -> 40000 | O9: 40000
A10: Mercredi | B10: 45147 | C10: 31000 | D10: 40000 | I10: 1 | K10: 100000 | L10: 31000
A11: Jeudi | B11: 45148 | C11: 30000 | D11: 50000 | I11: 1 | K11: 100000 | L11: 30000 | M11: loyer
A12: Vendredi | B12: 45149 | C12: 48000 | D12: 30000 | I12: 1 | K12: 100000 | L12: 48000 | O12: La caisse : 35000 Da
A13: Samedi | B13: 45150 | C13: 76000 | D13: 140000 | I13: 1 | K13: 100000 | L13: 76000 | O13: Che7i7a: 5000Da
A14: Dimanche | B14: 45151 | C14: 100000 | D14: 50000 | I14: 1 | K14: 100000 | L14: 100000
A15: Lundi | B15: 45152 | C15: 75000 | D15: 40000 | I15: 1 | K15: 100000 | L15: 75000
A16: Mardi | B16: 45153 | C16: 93000 | D16: 70000 | I16: 1 | K16: 100000 | L16: 93000
A17: Mercredi | B17: 45154 | C17: 39000 | D17: 50000 | I17: 1 | K17: 100000 | L17: 39000 | M17: Différence mois de Juin
A18: Jeudi | B18: 45155 | C18: 50000 | D18: 65000 | I18: 1 | K18: 100000 | L18: 50000 | M18: =D33-C33 -> 30000
A19: Vendredi | B19: 45156 | K19: 100000 | L19: 71000 | M19: Différence objectif
A20: Samedi | B20: 45157 | K20: 100000 | L20: 120000 | M20: =K34-E34 -> 0
A21: Dimanche | B21: 45158 | K21: 100000 | L21: 49000 | M21: Différence du Totale
A22: Lundi | B22: 45159 | K22: 100000 | L22: 42000 | M22: =D33-L33 -> -939000
A23: Mardi | B23: 45160 | K23: 100000 | L23: 35000 | M23: Les vendredis
A24: Mercredi | B24: 45161 | K24: 100000 | L24: 74000 | M24: =E4+E11+E18+E25 -> 0
A25: Jeudi | B25: 45162 | K25: 100000 | L25: 40000
A26: Vendredi | B26: 45163 | K26: 100000 | L26: 40000 | M26: Cash réel
A27: Samedi | B27: 45164 | K27: 100000 | L27: 60000 | M27: 210000
A28: Dimanche | B28: 45165 | K28: 100000 | L28: 123000 | M28: rest à payer
A29: Lundi | B29: 45166 | K29: 100000 | L29: 115000
A30: Mardi | B30: 45167 | K30: 100000 | L30: 70000
A31: Mercredi | B31: 45168 | L31: 70000
A32: Jeudi | B32: 45169 | L32: 60000
C33: =SUM(C2:C32) -> 911000 | D33: =SUM(D2:D32) -> 941000 | E33: ='Les charges '!F212*1 -> 491459.3 | F33: =Salaire!J24*1 -> 238645.5 | G33: 110000 | H33: =D33-E33-F33-G33 -> 100895.2 | I33: =SUM(I2:I32) -> 17 | L33: =SUM(L2:L32) -> 1880000 | M33: =M9-M27-M31 -> -36459.3

Sheet Pointage 
B1: Date | C1: Lynda | D1: Hafida | E1: Djamila | F1: Youssera | G1: Thiziri | H1: Kenza | I1: Yasmine | J1: Nadia | K1: Farida | L1: Islem | M1: Samia | N1: Nora | O1: Nadjet | P1: Remarque
A2: Mardi | B2: 45139 | C2: 1 | D2: 1 | E2: 1 | F2: 0 | G2: 1 | H2: 1 | I2: 0 | J2: 1 | K2: 0 | L2: 0 | M2: 1 | N2: 1 | O2: 0 | P2: kenza djate à 13h
A3: Mercredi | B3: 45140 | C3: 1.5 | D3: 1 | E3: 1 | F3: 0 | G3: 1 | H3: 1 | I3: 1 | J3: 1 | K3: 1 | L3: 0 | M3: 1 | N3: 1 | O3: 0
A4: Jeudi | B4: 45141 | C4: 1.5 | D4: 1 | E4: 1 | F4: 0 | G4: 1 | H4: 1.25 | I4: 1.25 | J4: 1 | K4: 1 | L4: 0 | M4: 1 | N4: 1 | O4: 0 | P4: elyoum kharedjou à 14h puisque on avait des traveaux
A5: Vendredi | B5: 45142 | C5: 0 | D5: 1 | E5: 1 | F5: 0 | G5: 1 | H5: 1 | I5: 1 | J5: 1 | K5: 1 | L5: 0 | M5: 0 | N5: 1 | O5: 0 | P5: kenza et yasmine djaw bekeri we khalitehom youkhouredjou à 12h30
A6: Samedi | B6: 45143 | C6: 1 | D6: 1 | E6: 1 | F6: 0 | G6: 1 | H6: 1 | I6: 1 | J6: 0 | K6: 1 | L6: 0 | M6: 1 | N6: 1 | O6: 0
A7: Dimanche | B7: 45144 | C7: 1 | D7: 1 | E7: 1 | F7: 0 | G7: 1 | H7: 1 | I7: 1 | J7: 1 | K7: 1 | L7: 0 | M7: 1 | N7: 1 | O7: 0
A8: Lundi | B8: 45145 | C8: 1 | D8: 1 | E8: 1 | F8: 0 | G8: 1 | H8: 1 | I8: 1 | J8: 1 | K8: 1 | L8: 0 | M8: 1 | N8: 0 | O8: 0
A9: Mardi | B9: 45146 | C9: 1 | D9: 1 | E9: 0 | F9: 1 | G9: 0 | H9: 1 | I9: 1 | J9: 1 | K9: 1 | L9: 0 | M9: 1 | N9: 0 | O9: 0
A10: Mercredi | B10: 45147 | C10: 1 | D10: 1 | E10: 1 | F10: 1 | G10: 1 | H10: 1 | I10: 0 | J10: 1 | K10: 1 | L10: 0 | M10: 1 | N10: 0 | O10: 0
A11: Jeudi | B11: 45148 | C11: 1 | D11: 1 | E11: 1 | F11: 0 | G11: 1 | H11: 1 | I11: 0 | J11: 1 | K11: 1 | L11: 0 | M11: 1 | N11: 0 | O11: 0
A12: Vendredi | B12: 45149 | C12: 1 | D12: 1 | E12: 0 | F12: 0 | G12: 1 | H12: 1 | I12: 1 | J12: 0 | K12: 1 | L12: 0 | M12: 0 | N12: 0 | O12: 1
A13: Samedi | B13: 45150 | C13: 1 | D13: 1 | E13: 1 | F13: 1 | G13: 1 | H13: 1 | I13: 1 | J13: 1 | K13: 1 | L13: 0 | M13: 1 | N13: 0 | O13: 0
A14: Dimanche | B14: 45151 | C14: 1 | D14: 1 | E14: 1 | F14: 1 | G14: 1 | H14: 1 | I14: 0 | J14: 1 | K14: 1 | L14: 0 | M14: 1 | N14: 0 | O14: 0
A15: Lundi | B15: 45152 | C15: 1 | D15: 1 | E15: 1 | F15: 1 | G15: 1 | H15: 0 | I15: 0 | J15: 2 | K15: 1 | L15: 0 | M15: 1 | N15: 0 | O15: 0
A16: Mardi | B16: 45153 | C16: 1.5 | D16: 1 | E16: 1 | F16: 0 | G16: 1 | H16: 1 | I16: 1 | J16: 1 | K16: 1 | L16: 0 | M16: 1 | N16: 0 | O16: 0
A17: Mercredi | B17: 45154 | C17: 1 | D17: 1 | E17: 1 | F17: 1 | G17: 0 | H17: 1 | I17: 1 | J17: 1 | K17: 1 | L17: 0 | M17: 1 | N17: 0 | O17: 0
A18: Jeudi | B18: 45155 | C18: 0 | D18: 1 | E18: 0 | F18: 0 | G18: 1 | H18: 1 | I18: 1 | J18: 1 | K18: 1 | L18: 0 | M18: 1 | N18: 0 | O18: 1
A19: Vendredi | B19: 45156 | J19: 1
A20: Samedi | B20: 45157
A21: Dimanche | B21: 45158
A22: Lundi | B22: 45159
A23: Mardi | B23: 45160
A24: Mercredi | B24: 45161
A25: Jeudi | B25: 45162
A26: Vendredi | B26: 45163
A27: Samedi | B27: 45164
A28: Dimanche | B28: 45165
A29: Lundi | B29: 45166
A30: Mardi | B30: 45167
A31: Mercredi | B31: 45168
A32: Jeudi | B32: 45169
C33: =SUM(C2:C32) -> 16.5 | D33: =SUM(D2:D32) -> 17 | E33: =SUM(E2:E32) -> 14 | F33: =SUM(F2:F32) -> 6 | G33: =SUM(G2:G32) -> 15 | H33: =SUM(H2:H32) -> 16.25 | I33: =SUM(I2:I32) -> 12.25 | J33: =SUM(J2:J32) -> 17 | K33: =SUM(K2:K32) -> 16 | L33: 0 | M33: =SUM(M2:M32) -> 15 | N33: =SUM(N2:N32) -> 6 | O33: =SUM(O2:O32) -> 2
C34: 1223 | D34: 1400 | E34: 1223 | F34: 1223 | G34: 1000 | H34: 1100 | I34: 1100 | J34: 1000 | K34: 1400 | L34: 1000 | M34: 1100 | N34: 926 | O34: 1200
C35: =C33*C34 -> 20179.5 | D35: =D34*D33 -> 23800 | E35: =E34*E33 -> 17122 | F35: =F34*F33 -> 7338 | G35: =G34*G33 -> 15000 | H35: =H34*H33 -> 17875 | I35: =I34*I33 -> 13475 | J35: =J34*J33 -> 17000 | K35: =K33*K34 -> 22400 | L35: =L33*L34 -> 0 | M35: =M33*M34 -> 16500 | N35: =N33*N34 -> 5556 | O35: =O34*O33 -> 2400 | P35: =SUM(D35:I35) -> 94610

Sheet Les charges 
C2: Produit | D2: Quantité | E2: Prix unitaire | F2: Prix | G2: Date d'achat
C3: les barquettes | D3: 5 | E3: 90 | F3: =D3*E3 -> 450 | G3: 45135
C4: épice chakhechoukha | D4: 1 | E4: 500 | F4: =D4*E4 -> 500 | G4: 45134
C5: pate a filo | D5: 1 | E5: 250 | F5: =D5*E5 -> 250 | G5: 45130
C6: Huile Elio 5 litres | D6: 10 | E6: 600 | F6: =D6*E6 -> 6000 | G6: 45127
C7: eau 1,5litres | D7: 5 | E7: 200 | F7: =D7*E7 -> 1000 | G7: 45127
C8: semen Madina 1,8kg | D8: 10 | E8: 820 | F8: =D8*E8 -> 8200 | G8: 45127
C9: djeldjelan | D9: 1 | E9: 850 | F9: =D9*E9 -> 850 | G9: 45126
C10: cuisses de poulet | D10: 4 | E10: 150 | F10: =D10*E10 -> 600 | G10: 45126
C11: poche jetable | D11: 10 | E11: 35 | F11: =D11*E11 -> 350 | G11: 45126
C12: sucre glace | D12: 7 | E12: 110 | F12: =D12*E12 -> 770 | G12: 45126
C13: Maa zehar | D13: 12 | E13: 70 | F13: =D13*E13 -> 840 | G13: 45126
C14: 3akeri | D14: 1 | E14: 1500 | F14: =D14*E14 -> 1500 | G14: 45125
C15: Boite 48/07 | D15: 3 | E15: 1550 | F15: =D15*E15 -> 4650
C16: boite 48/010 | D16: 1 | E16: 2700 | F16: =D16*E16 -> 2700
C17: boite 24 | D17: 1 | E17: 1100 | F17: =D17*E17 -> 1100
C18: boite 18 | D18: 1 | E18: 1550 | F18: =D18*E18 -> 1550
C19: boite 12 | D19: 1 | E19: 1350 | F19: =D19*E19 -> 1350
C20: boite 8 | D20: 0 | E20: 1150 | F20: =D20*E20 -> 0
C21: halwet turk | D21: 1 | E21: 1150 | F21: =D21*E21 -> 1150 | G21: 45102
C22: semoule Fine Sahel et Bousmail 25kg | D22: 15 | E22: 1000 | F22: =E22*D22 -> 15000 | G22: 45078
C23: Eau mineral 0,5 litre | D23: 7 | E23: 200 | F23: =D23*E23 -> 1400 | G23: 45041
C24: Margarine Fleurial 500 | D24: 20 | E24: 202 | F24: =D24*E24 -> 4040 | G24: 45069
C25: chocolat wedjedene noisette | D25: 0 | E25: 260 | F25: =E25*D25 -> 0 | G25: 21/01/2023
C26: chocolat wedjedane blanc ,au lait et noir | D26: 9 | E26: 225 | F26: =E26*D26 -> 2025 | G26: 44947
C27: Soda Slim 33cl | D27: 4 | E27: 420 | F27: =D27*E27 -> 1680 | G27: 14/06/2023
C28: noix | D28: 0 | E28: 1500 | F28: =D28*E28 -> 0 | G28: 45116
C29: jus tchina 33cl | D29: 3 | E29: 500 | F29: =D29*E29 -> 1500 | G29: 45113
C30: Maiis | D30: 10 | E30: 250 | F30: =D30*E30 -> 2500 | G30: 45109
C31: Lait en poudre | D31: 10 | E31: 550 | F31: =D31*E31 -> 5500 | G31: 45109
C32: amandes | D32: 12 | E32: 1530 | F32: =D32*E32 -> 18360 | G32: 45109
C33: semoule moula grosse 2kg | D33: 9 | E33: 250 | F33: =D33*E33 -> 2250 | G33: 45109
C34: gherss | D34: 13 | E34: 240 | F34: =D34*E34 -> 3120 | G34: 45109
C35: Farine Sim 1kg | D35: 36 | E35: 75 | F35: =D35*E35 -> 2700 | G35: 45109
C36: cheddar | D36: 2 | E36: 2120 | F36: =D36*E36 -> 4240 | G36: 45109
C37: Hariissa | D37: 12 | E37: 185 | F37: =D37*E37 -> 2220 | G37: 45109
C38: fromage bidon 3,8 | D38: 1 | E38: 1400 | F38: =D38*E38 -> 1400 | G38: 45109
C39: fromage special pizza | D39: 1 | E39: 850 | F39: =D39*E39 -> 850 | G39: 45109
... C46: Levure chimique | D46: 1 | E46: 600 | F46: =D46*E46 -> 600 | G46: 45108
C47: leveure boulangère | D47: 7 | E47: 390 | F47: =E47*D47 -> 2730 | G47: 45057
C48: Margarine Fleurial 250g 40 boites | D48: 30 | E48: 85 | F48: =E48*D48 -> 2550 | G48: 44999
C49: semoule gros Moula 10kg | D49: 1 | E49: 1280 | F49: =E49*D49 -> 1280 | G49: 45004
C50: rechta | D50: 3 | E50: 130 | F50: =E50*D50 -> 390
C51: oeuf | D51: 1 | E51: 500 | F51: =E51*D51 -> 500 | G51: 45139
C52: sachets | D52: 1 | E52: 1400 | F52: =E52*D52 -> 1400 | G52: 45139
C53: bessel | D53: 50 | E53: 50 | F53: =E53*D53 -> 2500 | G53: 45139
C54: oeuf | D54: 3 | E54: 550 | F54: =E54*D54 -> 1650 | G54: 45139
C55: détergents | D55: 1 | E55: 1500 | F55: =E55*D55 -> 1500 | G55: 45139
C56: poulet haché+ blanc de poulet | D56: 2 | E56: 1000 | F56: =E56*D56 -> 2000 | G56: 45139
C57: olive noir vert et dénoyauté | D57: 6 | E57: 500 | F57: =E57*D57 -> 3000 | G57: 45139
C58: olive | D58: 1 | E58: 100 | F58: =E58*D58 -> 100 | G58: 45139
C59: salade et autres | D59: 1 | E59: 1650 | F59: =E59*D59 -> 1650 | G59: 45139
C60: keyar | D60: 1 | E60: 50 | F60: =E60*D60 -> 50 | G60: 45139
C61: tomate cerise orange | D61: 1 | E61: 200 | F61: =E61*D61 -> 200 | G61: 45139
C62: cannel+ épice | D62: 1 | E62: 500 | F62: =E62*D62 -> 500 | G62: 45139
... C90: Maiizina | D90: 5 | E90: 180 | F90: =E90*D90 -> 900 | G90: 45140
C91: 3akeri | D91: 1 | E91: 1200 | F91: =E91*D91 -> 1200 | G91: 45140 | H91: 0
C92: sac poubellle | D92: 1 | E92: 250 | F92: =E92*D92 -> 250 | G92: 45140
C93: sucre glace | D93: 18 | E93: 100 | F93: =E93*D93 -> 1800 | G93: 45140
C94: poulet haché+ blanc de poulet | D94: 2 | E94: 1000 | F94: =E94*D94 -> 2000 | G94: 45140
C95: rechta | D95: 7 | E95: 100 | F95: =E95*D95 -> 700 | G95: 45140
C96: deyoul | D96: 5 | E96: 110 | F96: =E96*D96 -> 550 | G96: 45140
C97: plateaux griwech | D97: 2 | E97: 400 | F97: =E97*D97 -> 800 | G97: 45140
C98: Huile Elio 5 litres | D98: 20 | E98: 600 | F98: =E98*D98 -> 12000 | G98: 45139
C99: margarine Fleuriel 500g | D99: 8 | E99: 192 | F99: =E99*D99 -> 1536 | G99: 45141
C100: viande hachée | D100: 1 | E100: 1800 | F100: =E100*D100 -> 1800 | G100: 45141
C101: viande morceaux | D101: 8 | E101: 450 | F101: =E101*D101 -> 3600 | G101: 45141
C102: les légumes | D102: 3 | E102: 250 | F102: =E102*D102 -> 750 | G102: 45141
C103: couscous | D103: 3 | E103: 150 | F103: =E103*D103 -> 450 | G103: 45141
... C112: épinards | D112: 3 | E112: 30 | F112: =E112*D112 -> 90 | G112: 45141
C113: salade | D113: 1 | E113: 200 | F113: 200 | G113: 45142
C114: viande | D114: 2 | E114: 500 | F114: =E114*D114 -> 1000 | G114: 45142
C115: cuisses de poulet | D115: 4 | E115: 175 | F115: =E115*D115 -> 700 | G115: 45142
C116: grand cuisses de poulet | D116: 4 | E116: 275 | F116: =E116*D116 -> 1100 | G116: 45142
C117: Brahim achat | D117: 1 | E117: 19000 | F117: =E117*D117 -> 19000 | G117: 45142
C118: couscous | D118: 1 | E118: 200 | F118: =E118*D118 -> 200 | G118: 45142
C119: hamissa | D119: 1 | E119: 200 | F119: =E119*D119 -> 200 | G119: 45142
C120: légumes | D120: 1 | E120: 1000 | F120: =E120*D120 -> 1000 | G120: 45142
C121: sac poubelle+ omo | D121: 2 | E121: 250 | F121: =E121*D121 -> 500 | G121: 45142
C122: barquettes | D122: 15 | E122: 60 | F122: =E122*D122 -> 900 | G122: 45142
C123: viande hachée | D123: 1 | E123: 1600 | F123: =E123*D123 -> 1600 | G123: 45142
C124: poiulet haché + blanc de poulet | D124: 2 | E124: 1000 | F124: =E124*D124 -> 2000 | G124: 45142
C125: rechta | D125: 10 | E125: 100 | F125: =E125*D125 -> 1000 | G125: 45142
... C187: isis | D187: 1 | E187: 250 | F187: =E187*D187 -> 250 | G187: 45238
C188: dettes légumes | E188: 3650 | F188: =E188*D188 -> 0 | G188: 45146
C189: nakkach | D189: 700 | E189: 60 | F189: =E189*D189 -> 42000 | G189: 45268
C190: Harrissa | D190: 2 | E190: 200 | F190: =E190*D190 -> 400 | G190: 45268
C191: Tomate | D191: 2 | E191: 240 | F191: =E191*D191 -> 480 | G191: 45268
C192: 3akeri | D192: 1 | E192: 1200 | F192: =E192*D192 -> 1200 | G192: 45268
C193: sucre glace | D193: 5 | E193: 125 | F193: =E193*D193 -> 625 | G193: 45151
C194: gherss | D194: 4 | E194: 300 | F194: =E194*D194 -> 1200 | G194: 45151
C195: eau 5 litres | D195: 4 | E195: 110 | F195: =E195*D195 -> 440 | G195: 45151
C196: bessel | D196: 40 | E196: 50 | F196: =E196*D196 -> 2000 | G196: 45152
C197: oeuf | D197: 2 | E197: 650 | F197: =E197*D197 -> 1300 | G197: 45152
C198: Hamissa | D198: 1 | E198: 200 | F198: =E198*D198 -> 200 | G198: 45152
C199: zebib | D199: 1 | E199: 1400 | F199: =E199*D199 -> 1400 | G199: 45152
C200: khalouta | D200: 1 | E200: 1000 | F200: =E200*D200 -> 1000 | G200: 45152
... C202: semoule FineSahel 25kg | D202: 15 | E202: 1000 | F202: =E202*D202 -> 15000 | G202: 45155
F203: =E203*D203 -> 0
F204: =E204*D204 -> 0
...

Sheet Salaire
I9: Nom | J9: Salaire | K9: Avance | L9: Salaire à payer
H10: 1 | I10: Sofiane | J10: 30000 | K10: 30000 | L10: =J10-K10 -> 0
H11: 2 | I11: Amel | J11: 30000 | K11: 30000 | L11: =J11-K11 -> 0
H12: 3 | I12: Lynda | J12: ='Pointage '!C35*1 -> 20179.5 | K12: 20500 | L12: =J12-K12 -> -320.5
H13: 4 | I13: Hafida | J13: ='Pointage '!D35*1 -> 23800 | K13: 24000 | L13: =J13-K13 -> -200
H14: 5 | I14: Djamila | J14: ='Pointage '!E35*1 -> 17122 | K14: 17500 | L14: =J14-K14 -> -378
H15: 6 | I15: Youssera | J15: ='Pointage '!F35*1 -> 7338 | K15: 3000 | L15: =J15-K15 -> 4338
H16: 7 | I16: Thiziri | J16: ='Pointage '!G35*1 -> 15000 | K16: 15000 | L16: =J16-K16 -> 0
H17: 8 | I17: Kenza | J17: ='Pointage '!H35*1 -> 17875 | K17: 18000 | L17: =J17-K17 -> -125
H18: 9 | I18: Yasmine | J18: ='Pointage '!I35*1 -> 13475 | K18: 13500 | L18: =J18-K18 -> -25
H19: 10 | I19: Nadia | J19: ='Pointage '!J35*1 -> 17000 | K19: 17000 | L19: =J19-K19 -> 0
H20: 11 | I20: Nadjet | J20: ='Pointage '!O35*1 -> 2400 | K20: 2500 | L20: =J20-K20 -> -100
H21: 12 | I21: Farida | J21: ='Pointage '!K35*1 -> 22400 | K21: 22500 | L21: =J21-K21 -> -100
H22: 13 | I22: Samia | J22: ='Pointage '!M35*1 -> 16500 | K22: 16500 | L22: =J22-K22 -> 0
H23: 14 | I23: Nora | J23: ='Pointage '!N35*1 -> 5556 | K23: 6000 | L23: =J23-K23 -> -444
I24: TOTAL | J24: =SUM(J10:J23) -> 238645.5 | K24: =SUM(K10:K23) -> 236000 | L24: =SUM(L10:L23) -> 2645.5
I25: =J24-K24 -> 2645.5 | L25: =J25-K25 -> 0

Sheet Feuille 5
G11: Mois de Février | H11: Mois de Mars | I11: Mois d'Avril | J11: Mois de Mai | K11: Mois de Jiun | L11: Mois de Juillet | M11: Mois d'Aout
F12: Recette | G12: 1400000 | H12: 1928000 | I12: 1488000 | J12: 1540000 | K12: 1577000 | L12: 1880000 | M12: 941000
F13: Charges | G13: 597000 | H13: 938000 | I13: 670000 | J13: 753000 | K13: 716000 | L13: 834000 | M13: 492000
F14: Salaires | G14: 413000 | H14: 360000 | I14: 335000 | J14: 347000 | K14: 331000 | L14: 416000 | M14: 239000
F15: Loyer | G15: 110000 | H15: 110000 | I15: 110000 | J15: 110000 | K15: 110000 | L15: 110000 | M15: 110000
F16: Profit Net | G16: 280000 | H16: 520000 | I16: 370000 | J16: =J12-J13-J14-J15 -> 330000 | K16: =K12-K13-K14-K15 -> 420000 | L16: 520000 | M16: 100000
