Workbook

Sheet RECAP
B1: Date | C1: Recette de Novembre 2022 | D1: Recette | E1: Charges | F1: Salaire | G1: Loyer | H1: Net Profit | I1: Nb de jours | K1: Objectif | L1: Novembre | M1: Bénéfice Moyen par jour | N1: Moyenne | O1: Moyenne salaire | P1: pourcentage du salaire vis à vis la recettte
A2: Jeudi | B2: 44896 | C2: 2000 | D2: 50000 | I2: 1 | K2: 0 | L2: 2000 | M2: =H33/I33 -> 20657.935 | N2: =D33/I33 -> 62709.677 | O2: =F33/I33 -> 12920.968 | P2: =O2/N2 -> 0.20604424
A3: vendredi | B3: 44897 | C3: 52000 | D3: 40000 | I3: 1 | K3: 70000 | L3: 52000
A4: samedi | B4: 44898 | C4: 69000 | D4: 30000 | I4: 1 | K4: 70000 | L4: 69000 | M4: Moyenne des charges par jour | N4: Objectif
A5: dimanche | B5: 44899 | C5: 60000 | D5: 27000 | I5: 1 | K5: 70000 | L5: 60000 | M5: =E33/I33 -> 25582.387 | N5: 70000
A6: lundi | B6: 44900 | C6: 60000 | D6: 39000 | I6: 1 | K6: 70000 | L6: 60000 | M6: ²
A7: mardi | B7: 44901 | C7: 45000 | D7: 41000 | I7: 1 | K7: 70000 | L7: 45000
A8: mercredi | B8: 44902 | C8: 40000 | D8: 44000 | I8: 1 | K8: 70000 | L8: 40000 | M8: Cash restant | N8: Magasin | O8: caisse | P8: cash en attente pour le récupérer =Dettes éxterieurs
A9: jeudi | B9: 44903 | C9: 53000 | D9: 66000 | I9: 1 | K9: 70000 | L9: 53000 | M9: =D33+N11-N9-E33-Salaires!I25 -> 1100446 | N9: =P9+O9 -> 135000 | O9: 55000 | P9: 80000
A10: vendredi | B10: 44904 | C10: 40000 | D10: 55000 | I10: 1 | K10: 70000 | L10: 40000 | P10: Sofiane: 120000+500000
A11: samedi | B11: 44905 | C11: 60000 | D11: 47000 | I11: 1 | K11: 70000 | L11: 60000 | M11: loyer | N11: 478000 | P11: 9000
A12: dimanche | B12: 44906 | C12: 110000 | D12: 40000 | I12: 1 | K12: 70000 | L12: 110000 | O12: l
A13: lundi | B13: 44907 | C13: 72000 | D13: 90000 | I13: 1 | K13: 70000 | L13: 72000 | O13: caisse: 15000 | P13: mokrani: 71000
A14: mardi | B14: 44908 | C14: 50000 | D14: 50000 | I14: 1 | K14: 70000 | L14: 50000 | O14: ccp 40000
A15: mercredi | B15: 44909 | C15: 71000 | D15: 40000 | I15: 1 | K15: 70000 | L15: 71000
A16: jeudi | B16: 44910 | C16: 73000 | D16: 70000 | I16: 1 | K16: 70000 | L16: 73000 | O16: Sofiane Loyer Magasin | P16: 620000
A17: vendredi | B17: 44911 | C17: 90000 | D17: 42000 | I17: 1 | K17: 70000 | L17: 90000 | M17: Différence mois de Novembre | O17: Bénéfice Mois de Novembre | P17: 540000
A18: samedi | B18: 44912 | C18: 60000 | D18: 62000 | I18: 1 | K18: 70000 | L18: 60000 | M18: =D33-C33 -> 278000 | O18: Amel | P18: 300000
A19: dimanche | B19: 44913 | C19: 70000 | D19: 47000 | I19: 1 | K19: 70000 | L19: 70000 | M19: Différence objectif | O19: Sofiane complément loyer + vidange +le reste du bénéfice | P19: 137000
A20: lundi | B20: 44914 | C20: 70000 | D20: 40000 | I20: 1 | K20: 70000 | L20: 70000 | M20: =K33-D33 -> 86000 | O20: 60000+10000+67000
A21: mardi | B21: 44915 | C21: 40000 | D21: 94000 | I21: 1 | K21: 70000 | L21: 40000
A22: mercredi | B22: 44916 | C22: 24000 | D22: 60000 | I22: 1 | K22: 70000 | L22: 24000
A23: jeudi | B23: 44917 | C23: 40000 | D23: 70000 | I23: 1 | K23: 70000 | L23: 40000 | M23: Les vendredis
A24: vendredi | B24: 44918 | C24: 90000 | D24: 90000 | I24: 1 | K24: 70000 | L24: 90000 | M24: =D5+D12+D19+D26 -> 144000 | O24: Cash réel avec le bénéfice du Mois de Novembre
A25: samedi | B25: 44919 | C25: 60000 | D25: 78000 | I25: 1 | K25: 70000 | L25: 60000
A26: dimanche | B26: 44920 | C26: 60000 | D26: 30000 | I26: 1 | K26: 70000 | L26: 100000 | M26: Cash réel | O26: =D33+N11+P17-O9-P16-P18-P19-P9-E33-Salaires!I25 -> 583446
A27: lundi | B27: 44921 | C27: 40000 | D27: 27000 | I27: 1 | K27: 70000 | L27: 40000 | M27: 326000
A28: mardi | B28: 44922 | C28: 30000 | D28: 55000 | I28: 1 | K28: 70000 | L28: 30000 | M28: rest à payer | N28: che7i7a
A29: mercredi | B29: 44923 | C29: 65000 | D29: 110000 | I29: 1 | K29: 70000 | L29: 65000 | M29: =M9-M27 -> 774446
A30: jeudi | B30: 44924 | C30: 40000 | D30: 110000 | I30: 1 | K30: 70000 | L30: 40000 | P30: =D33+N11+P17-O9-P9-P16-P18-P19-E33-Salaires!I25 -> 583446
A31: vendredi | B31: 44925 | C31: 30000 | D31: 160000 | I31: 1 | K31: 70000 | L31: 30000
A32: samedi | B32: 44926 | C32: 0 | D32: 140000 | I32: 1 | L32: 0
C33: =SUM(C2:C32) -> 1666000 | D33: =SUM(D2:D32) -> 1944000 | E33: ='Les charges '!H294*1 -> 793054 | F33: =Salaires!H25*1 -> 400550 | G33: 110000 | H33: =D33-G33-F33-E33 -> 640396 | I33: =SUM(I2:I32) -> 31 | K33: =SUM(K2:K32) -> 2030000 | L33: =SUM(L2:L32) -> 1706000
C35: Objectif | D35: 2030000 | E35: 700000 | F35: 310000 | G35: 110000 | H35: 910000
C36: Mois d'Octobre | D36: 1706000 | E36: 717000 | F36: 338000 | G36: 110000 | H36: 540000
M37: Cash restant
M38: =D33-E33-G33-O9-Salaires!I25 -> 592446
C39: La différence | D39: =D33-D36 -> 238000 | E39: =E33-E36 -> 76054 | F39: =F33-F36 -> 62550 | G39: =G33-G36 -> 0 | H39: =H33-H36 -> 100396

Sheet Pointage
B1: Date | C1: Soumia | D1: Hafida | E1: Wahiba | F1: vendeuse | G1: djamila | H1: Nadjia | I1: Yousera | J1: Lynda | K1: Kenza | L1: Fouzia | M1: SAmira | N1: Alia | O1: Yasmine | P1: Farida | Q1: Extra | S1: Remarque
A2: Jeudi | B2: 44896 | C2: 0 | D2: 1 | E2: 1 | F2: 0 | G2: 0 | H2: 0 | I2: 1 | J2: 1 | K2: 0 | L2: 1 | M2: 1 | N2: 1 | O2: 1 | P2: 1 | Q2: 0
A3: vendredi | B3: 44897 | C3: 0 | D3: 0 | E3: 0 | F3: 0 | G3: 1 | H3: 0 | I3: 0 | J3: 0 | K3: 1 | L3: 1 | M3: 0 | N3: 1.5 | O3: 1 | P3: 0 | Q3: 0
A4: samedi | B4: 44898 | C4: 0 | D4: 1 | E4: 1 | F4: 0 | G4: 1 | H4: 0 | I4: 1 | J4: 1 | K4: 1 | L4: 0 | M4: 1 | N4: 0 | O4: 1 | P4: 0 | Q4: 0
A5: dimanche | B5: 44899 | C5: 0 | D5: 1 | E5: 1 | F5: 1 | G5: 1 | H5: 0 | I5: 1 | J5: 1 | K5: 0.5 | L5: 1 | M5: 1 | N5: 1.5 | O5: 0 | P5: 0 | Q5: 1.5
A6: lundi | B6: 44900 | C6: 0 | D6: 1 | E6: 1 | F6: 1 | G6: 1 | H6: 1 | I6: 1 | J6: 1 | K6: 1 | L6: 1 | M6: 1 | N6: 1 | O6: 0 | P6: 0 | Q6: 0
A7: mardi | B7: 44901 | C7: 0 | D7: 1 | E7: 1 | F7: 1 | G7: 1 | H7: 1 | I7: 0 | J7: 1 | K7: 0 | L7: 0 | M7: 1 | N7: 1 | O7: 0 | P7: 0 | Q7: 0
A8: mercredi | B8: 44902 | C8: 0 | D8: 1 | E8: 1 | F8: 1 | G8: 0 | H8: 1 | I8: 1 | J8: 1 | K8: 0 | L8: 1 | M8: 1 | N8: 1 | O8: 0 | P8: 0 | Q8: 1.5
A9: jeudi | B9: 44903 | C9: 0 | D9: 1 | E9: 1 | F9: 1 | G9: 0 | H9: 0 | I9: 1 | J9: 1 | K9: 1 | L9: 1 | M9: 1 | N9: 1 | O9: 0 | P9: 0 | Q9: 0
A10: vendredi | B10: 44904 | C10: 0 | D10: 0 | E10: 0 | F10: 1 | G10: 1 | H10: 1 | I10: 1 | J10: 1 | K10: 0 | L10: 0 | M10: 0 | N10: 1 | O10: 1 | P10: 0 | Q10: 0
A11: samedi | B11: 44905 | C11: 1 | D11: 1 | E11: 1 | F11: 1 | G11: 1 | H11: 0.5 | I11: 1 | J11: 1 | K11: 0 | L11: 1 | M11: 0 | N11: 1 | O11: 0 | P11: 0 | Q11: 0
A12: dimanche | B12: 44906 | C12: 1 | D12: 1 | E12: 1 | F12: 1 | G12: 1 | H12: 0 | I12: 1 | J12: 1 | K12: 0 | L12: 1 | M12: 1 | N12: 1 | O12: 0 | P12: 0 | Q12: 0
A13: lundi | B13: 44907 | C13: 1 | D13: 1 | E13: 2 | F13: 0.5 | G13: 1 | H13: 1 | I13: 1 | J13: 1 | K13: 1 | L13: 2 | M13: 1 | N13: 0 | O13: 0 | P13: 0 | Q13: 0
A14: mardi | B14: 44908 | C14: 1 | D14: 1 | E14: 1 | F14: 1 | G14: 1 | H14: 1 | I14: 1 | J14: 1 | K14: 0 | L14: 0 | M14: 1 | N14: 0 | O14: 0 | P14: 0 | Q14: 0
A15: mercredi | B15: 44909 | C15: 1 | D15: 1 | E15: 1 | F15: 1 | G15: 0 | H15: 1 | I15: 1 | J15: 1 | K15: 0 | L15: 1 | M15: 1 | N15: 1,5 | O15: 1 | P15: 0 | Q15: 0
A16: jeudi | B16: 44910 | C16: 1 | D16: 1 | E16: 0 | F16: 1 | G16: 0 | H16: 1 | I16: 1 | J16: 1 | K16: 1 | L16: 1 | M16: 1 | N16: 1,5 | O16: 1 | P16: 0 | Q16: 0
A17: vendredi | B17: 44911 | C17: 0 | D17: 0 | E17: 0 | F17: 0 | G17: 0 | H17: 1 | I17: 0 | J17: 1 | K17: 0 | L17: 0 | M17: 1 | N17: 0 | O17: 1 | P17: 0 | Q17: 2
A18: samedi | B18: 44912 | C18: 1 | D18: 1 | E18: 1 | F18: 1 | G18: 0 | H18: 0 | I18: 0,5 | J18: 1 | K18: 0 | L18: 1 | M18: 1 | N18: 1,5 | O18: 0 | P18: 0 | Q18: 0
A19: dimanche | B19: 44913 | C19: 1 | D19: 1 | E19: 1 | F19: 1 | G19: 1 | H19: 0 | I19: 1 | J19: 1 | K19: 0 | L19: 1 | M19: 1 | N19: 1 | O19: 0 | P19: 0 | Q19: 0
A20: lundi | B20: 44914 | C20: 1 | D20: 1 | E20: 2 | F20: 1 | G20: 1 | H20: 0 | I20: 1 | J20: 1 | K20: 1 | L20: 1 | M20: 1 | N20: 1.5 | O20: 0 | P20: 0 | Q20: 0
A21: mardi | B21: 44915 | C21: 1 | D21: 1 | E21: 1 | F21: 0 | G21: 1 | H21: 0 | I21: 1 | J21: 1 | K21: 1 | L21: 1 | M21: 1 | N21: 0 | O21: 0 | P21: 0 | Q21: 0
A22: mercredi | B22: 44916 | C22: 0 | D22: 1 | E22: 2 | F22: 1 | G22: 0 | H22: 0 | I22: 1 | J22: 1 | K22: 0.5 | L22: 1.5 | M22: 1 | N22: 1.5 | O22: 0 | P22: 0 | Q22: 0
A23: jeudi | B23: 44917 | C23: 0 | D23: 1 | E23: 1 | F23: 0 | G23: 0 | H23: 0 | I23: 1 | J23: 2 | K23: 0.5 | L23: 0 | M23: 1 | N23: 1.5 | O23: 1 | P23: 0 | Q23: 0
A24: vendredi | B24: 44918 | C24: 0 | D24: 1 | E24: 0 | F24: 0 | G24: 1 | H24: 0 | I24: 1 | J24: 1 | K24: 1 | L24: 1 | M24: 1 | N24: 0 | O24: 1.5 | P24: 0 | Q24: 0
A25: samedi | B25: 44919 | C25: 0 | D25: 1 | E25: 0 | F25: 0 | G25: 1 | H25: 0 | I25: 0 | J25: 1.25 | K25: 1.25 | L25: 1 | M25: 1 | N25: 0 | O25: 1.5 | P25: 0 | Q25: 0
A26: dimanche | B26: 44920 | C26: 0 | D26: 1 | E26: 1 | F26: 1 | G26: 1 | H26: 0 | I26: 1 | J26: 0 | K26: 0 | L26: 1 | M26: 1 | N26: 0 | O26: 0 | P26: 1 | Q26: 0
A27: lundi | B27: 44921 | C27: 0 | D27: 1 | E27: 1 | F27: 1 | G27: 1 | H27: 0 | I27: 1 | J27: 0 | K27: 0 | L27: 0 | M27: 1 | N27: 0 | O27: 1 | P27: 1 | Q27: 0
A28: mardi | B28: 44922 | C28: 0 | D28: 1 | E28: 2 | F28: 1 | G28: 1 | H28: 0 | I28: 1 | J28: 2 | K28: 1 | L28: 1 | M28: 1 | N28: 0 | O28: 0 | P28: 1 | Q28: 0
A29: mercredi | B29: 44923 | C29: 0 | D29: 1 | E29: 1 | F29: 1 | G29: 1 | H29: 0 | I29: 1 | J29: 2 | K29: 1 | L29: 0 | M29: 2 | N29: 0 | O29: 1.5 | P29: 1 | Q29: 0
A30: jeudi | B30: 44924 | C30: 0 | D30: 1 | E30: 2 | F30: 1 | G30: 1 | H30: 0 | I30: 0 | J30: 1.5 | K30: 1.25 | L30: 1 | M30: 1 | N30: 0 | O30: 1.5 | P30: 1.5 | Q30: 0
A31: vendredi | B31: 44925 | C31: 0 | D31: 0 | E31: 2 | F31: 1 | G31: 2 | H31: 0 | I31: 0 | J31: 2 | K31: 1.5 | L31: 1.5 | M31: 1 | N31: 0 | O31: 1.5 | P31: 2 | Q31: 0
A32: samedi | B32: 44926 | C32: 0 | D32: 1 | E32: 2 | F32: 0,5 | G32: 2 | H32: 0 | I32: 1,5 | J32: 2 | K32: 2 | L32: 1,5 | M32: 3 | N32: 0 | O32: 2 | P32: 2 | Q32: 0
C33: =SUM(C2:C32) -> 10 | D33: =SUM(D2:D32) -> 27 | E33: =SUM(E2:E32) -> 32 | F33: =SUM(F2:F32) -> 21.5 | G33: =SUM(G2:G32) -> 24 | H33: =SUM(H2:H32) -> 9.5 | I33: =SUM(I2:I32) -> 23 | J33: =SUM(J2:J32) -> 33.75 | ... Q33: =SUM(Q2:Q32) -> 5
C34: 1000 | D34: 1400 | E34: 1200 | F34: 1000 | G34: 1200 | H34: 1000 | I34: 1150 | J34: 1200 | K34: 1000 | L34: 1200 | M34: 1000 | N34: 800 | O34: 1000 | P34: 1200 | Q34: 1000
C35: =C34*C33 -> 10000 | D35: =D34*D33 -> 37800 | E35: =E34*E33 -> 38400 | F35: =F34*F33 -> 21500 | G35: =G34*G33 -> 28800 | H35: =H34*H33 -> 9500 | I35: =I34*I33 -> 26450 | J35: =J34*J33 -> 40500 | ... Q35: =Q34*Q33 -> 5000 | S35: =SUM(C35:Q35) -> 340550

Sheet Les charges 
E2: Produit | F2: Quantité | G2: Prix unitaire | H2: Prix | I2: Date d'achat
E3: oeufs | F3: 3 | G3: 570 | H3: =F3*G3 -> 1710 | I3: 44896
E4: Deyoul | F4: 3 | G4: 110 | H4: =F4*G4 -> 330 | I4: 44896
E5: blanc de poulet + haché | F5: 7 | G5: 650 | H5: =F5*G5 -> 4550 | I5: 44896
E6: épinards | F6: 10 | G6: 30 | H6: =F6*G6 -> 300 | I6: 44896
E7: thym | F7: 5 | G7: 30 | H7: =F7*G7 -> 150 | I7: 44896
E8: rechta | F8: 7 | G8: 12 | H8: =F8*G8 -> 84 | I8: 44896
E9: légumes | F9: 5 | G9: 120 | H9: =F9*G9 -> 600 | I9: 44896
E10: détergents + couteau | F10: 1 | G10: 1400 | H10: =F10*G10 -> 1400 | I10: 44896
E11: les pilles | F11: 20 | G11: 50 | H11: =F11*G11 -> 1000 | I11: 44896
E12: sac poubelle | F12: 1 | G12: 250 | H12: =F12*G12 -> 250 | I12: 44896
E13: ma9ela | F13: 1 | G13: 5500 | H13: =F13*G13 -> 5500 | I13: 44896
E14: épice poulet | F14: 1 | G14: 200 | H14: =F14*G14 -> 200 | I14: 44896
... E20: bessel | F20: 50 | G20: 100 | H20: =F20*G20 -> 5000 | I20: 44896
E21: assila Madina | F21: 6 | G21: 750 | H21: =F21*G21 -> 4500 | I21: 24/11/2022
E22: fardeau semoule Moula 1kg | F22: 2 | G22: 1000 | H22: =F22*G22 -> 2000 | I22: 44887
E23: fardeau semoule Moula 2kg | F23: 3 | G23: 1500 | H23: =F23*G23 -> 4500 | I23: 44887
E24: semoule moyenne Amour | F24: 2 | G24: 1200 | H24: =F24*G24 -> 2400 | I24: 44887
E25: huiles 2 litres | F25: 8 | G25: 1416 | H25: =G25*F25 -> 11328 | I25: 44854
E26: huile 5 litres | F26: 50 | G26: 600 | H26: =F26*G26 -> 30000 | I26: 24/11/2022
E27: barquettes aluminium 1120 | F27: 50 | G27: 35 | H27: =G27*F27 -> 1750 | I27: 19/11/2022
E28: barquettes aluminium 2 compartiments | F28: 20 | G28: 36 | H28: =G28*F28 -> 720 | I28: 19/11/2022
E29: tofia 2kg | F29: 2 | G29: 950 | H29: =G29*F29 -> 1900 | I29: 19/11/2022
E30: sac croissant num24 | F30: 1 | G30: 900 | H30: =G30*F30 -> 900 | I30: 19/11/2022
E31: sac croissant num14 | F31: 1 | G31: 900 | H31: =G31*F31 -> 900 | I31: 19/11/2022
E32: papier aluminium | F32: 3 | G32: 2000 | H32: =G32*F32 -> 6000 | I32: 19/11/2022
E33: boites 48/10 50 | F33: 2 | G33: 2300 | H33: =G33*F33 -> 4600 | I33: 19/11/2022
E34: cheddar | F34: 1 | G34: 1950 | H34: =G34*F34 -> 1950 | I34: 19/11/2022
E35: fromage gouda | F35: 1 | G35: 2050 | H35: =G35*F35 -> 2050 | I35: 19/11/2022
E36: moul quiches | F36: 50 | G36: 12 | H36: =G36*F36 -> 600 | I36: 44880
E37: moul djouzia | F37: 50 | G37: 10 | H37: =G37*F37 -> 500 | I37: 44880
E38: les poches | F38: 1 | G38: 650 | H38: =G38*F38 -> 650 | I38: 44880
E39: nacré | F39: 2 | G39: 100 | H39: =G39*F39 -> 200 | I39: 44880
E40: semoule Fine Mama 25kg | F40: 3 | G40: 1000 | H40: =G40*F40 -> 3000 | I40: 44871
E41: farine Sim 1kg | F41: 1 | G41: 670 | H41: =G41*F41 -> 670 | I41: 20/11/2022
E42: chocolat blanc wedjedan | F42: 33 | G42: 225 | H42: =G42*F42 -> 7425 | I42: 20/11/2022
E43: levure nouara | F43: 1 | G43: 570 | H43: =G43*F43 -> 570 | I43: 20/11/2022
E44: sucre glace 1kg | F44: 7 | G44: 103 | H44: =G44*F44 -> 721 | I44: 20/11/2022
E45: thon | F45: 2 | G45: 1850 | H45: =G45*F45 -> 3700 | I45: 19/11/2022
E46: fromage bidon 2.2kg | F46: 2 | G46: 800 | H46: =G46*F46 -> 1600 | I46: 19/11/2022
E47: fromage bidon 3.8kg | F47: 1 | G47: 1320 | H47: =G47*F47 -> 1320 | I47: 19/11/2022
E48: sac transparent | F48: 2 | G48: 1140 | H48: =G48*F48 -> 2280 | I48: 44882
E49: sac croissant num24 | F49: 4 | G49: 1450 | H49: =G49*F49 -> 5800 | I49: 44878
E50: Thermo | F50: 2 | G50: 2600 | H50: =G50*F50 -> 5200 | I50: 44879
E51: sucre 25kg | F51: 3 | G51: 2750 | H51: =G51*F51 -> 8250 | I51: 44878
E52: Jus Tchina 33cl | F52: 4 | G52: 550 | H52: =G52*F52 -> 2200 | I52: 44878
E53: maa zehar | F53: 12 | G53: 65 | H53: =G53*F53 -> 780 | I53: 44876
E54: lait en poudre 500g | F54: 8 | G54: 530 | H54: =G54*F54 -> 4240 | I54: 44876
E55: Soda Slim 33cl | F55: 6 | G55: 420 | H55: =G55*F55 -> 2520 | I55: 44874
E56: Tomate conserve | F56: 12 | G56: 215 | H56: =G56*F56 -> 2580 | I56: 44872
E57: eau minéral lala khedidja 0.5litre | F57: 10 | G57: 200 | H57: =G57*F57 -> 2000 | I57: 44868
E58: canette pepes | F58: 3 | G58: 600 | H58: =G58*F58 -> 1800 | I58: 44868
E59: boite 08 100 | F59: 3 | G59: 1400 | H59: =G59*F59 -> 4200 | I59: 44868
... E110: riz | F110: 1 | G110: 250 | H110: =G110*F110 -> 250 | I110: 44724
E111: teliteli | F111: 1 | G111: 70 | H111: =G111*F111 -> 70 | I111: 44724 | J111: 1
E112: isis | F112: 1 | G112: 280 | H112: =G112*F112 -> 280 | I112: 44724
E113: javel | F113: 1 | G113: 300 | H113: =G113*F113 -> 300 | I113: 44724
E114: amande | F114: 22 | G114: 1500 | H114: =G114*F114 -> 33000 | I114: 44724
E115: quinquaillerie | F115: 1 | G115: 3250 | H115: =G115*F115 -> 3250 | I115: 44902
E116: rechta | F116: 10 | G116: 120 | H116: =G116*F116 -> 1200 | I116: 44902
E117: blanc de poulet | F117: 2 | G117: 700 | H117: =G117*F117 -> 1400 | I117: 44902
E118: cuisses | F118: 5 | G118: 160 | H118: =G118*F118 -> 800 | I118: 44902
E119: tomate fraiche | F119: 3 | G119: 100 | H119: =G119*F119 -> 300 | I119: 44902
E120: légumes | F120: 1 | G120: 400 | H120: =G120*F120 -> 400 | I120: 44902
E121: rechta | F121: 10 | G121: 100 | H121: =G121*F121 -> 1000 | I121: 44902
E122: épinards + herebes | F122: 10 | G122: 20 | H122: =G122*F122 -> 200 | I122: 44902
E123: boites temina | F123: 1 | G123: 350 | H123: =G123*F123 -> 350 | I123: 44902
... E187: sachets | F187: 2 | G187: 300 | H187: =G187*F187 -> 600 | I187: 44908
E188: Farine 25kg | F188: 1 | G188: 650 | H188: =G188*F188 -> 650 | I188: 14/12/2022
E189: oeufs | F189: 4 | G189: 650 | H189: =G189*F189 -> 2600 | I189: 14/12/2022
E190: farine Sim 1kg | F190: 5 | G190: 680 | H190: =G190*F190 -> 3400 | I190: 14/12/2022
E191: chocolat blanc wedjedan | F191: 6 | G191: 230 | H191: =G191*F191 -> 1380 | I191: 14/12/2022
E192: crème fraiche | F192: 4 | G192: 330 | H192: =G192*F192 -> 1320 | I192: 14/12/2022
E193: miel | F193: 4 | G193: 770 | H193: =G193*F193 -> 3080 | I193: 14/12/2022
E194: sucre glace 1kg | F194: 12 | G194: 115 | H194: =G194*F194 -> 1380 | I194: 14/12/2022
E195: isis | F195: 2 | G195: 300 | H195: =G195*F195 -> 600 | I195: 14/12/2022
E196: bessel | F196: 23 | G196: 100 | H196: =G196*F196 -> 2300 | I196: 14/12/2022
E197: rechta | F197: 5 | H197: =G197*F197 -> 0 | I197: 14/12/2022
E198: deyoul | F198: 8 | G198: 100 | H198: =G198*F198 -> 800 | I198: 14/12/2022
E199: chakhechoukhate defer | F199: 1 | G199: 250 | H199: =G199*F199 -> 250 | I199: 14/12/2022
E200: poulet haché et blanc de poulet | F200: 2 | H200: =G200*F200 -> 0 | I200: 13/12/2022
E201: cuisse | F201: 1 | H201: =G201*F201 -> 0 | I201: 13/12/2022
E202: epice poulet | G202: 200 | H202: =G202*F202 -> 0 | I202: 13/12/2022
E203: poulet + rechta | H203: =G203*F203 -> 0
E204: tomate fraiche | F204: 3 | G204: 90 | H204: =G204*F204 -> 270 | I204: 13/12/2022
E205: bessel | F205: 100 | G205: 100 | H205: =G205*F205 -> 10000 | I205: 44910
E206: rechta | F206: 25 | H206: =G206*F206 -> 0 | I206: 44911
E207: storm | F207: 1 | G207: 1000 | H207: =G207*F207 -> 1000 | I207: 44911
H208: =G208*F208 -> 0 | I208: 44911
E209: viande morceaux | F209: 8 | H209: =G209*F209 -> 0 | I209: 44911
E210: Hamissa | F210: 3 | G210: 200 | H210: =G210*F210 -> 600 | I210: 44911
E211: légumes marché | F211: 1 | G211: 1000 | H211: =G211*F211 -> 1000 | I211: 17/12/2022
E212: Ka3ek nakache | F212: 400 | G212: 50 | H212: =G212*F212 -> 20000 | I212: 17/12/2022
E213: leben | F213: 2 | G213: 140 | H213: =G213*F213 -> 280 | I213: 17/12/2022
E214: couscouss | F214: 1 | G214: 190 | H214: =G214*F214 -> 190 | I214: 17/12/2022
E215: fromage | F215: 4 | G215: 350 | H215: =G215*F215 -> 1400 | I215: 18/12/2022
E216: pate | F216: 1 | G216: 100 | H216: =G216*F216 -> 100 | I216: 18/12/2022
E217: semouel sahel 25kg | F217: 1 | G217: 1000 | H217: =G217*F217 -> 1000 | I217: 18/12/2022
E218: semoule Moyenne Moula | F218: 8 | G218: 250 | H218: =G218*F218 -> 2000 | I218: 18/12/2022
E219: sel | F219: 1 | G219: 400 | H219: =G219*F219 -> 400 | I219: 18/12/2022
...

Sheet Salaires
G7: Nom | H7: Salaire | I7: Avance | J7: Salaire à payer
F8: 1 | G8: Sofiane | H8: 30000 | I8: 30000 | J8: =H8-I8 -> 0 | K8: 15000+10000+5000
F9: 2 | G9: Amel | H9: 30000 | I9: 30000 | J9: =H9-I9 -> 0
F10: 3 | G10: Kenza | H10: =Pointage!K35*1 -> 18500 | I10: 18500 | J10: =H10-I10 -> 0
F11: 4 | G11: Hafida | H11: =Pointage!D35*1 -> 37800 | I11: 38000 | J11: =H11-I11 -> -200 | K11: 5000+2000+500
F12: 5 | G12: Wahiba | H12: =Pointage!E35*1 -> 38400 | I12: 38500 | J12: =H12-I12 -> -100
F13: 6 | G13: Vendeuse | H13: =Pointage!F35*1 -> 21500 | I13: 21500 | J13: =H13-I13 -> 0
F14: 7 | G14: Djamila | H14: =Pointage!G35*1 -> 28800 | I14: 29000 | J14: =H14-I14 -> -200
F15: 8 | G15: Nadjia | H15: =Pointage!H35*1 -> 9500 | I15: 9500 | J15: =H15-I15 -> 0
F16: 9 | G16: Yousera | H16: =Pointage!I35*1 -> 26450 | I16: 26500 | J16: =H16-I16 -> -50 | K16: 5000+5000
F17: 10 | G17: lynda | H17: =Pointage!J35*1 -> 40500 | I17: 40500 | J17: =H17-I17 -> 0
F18: 11 | G18: Alia | H18: =Pointage!N35*1 -> 13200 | I18: 5000 | J18: =H18-I18 -> 8200
F19: 12 | G19: Samira | H19: =Pointage!M35*1 -> 31000 | I19: 31000 | J19: =H19-I19 -> 0 | K19: 1000+1000+29000
F20: 13 | G20: Fouzia | H20: =Pointage!L35*1 -> 28800 | I20: 29000 | J20: =H20-I20 -> -200
F21: 14 | G21: Yasmine | H21: =Pointage!O35*1 -> 18500 | I21: 18500 | J21: =H21-I21 -> 0
F22: 15 | G22: Soumia | H22: =Pointage!C35*1 -> 10000 | I22: 10000 | J22: =H22-I22 -> 0
F23: 16 | G23: Farida | H23: =Pointage!P35*1 -> 12600 | I23: 13000 | J23: =H23-I23 -> -400
F24: 17 | G24: Extra | H24: =Pointage!Q35*1 -> 5000 | I24: 5000 | J24: =H24-I24 -> 0 | K24: 1500+1500+2000
G25: TOTAL | H25: =SUM(H8:H24) -> 400550 | I25: =SUM(I8:I24) -> 393500 | J25: =SUM(J8:J24) -> 7050
G26: =H25-I25 -> 7050 | J26: =H26-I26 -> 0

Sheet Feuille 5
