Workbook

Sheet RECAP
B1: Date | C1: Recette de Janvier | D1: Recette | E1: Charges | F1: Salaire | G1: Loyer | H1: Net Profit | I1: Nb de jours | K1: Janvier
A2: Lundi | B2: 44228 | C2: 26000 | D2: 39000 | I2: 1 | K2: 26000 | L2: Moyenne
A3: Mardi | B3: 44229 | C3: 30000 | D3: 38000 | I3: 1 | K3: 30000 | L3: =D31/I31 -> 37392.857
A4: Mercredi | B4: 44230 | C4: 27000 | D4: 34000 | I4: 1 | K4: 27000
A5: Jeudi | B5: 44231 | C5: 27000 | D5: 53000 | I5: 1 | K5: 27000 | L5: 47000
A6: Vendredi | B6: 44232 | C6: 48000 | D6: 45000 | I6: 1 | K6: 48000
A7: Samedi | B7: 44233 | C7: 33000 | D7: 35000 | I7: 1 | K7: 33000
A8: Dimanche | B8: 44234 | C8: 63000 | D8: 27000 | I8: 1 | K8: 63000
A9: Lundi | B9: 44235 | C9: 54000 | D9: 32000 | I9: 1 | K9: 54000
A10: Mardi | B10: 44236 | C10: 46000 | D10: 47000 | I10: 1 | K10: 46000
A11: Mercredi | B11: 44237 | C11: 61000 | D11: 56000 | I11: 1 | K11: 61000
A12: Jeudi | B12: 44238 | C12: 92000 | D12: 46000 | I12: 1 | K12: 92000
A13: Vendredi | B13: 44239 | C13: 58000 | D13: 43000 | I13: 1 | K13: 58000
A14: Samedi | B14: 44240 | C14: 39000 | D14: 48000 | I14: 1 | K14: 39000 | L14: Cash restant | M14: Magasin | O14: Différence mois de Janvier
A15: Dimanche | B15: 44241 | C15: 41000 | D15: 28000 | I15: 1 | K15: 41000 | L15: =D31+Charges!G248-M15-E31-'Salaires '!K23 -> 514628 | M15: 25000 | O15: =D31-C31 -> -147000
A16: Lundi | B16: 44242 | C16: 28000 | D16: 33000 | I16: 1 | K16: 28000
A17: Mardi | B17: 44243 | C17: 28000 | D17: 27000 | I17: 1 | K17: 28000 | M17: 19450 | N17: caisse | O17: 497600
A18: Mercredi | B18: 44244 | C18: 28000 | D18: 33000 | I18: 1 | K18: 28000 | M18: 5550 | N18: Sifou | O18: 310000 | P18: cash
A19: Jeudi | B19: 44245 | C19: 39000 | D19: 54000 | I19: 1 | K19: 39000 | O19: 2000 | P19: Storm Sofiane
A20: Vendredi | B20: 44246 | C20: 50000 | D20: 48000 | I20: 1 | K20: 50000 | O20: 15000 | P20: ElAzehar
A21: Samedi | B21: 44247 | C21: 36000 | D21: 20000 | I21: 1 | K21: 36000 | O21: 5000 | P21: ménage bureau
A22: Dimanche | B22: 44248 | C22: 25000 | D22: 20000 | I22: 1 | K22: 25000 | O22: 20000 | P22: cash chez Sofiane
A23: Lundi | B23: 44249 | C23: 30000 | D23: 30000 | I23: 1 | K23: 30000 | O23: 91100 | P23: magasin+charges de Mars
A24: Mardi | B24: 44250 | C24: 32000 | D24: 21000 | I24: 1 | K24: 32000 | O24: =O17-O18-O19-O20-O21-O22-O23 -> 54500
A25: Mercredi | B25: 44251 | C25: 40000 | D25: 35000 | I25: 1 | K25: 40000
A26: Jeudi | B26: 44252 | C26: 46000 | D26: 38000 | I26: 1 | K26: 46000
A27: Vendredi | B27: 44253 | C27: 80000 | D27: 43000 | I27: 1 | K27: 80000
A28: Samedi | B28: 44254 | C28: 34000 | D28: 34000 | I28: 1 | K28: 34000
A29: Dimanche | B29: 44255 | C29: 36000 | D29: 40000 | I29: 1 | K29: 36000
C30: 17000 | K30: 17000
B31: Total | C31: =SUM(C2:C30) -> 1194000 | D31: =SUM(D2:D30) -> 1047000 | E31: =Charges!G247*1 -> 499172 | F31: ='Salaires '!J23*1 -> 197704 | G31: 50000 | H31: =D31+Charges!G248-E31-F31-G31 -> 320124 | I31: =SUM(I2:I30) -> 28 | K31: =SUM(K2:K30) -> 1194000 | O31: 40000 | P31: le magasin me doit
C33: Objectif | D33: 1365000 | E33: 500000 | F33: 215000 | G33: 50000 | H33: 600000
C34: Mois de Janvier | D34: 1194000 | E34: 468000 | F34: 215000 | G34: 50000 | H34: 480000
D36: =D33-D31 -> 318000 | E36: =E33-E31 -> 828 | F36: =F33-F31 -> 17296 | G36: =G33-G31 -> 0 | H36: =H33-H31 -> 279876

Sheet Charges
D3: Produit | E3: Quantité | F3: Prix unitaire | G3: Prix | H3: Date d'achat
D4: Semoule moyenne SIM 10kg | E4: 10 | F4: 410 | G4: 4100 | H4: 44228
D5: semoule moyenne Sim 2kg | E5: 2fardeaux de 12kg | F5: 930 | G5: 1860 | H5: 44228
D6: Farine Mama | E6: 5 fardeaux | F6: 680 | G6: 3400 | H6: 44228
D7: Sucre | E7: 1 fardeau | F7: 74 | G7: 740 | H7: 44228
D8: sel | E8: 3 fardeau | F8: 21.330 | G8: 960 | H8: 44228
D9: maa zehar | E9: 1 carton | F9: 50 | G9: 600 | H9: 44228
D10: harrissa | E10: 1 carton de 12kg | F10: 196 | G10: 2352 | H10: 44228
D11: maizina | E11: 5kg | F11: 170 | G11: 850 | H11: 44228
D12: sachets | E12: 2 | F12: 50 | G12: 100 | H12: 44228
D13: livraison | E13: 1 | F13: 1000 | G13: 1000 | H13: 44228
D14: pate d'arome citron | E14: 1 | F14: 800 | G14: 800 | H14: 44228
D15: sucre glace | E15: 1 fardeau de 16kg | F15: 77 | G15: 1232 | H15: 44248
D16: sac 25 | E16: 1 | F16: 1650 | G16: 1650 | H16: 44248 | J16: Magasin
D17: sac à pain | E17: 12 | F17: 50 | G17: 600 | H17: 44228 | J17: éléctricien | K17: 1 | L17: 1000 | M17: 44248
D18: plateau | E18: 2 | F18: 100 | G18: 200 | H18: 44228 | J18: resort du rideau | K18: 2 | L18: 15000 | M18: 44234
D19: Ka3ek nakach | E19: 200 | F19: 50 | G19: 10000 | H19: 44228 | J19: réparation rideau | K19: 1 | L19: 2000 | M19: 44233
D20: Baghrir | F20: 40et 45 | G20: 20000 | H20: 44228 | J20: Balance | K20: 1 | L20: 2000 | M20: 44245
D21: huile | E21: 16 bidons de 5 litres | F21: 535 | G21: 8560 | H21: 44228
D22: Margarine Mani | E22: 2 cartons de 24 boites 500g | F22: 125 | G22: 6000 | H22: 44228
D23: Tomate conserve | E23: 1 carton de 12kg | F23: 160 | G23: 1920 | H23: 44228
D24: miel | E24: 4 bidons de 5kg | F24: 600 | G24: 2400 | H24: 44228
D25: fromage spécial pizza | E25: 13kg | F25: 240 | G25: 3120 | H25: 44228 | J25: Total | L25: =SUM(L17:L24) -> 20000
D26: vinaigre | E26: 1 fardeau de 10 litres | F26: 55 | G26: 550 | H26: 44228
D27: oeufs | E27: 3 plateaux | F27: 330 | G27: 1000 | H27: 44228
D28: Boites 08/07 | E28: 2 cartons | F28: 870 | G28: 1740 | H28: 44228
D29: Boites 48/10 | E29: 2 cartons | F29: 1550 | G29: 3100 | H29: 44228
D30: Boites 36/10 | E30: 2 cartons | F30: 1150 | G30: 2300 | H30: 44228
D31: Boites 36/07 | E31: 2 cartons | F31: 900 | G31: 1800 | H31: 44228
D32: Tofia | E32: 1 boite de 3kg | F32: 850 | G32: 850 | H32: 44228
D33: Levure Nouara | E33: 1 boite | F33: 430 | G33: 430 | H33: 44228
D34: Sacs 06 | E34: 1 | F34: 350 | G34: 350 | H34: 44228
D35: quissettes N°10 | E35: un fardeau | F35: 1400 | G35: 1400 | H35: 44228
D36: viande hachée | E36: / | F36: 500 | G36: 500 | H36: 44228
D37: rechta | E37: 30kg | F37: 100 | G37: 3000 | H37: 44228
D38: viande +poulet hachées | E38: 3 | F38: 1500 | G38: 1500 | H38: 44228
D39: papier alumium +papier torchan | E39: 2 | F39: 1650 | G39: 1650 | H39: 44228
D40: viande | E40: 5 | F40: 300 | G40: 1500 | H40: 44228
D41: na3ena3 yabess | E41: 500g | F41: 1000 | G41: 500 | H41: 44228
D42: cuisses+blanc | E42: 6 | F42: / | G42: 850 | H42: 44228
D43: boites 1185/1065/08/07 | E43: 12+10+20 | F43: 40+25+10 | G43: 1100 | H43: 44228
D44: Légumes | E44: 5 | F44: 600 | G44: 600 | H44: 44228
D45: Semoule Mama 25kg | E45: 5sachets | F45: 1300 | G45: 6500 | H45: 44228
D46: Semoule Mama 2kg | E46: 20 fardeaux | F46: 1200 | G46: 24000 | H46: 44228
D47: Amandes | E47: 6kg | F47: 1400 | G47: 8400 | H47: 44228
D48: légumes | E48: 6kg | F48: / | G48: 600 | H48: 44228
D49: cuisses+poulet hachée | E49: 5+1kg | F49: 120+500 | G49: 1100 | H49: 44228
D50: viande hachée | E50: 300 | F50: 1500 | G50: 500 | H50: 44228
D51: teliteli | E51: 2 | F51: 100 | G51: 200 | H51: 44228
D52: les herbes | E52: 10 | F52: 30 | G52: 300 | H52: 44228
D53: cuisses | E53: 7 | F53: 70 | G53: 490 | H53: 44228
D54: bessel | E54: 20kg | F54: 50 | G54: 1000 | H54: 44228
D55: légumes | E55: 6kg | F55: 100 | G55: 650 | H55: 44228
D56: 7alewet turk,chocolat blanc,pistache,cawcaw | E56: 5 | F56: / | G56: 1400 | H56: 44228
D57: tomate fraiche | E57: 10kg | F57: 40 | G57: 400 | H57: 44228
D58: transport marchandise | E58: 1 | F58: 500 | G58: 500 | H58: 44228
D59: plats en argile | E59: 2 | F59: 400 | G59: 800 | H59: 44228
D60: Ka3ek nakach | E60: 140 | F60: 50 | G60: 7000 | H60: 44228
D61: barquettes1065 | E61: 100 | F61: 23 | G61: 2300 | H61: 44228
D62: barquettes 1185 | E62: 4 | F62: 40 | G62: 160 | H62: 44228
D63: boites blanches | E63: 50 | F63: 12 | G63: 600 | H63: 44228
D64: herbes | E64: 7 | F64: 30 | G64: 200 | H64: 44228
D65: lentilles | E65: 2kg | F65: 150 | G65: 300 | H65: 44228
D66: huile | E66: 48 bidons de 5 litres | F66: 535 | G66: 25700 | H66: 44228
D67: transport zehor+zoubida | E67: 2 | F67: 1500 | G67: 1500 | H67: 44229
D68: semoule baraka 5kg | E68: 1 | F68: 370 | G68: 370 | H68: 44230
D69: yaourt | E69: 5 | F69: 20 | G69: 100 | H69: 44230
D70: yaourt | E70: 6 | F70: 15 | G70: 90 | H70: 44230
D71: rechta | E71: 4kg | F71: 100 | G71: 400 | H71: 44230
D72: deyoul | E72: 2 | F72: 80 | G72: 160 | H72: 44230
D73: isis savon liquide | E73: 1 | F73: 100 | G73: 100 | H73: 44230
D74: semoule | E74: 23 fardeaux | F74: 1200 | G74: 27600 | H74: 44231
D75: oeufs | E75: 1 plateau | F75: 400 | G75: 400 | H75: 44231
D76: viande hachée | E76: / | F76: 1500 | G76: 600 | H76: 44231
D77: amandes | E77: 1kg | F77: 2000 | G77: 2000 | H77: 44231
D78: rechta | E78: 20kg | F78: 100 | G78: 2000 | H78: 44231
D79: Tansport | E79: 1 | F79: 500 | G79: 500 | H79: 44231
D80: tomate | E80: 11kg | F80: 45 | G80: 500 | H80: 44233
D81: bessel | E81: 18kg | F81: 55 | G81: 1000 | H81: 44233
D82: rechta | E82: 20kg | F82: 100 | H82: 44233
D83: Transport | E83: 1 | F83: 500 | G83: 500 | H83: 44233
D84: Ka3ek nakach 21/31/04/06 | E84: 368 | F84: 50 | G84: 18400 | H84: 44233
D85: ka3ek nakach vide | E85: 12 | F85: 30 | G85: 360 | H85: 44233
D86: beniwen | E86: 40 | H86: 44233
D87: boites 36/07 | E87: fardeau de 50 | F87: 21 | G87: 1050 | H87: 44233
D88: Transport Zehor | E88: 2 | F88: 1000 | G88: 2000 | H88: 44233
D89: légumes et herbes | E89: 6 | F89: / | G89: 300 | H89: 44234
D90: boissons: coca canette, coca, Rouiba,ifruit, hamoud, eau | E90: 12 | F90: / | G90: 4950 | H90: 44234
D91: sucre cristalisé | E91: 1 fardeau de 10kg | F91: 74 | G91: 740 | H91: 44234
D92: maa zehar | E92: 1 carton de 12 | F92: 50 | G92: 600 | H92: 44234
D93: semen Madina | E93: 4 de1.8kg | F93: 460 | G93: 1840 | H93: 44234
D94: hrissa 1kg cab | E94: 1 carton de 12kg | F94: 198 | G94: 2376 | H94: 44234
D95: Margarine Mani | E95: 1 | F95: 123 | G95: 2952 | H95: 44234
D96: Farine Sim | E96: 10kg | F96: 53 | G96: 530 | H96: 44234
D97: Nouara | E97: 1 | F97: 450 | G97: 450 | H97: 44234
D98: 3akeri | E98: 1kg | F98: 650 | G98: 650 | H98: 44234
D99: javel | E99: 1 | F99: 170 | G99: 170 | H99: 44234
D100: isis savon liquide | E100: 1 | F100: 380 | G100: 380 | H100: 44234
D101: Aluminium | E101: 1 | F101: 1200 | G101: 1200 | H101: 44234
D102: amandes | E102: 500g | F102: 2200 | G102: 1100 | H102: 44234
...

Sheet Pointage
B1: Date | C1: Zehor | D1: Zoubida | E1: Nadjet | F1: Hadjer | G1: Amel | H1: Soumia | I1: Hafida | J1: Karima | K1: Nouara | L1: Zahida | M1: Remarque
A2: Lundi | B2: 44228 | C2: 1 | D2: 1 | E2: 0 | F2: 0 | G2: 1 | H2: 1 | I2: 0.5 | J2: 1 | K2: 0 | L2: 1
A3: Mardi | B3: 44229 | C3: 1 | D3: 1 | E3: 1 | F3: 1 | G3: 1 | H3: 1 | I3: 0.5 | J3: 1 | K3: 0 | L3: 0
A4: Mercredi | B4: 44230 | C4: 1 | D4: 1 | E4: 1 | F4: 0 | G4: 1 | H4: 1 | I4: 0.5 | J4: 0 | K4: 0 | L4: 0
A5: Jeudi | B5: 44231 | C5: 1 | D5: 1 | E5: 1 | F5: 0 | G5: 1 | H5: 1 | I5: 0.5 | J5: 0 | K5: 0 | L5: 0
A6: Vendredi | B6: 44232 | C6: 1 | D6: 0 | E6: 0 | F6: 1 | G6: 0 | H6: 0 | I6: 0 | J6: 0 | K6: 1 | L6: 1
A7: Samedi | B7: 44233 | C7: 1 | D7: 1 | E7: 0 | F7: 0 | G7: 1 | H7: 1 | I7: 0 | J7: 1 | K7: 1 | L7: 0.5
A8: Dimanche | B8: 44234 | C8: 0 | D8: 1 | E8: 0 | F8: 0 | G8: 0 | H8: 1 | I8: 1 | J8: 1 | K8: 1 | L8: 1
A9: Lundi | B9: 44235 | C9: 1 | D9: 1 | E9: 0 | F9: 0 | G9: 1 | H9: 1 | I9: 1 | J9: 0 | K9: 1 | L9: 1
A10: Mardi | B10: 44236 | C10: 1 | D10: 1 | E10: 0 | F10: 0 | G10: 1 | H10: 1 | I10: 0 | J10: 0 | K10: 1 | L10: 1
A11: Mercredi | B11: 44237 | C11: 1 | D11: 1 | E11: 0 | F11: 0 | G11: 1 | H11: 1 | I11: 1 | J11: 0 | K11: 1 | L11: 1
A12: Jeudi | B12: 44238 | C12: 1 | D12: 1 | E12: 0 | F12: 1 | G12: 1 | H12: 1 | I12: 1 | J12: 0 | K12: 1 | L12: 1
A13: Vendredi | B13: 44239 | C13: 1 | D13: 0 | E13: 0 | F13: 1 | G13: 1 | H13: 0 | I13: 1 | J13: 0 | K13: 1 | L13: 1.67
... A29: Dimanche | B29: 44255 | C29: 1 | D29: 0 | E29: 0 | F29: 0 | G29: 1 | H29: 1 | I29: 1 | J29: 0 | K29: 1 | L29: 1
A30: TOTAL | C30: =SUM(C2:C29) -> 26 | D30: =SUM(D2:D29) -> 16 | E30: =SUM(E2:E29) -> 3 | F30: =SUM(F2:F29) -> 8 | G30: =SUM(G2:G29) -> 23 | H30: =SUM(H2:H29) -> 20.5 | I30: =SUM(I2:I29) -> 19 | J30: =SUM(J2:J29) -> 4 | ... L30: =SUM(L2:L29) -> 24.17
A31: TAUX | C31: 2000 | D31: 1200 | E31: 1000 | F31: 1000 | G31: 1200 | H31: 800 | I31: 1000 | J31: 500 | K31: 1000 | L31: 1200 | M31: =SUM(C31:L31) -> 10900
C32: =C31*C30 -> 52000 | D32: =D31*D30 -> 19200 | E32: =E31*E30 -> 3000 | F32: =F31*F30 -> 8000 | G32: =G31*G30 -> 27600 | H32: =H31*H30 -> 16400 | I32: =I31*I30 -> 19000 | J32: =J31*J30 -> 2000 | K32: =K31*K30 -> 21500 | L32: =L30*L31 -> 29004 | M32: =SUM(C32:L32) -> 197704
R36: Date | S36: Zehor
R37: 44228 | S37: 1
R38: 44229 | S38: 1
R39: 44230 | S39: 1
R40: 44231 | S40: 1
R41: 44232 | S41: 1
R42: 44233 | S42: 1
R43: 44234 | S43: 0
R44: 44235 | S44: 1
R45: 44236 | S45: 1
R46: 44237 | S46: 1
R47: 44238 | S47: 1
R48: 44239 | S48: 1
... R64: 44255 | S64: 1
S65: =SUM(S37:S64) -> 26
S66: 2000
S67: =S66*S65 -> 52000
P69: Date | Q69: Zahida
O70: Lundi | P70: 44228 | Q70: 1
O71: Mardi | P71: 44229 | Q71: 0
O72: Mercredi | P72: 44230 | Q72: 0
O73: Jeudi | P73: 44231 | Q73: 0
O74: Vendredi | P74: 44232 | Q74: 1
O75: Samedi | P75: 44233 | Q75: 0.5
O76: Dimanche | P76: 44234 | Q76: 1
O77: Lundi | P77: 44235 | Q77: 1
O78: Mardi | P78: 44236 | Q78: 1
O79: Mercredi | P79: 44237 | Q79: 1
O80: Jeudi | P80: 44238 | Q80: 1
O81: Vendredi | P81: 44239 | Q81: 1.67
... O97: Dimanche | P97: 44255 | Q97: 1
O98: TOTAL | Q98: =SUM(Q70:Q97) -> 24.17
O99: TAUX | Q99: 1200 | R99: 800 | S99: 1000 | T99: 500 | U99: 1000 | V99: 1200 | W99: =SUM(Q99:V99) -> 5700

Sheet Salaires 
I12: Nom | J12: Salaire | K12: Avance
H13: 1 | I13: Zehor | J13: =Pointage!C32*1 -> 52000 | K13: 2000
H14: 2 | I14: Amel | J14: =Pointage!G32*1 -> 27600 | K14: 2000
H15: 3 | I15: Nowara | J15: =Pointage!K32*1 -> 21500
H16: 4 | I16: karima | J16: =Pointage!J32*1 -> 2000 | K16: 2000
H17: 5 | I17: Nadjet | J17: =Pointage!E32*1 -> 3000 | K17: 3000
H18: 6 | I18: Hadjer | J18: =Pointage!F32*1 -> 8000
H19: 7 | I19: Zoubida | J19: =Pointage!D32*1 -> 19200 | K19: 19200
H20: 8 | I20: Hafida | J20: =Pointage!I32*1 -> 19000
H21: 9 | I21: Soumia | J21: =Pointage!H32*1 -> 16400
H22: 10 | I22: Zahida | J22: =Pointage!L32*1 -> 29004
I23: TOTAL | J23: =SUM(J13:J22) -> 197704 | K23: =SUM(K13:K22) -> 28200
J24: =J23-K23 -> 169504
Q28: Nom | R28: Salaire
P29: 1 | Q29: Zehor | R29: 50000
P30: 2 | Q30: Amel | R30: 25600
P31: 3 | Q31: Nowara | R31: 21500
P32: 4 | Q32: Hadjer | R32: 8000
P33: 5 | Q33: Hafida | R33: 19000
P34: 6 | Q34: Soumia | R34: 16400
P35: 7 | Q35: Zahida | R35: 29000
Q36: TOTAL | R36: =SUM(R29:R35) -> 169500
