Workbook

Sheet RECAP
B1: Date | C1: Recette mois d'Octobre | D1: Recette | E1: Charges | F1: Salaire | G1: Loyer | H1: Net Profit | I1: Nb de jours
A2: Dimanche | B2: 44136 | C2: 53000 | D2: 23000 | I2: 1 | L2: Moyenne
A3: Lundi | B3: 44137 | C3: 0 | D3: 20000 | E3: 0 | F3: 0 | G3: 0 | H3: 0 | I3: 1 | L3: =D32/I32 -> 24600 | N3: Sofiane | O3: Amel
A4: Mardi | B4: 44138 | C4: 20000 | D4: 22000 | I4: 1 | N4: 40000 | O4: 31000
A5: Mercredi | B5: 44139 | C5: 20000 | D5: 27000 | I5: 1 | L5: 30000
A6: Jeudi | B6: 44140 | C6: 21000 | D6: 37000 | I6: 1
A7: Vendredi | B7: 44141 | C7: 20000 | D7: 26000 | I7: 1
A8: Samedi | B8: 44142 | C8: 34000 | D8: 12000 | I8: 1
A9: Dimanche | B9: 44143 | C9: 33000 | D9: 22000 | I9: 1
A10: Lundi | B10: 44144 | C10: 0 | D10: 16000 | E10: 0 | F10: 0 | G10: 0 | H10: 0 | I10: 1
A11: Mardi | B11: 44145 | C11: 29000 | D11: 18000 | I11: 1
A12: Mecredi | B12: 44146 | C12: 26000 | D12: 24000 | I12: 1 | L12: Cash restant | M12: Magasin | P12: Différence
A13: Jeudi | B13: 44147 | C13: 27000 | D13: 34000 | I13: 1 | L13: =D32+'Charges '!G145-M13-E32-Salaires!J22-L16-P21 -> 448605 | M13: 30000 | P13: =D32-C32 -> -301000
A14: Vendredi | B14: 44148 | C14: 29000 | D14: 16000 | I14: 1
A15: Samedi | B15: 44149 | C15: 32000 | D15: 19000 | I15: 1 | L15: 320000
A16: Dimanche | B16: 44150 | C16: 40000 | D16: 17000 | I16: 1 | L16: 21000 | M16: Sofiane | N16: 15000 | O16: 6000
A17: Lundi | B17: 44151 | C17: 35000 | D17: 22000 | E17: 0 | F17: 0 | G17: 0 | H17: 0 | I17: 1
A18: Mardi | B18: 44152 | C18: 33000 | D18: 20000 | I18: 1 | L18: =L13-L15 -> 128605
A19: Mercredi | B19: 44153 | C19: 43000 | D19: 24000 | I19: 1 | L19: 75000
A20: Jeudi | B20: 44154 | C20: 32000 | D20: 52000 | I20: 1 | L20: =L18-L19 -> 53605
A21: Vendredi | B21: 44155 | C21: 33000 | D21: 30000 | I21: 1
A22: Samedi | B22: 44156 | C22: 49000 | D22: 27000 | I22: 1
A23: Dimanche | B23: 44157 | C23: 35000 | D23: 19000 | I23: 1
A24: Lundi | B24: 44158 | C24: 30000 | D24: 30000 | E24: 0 | F24: 0 | G24: 0 | H24: 0 | I24: 1
A25: Mardi | B25: 44159 | C25: 48000 | D25: 29000 | I25: 1
A26: Mercredi | B26: 44160 | C26: 52000 | D26: 26000 | I26: 1
A27: Jeudi | B27: 44161 | C27: 55000 | D27: 30000 | I27: 1
A28: Vendredi | B28: 44162 | C28: 66000 | D28: 20000 | I28: 1
A29: Samedi | B29: 44163 | C29: 80000 | D29: 28000 | I29: 1
A30: Dimanche | B30: 44164 | C30: 40000 | D30: 24000 | I30: 1
A31: Lundi | B31: 44165 | C31: 24000 | D31: 24000 | I31: 1
A32: TOTAL | C32: =SUM(C2:C31) -> 1039000 | D32: =SUM(D2:D31) -> 738000 | E32: ='Charges '!G144*1 -> 271895 | F32: =Salaires!I22*1 -> 189100 | G32: 77000 | H32: =D32+'Charges '!G145-E32-F32-G32 -> 240005 | I32: =SUM(I2:I31) -> 30
A33: TAUX | D33: 1 | E33: =E32/C32 -> 0.26168912 | F33: =F32/C32 -> 0.18200192 | G33: =G32/C32 -> 0.074109721 | H33: =H32/C32 -> 0.23099615
E35: 357000 | F35: 210000

Sheet Charges 
E4: Produit | F4: Quantité | G4: Prix | H4: Date d'achat
E5: étagères | F5: 1 | G5: 15000 | H5: mois de septembre
E6: Semoule | F6: 40 sachets de 10kg | G6: 24800 | H6: 44136
E7: huile | F7: 20 bidons de 5 litres | G7: 11000 | H7: 44136
E8: amandes | F8: 1kg | G8: 1700 | H8: 44136
E9: margarine | F9: 1 carton de 24 boites 250g | G9: 2760 | H9: 44136
E10: levure de bière | F10: 20 de 500g | G10: 5000 | H10: 44136
E11: Détergents | F11: 3 | G11: 400 | H11: 44136
E12: pièces pour la plaque chauffante | F12: 3 | G12: 1300 | H12: 44136
E13: bessel | F13: 20kg | G13: 700 | H13: 44136
E14: bessel | F14: 20kg | G14: 400 | H14: 44136
E15: tomate | F15: 5kg | G15: 300 | H15: 44136
E16: épices | F16: / | G16: 200 | H16: 44136
E17: viande hachéé | F17: 500g | G17: 800 | H17: 44136
E18: eau d'oranger | F18: 2 | G18: 170 | H18: 44136
E19: coriandre | F19: 3 | G19: 60 | H19: 44136
E20: semoule moyenne Sim | F20: 6 sachets de 10kg | G20: 3000 | H20: 44136
E21: Tomate conserve kigtome | F21: 1 carton | G21: 2640 | H21: 44136
E22: yaourt | F22: 5 | G22: 50 | H22: 44136
E23: farine | F23: 1kg | G23: 85 | H23: 44136
E24: plats 40/60 | F24: 3 | G24: 1050 | H24: 44136
E25: Maizina | F25: 2kg | G25: 300 | H25: 44136
E26: farine Mama | F26: 5kg | G26: 425 | H26: 44136
E27: semen Madina | F27: 4*2kg | G27: 1680 | H27: 44136
E28: sucre glace | F28: 12kg | G28: 1080 | H28: 44136
E29: Margarine Mani | F29: 2 cartons de 24 boites | G29: 5520 | H29: 44136
E30: levure chimique | F30: 1 boite | G30: 450 | H30: 44136
E31: miel de 5kg | F31: 3 | G31: 1770 | H31: 44136
E32: Faine Mama | F32: 3 fardeaux | G32: 2040 | H32: 44136
E33: Harrissa | F33: 1 carton de 12kg | G33: 2460 | H33: 44136
E34: sel | F34: fardeau de 15kg | G34: 330 | H34: 44136
E35: Confiture | F35: 1 carton de 12kg | G35: 1620 | H35: 44136
E36: eau d'oranger | F36: 12 | G36: 660 | H36: 44136
E37: fromage speciale pizza | F37: 12kg | G37: 2400 | H37: 44136
E38: Amandes | F38: 2kg | G38: 3300 | H38: 44136
E39: arome de citron | F39: 1 | G39: 750 | H39: 44136
E40: vanille | F40: / | G40: 200 | H40: 44136
E41: boites de mekiret | F41: 2 fardeaux | G41: 1500 | H41: 44136
E42: serviette en papier | F42: 1 | G42: 55 | H42: 44136
E43: chocolat optella | F43: 2 bidons de 3kg | G43: 1620 | H43: 44136
E44: les quissettes + dentelle | F44: 2 | G44: 200 | H44: 44136
E45: viande hachéé | F45: / | G45: 500 | H45: 44136
E46: boissons Rafik | F46: 8 | G46: 7000 | H46: 44137
E47: oeuf et autres achats | F47: 3 | G47: 500 | H47: 44137
E48: semoule Mama fine | F48: 7 sachets de 10kg | G48: 3850 | H48: 44137
E49: bahar | F49: 1 | G49: 500 | H49: 44137
E50: semoule Mama fine | F50: 20 sachets den 10 kg | G50: 12600 | H50: 44137
E51: semoule Mama fine | F51: 5 sachets de 10kg | G51: 2750 | H51: 44137
E52: semoule Mama fine | F52: 05 sachets de 10kg | G52: 3150 | H52: 44138
E53: boites 48/10 36/10 36/7 12/07 08/07 | F53: 5 | G53: 5250 | H53: 44137
E54: lait candia | F54: 1 | G54: 100 | H54: 44137
E55: flexy internet | F55: 1 mois | G55: 1500 | H55: 44137
E56: Rechta | F56: 100kg | G56: 1000 | H56: 44138
E57: semoule temina | F57: 1kg | G57: 100 | H57: 44139
E58: herebes | F58: 11 | G58: 220 | H58: 44139
E59: rechta | F59: 200kg | G59: 2000 | H59: 44139
E60: poulet hachée | F60: / | G60: 500 | H60: 44140
E61: citron | F61: 3 | G61: 100 | H61: 44140
E62: ciseaux | F62: 1 | G62: 100 | H62: 44140
E63: rechta | F63: 200kg | G63: 2000 | H63: 44140
E64: lave main | F64: 1 | G64: 100 | H64: 44140
E65: viande hachéé | F65: / | G65: 500 | H65: 44141
E66: trasport heech :( | F66: 1 | G66: 500 | H66: 44141
E67: Rechta | F67: 100kg | G67: 1000 | H67: 44141
E68: transport zehor | F68: 1 | G68: 750 | H68: 44141
E69: poivre tomate fraiche | F69: 2kg | G69: 300 | H69: 44141
E70: bessel | F70: 100kg | G70: 4000 | H70: 44143
E71: huile | F71: 30 | G71: 15600 | H71: 44143
E72: viande hachéé, poulet hachée | F72: 2 | G72: 1000 | H72: 44144
E73: ouefs | F73: 1 plateau | G73: 380 | H73: 44144
E74: yaourt | F74: 2 | G74: 30 | H74: 44144
E75: rechta | F75: 10kg | G75: 1000 | H75: 44144
E76: transport heech | F76: 1 | G76: 500 | H76: 44144
E77: habet 7alawa | F77: 1kg | G77: 1000 | H77: 44145
E78: coriandre: menth, thyme | F78: 7 | G78: 200 | H78: 44145
E79: Rechta | F79: 10kg | G79: 1000 | H79: 44145
E80: yaourt | F80: 20 boîtes | G80: 200 | H80: 44145
E81: amandes | F81: 1kg | G81: 1600 | H81: 44146
E82: détergents +bali+thon +3akeri | G82: 1450 | H82: 44146
E83: farine Mama | F83: 3 fardeaux | G83: 2100 | H83: 44147
E84: sucre cristalisé | F84: 1 fardeau | G84: 750 | H84: 44147
E85: lait en poudre | F85: 2kg | G85: 1480 | H85: 44147
E86: fromage speciale pizza | F86: 13kg | G86: 2600 | H86: 44147
E87: boites 48/10 | F87: 1 | G87: 1300 | H87: 44147
E88: boites 36/7 | F88: 1 | G88: 750 | H88: 44147
E89: sachets 5kg | F89: 1 faredau | G89: 1250 | H89: 44147
E90: 3akeri | F90: 1kg | G90: 800 | H90: 44147
E91: herbes | F91: 5 | G91: 100 | H91: 44147
E92: achats ; isis , viande hachée, thon | G92: 1000 | H92: 44148
E93: transport +bessel | F93: 3 | G93: 1500 | H93: 44149
E94: Transport Zehor vendredi | F94: 2 | G94: 2000 | H94: 44148
E95: Gobelet sorbet | F95: 100 | G95: 1650 | H95: 44150
E96: boits 36/07 | F96: 1 | G96: 850 | H96: 44150
E97: boites 36/10 | F97: 1 | G97: 1100 | H97: 44150
E98: eau petites bouteilles | F98: 5 fardeaux | G98: 900 | H98: 44150
E99: serviette en papier | F99: 5 | G99: 250 | H99: 44150
E100: isis | F100: 1 | G100: 260 | H100: 44150
E101: sac poubelle | F101: 1 | G101: 260 | H101: 44150
E102: papier aluminium | F102: 1 | G102: 1350 | H102: 44150
E103: cotex | F103: 1 | G103: 250 | H103: 44150
...

Sheet Pointage
B1: Date | C1: Zehor | D1: Zoubida | E1: Nadjet | F1: Hadjer | G1: Amel | H1: Karima | I1: Nouara | J1: Zahida | K1: Remarque
A2: Dimanche | B2: 44136 | C2: 1 | D2: 1 | E2: 0 | F2: 0.5 | G2: 1 | H2: 1 | I2: 1 | J2: 0
A3: Lundi | B3: 44137 | C3: 1 | D3: 1 | E3: 0 | F3: 0 | G3: 1 | H3: 1 | I3: 1 | J3: 1
A4: Mardi | B4: 44138 | C4: 1 | D4: 1 | E4: 0 | F4: 0 | G4: 1 | H4: 1 | I4: 1 | J4: 0
A5: Mercredi | B5: 44139 | C5: 1 | D5: 1 | E5: 0 | F5: 1 | G5: 1 | H5: 1 | I5: 1 | J5: 0
A6: Jeudi | B6: 44140 | C6: 1 | D6: 1 | E6: 0 | F6: 0 | G6: 1 | H6: 1 | I6: 1 | J6: 0
A7: Vendredi | B7: 44141 | C7: 1 | D7: 0 | E7: 0 | F7: 0 | G7: 0 | H7: 1 | I7: 1 | J7: 1
A8: Samedi | B8: 44142 | C8: 0 | D8: 1 | E8: 0 | F8: 0 | G8: 1 | H8: 1 | I8: 1 | J8: 1
A9: Dimanche | B9: 44143 | C9: 0 | D9: 1 | E9: 0 | F9: 0 | G9: 1 | H9: 1 | I9: 1 | J9: 1
A10: Lundi | B10: 44144 | C10: 1 | D10: 1 | E10: 0 | F10: 0 | G10: 1 | H10: 1 | I10: 1 | J10: 1
A11: Mardi | B11: 44145 | C11: 1 | D11: 1 | E11: 0 | F11: 0 | G11: 1 | H11: 1 | I11: 0 | J11: 1
A12: Mecredi | B12: 44146 | C12: 0 | D12: 1 | E12: 0 | F12: 0 | G12: 1 | H12: 1 | I12: 1 | J12: 1
A13: Jeudi | B13: 44147 | C13: 1 | D13: 1 | E13: 0 | F13: 0 | G13: 1 | H13: 1 | I13: 1 | J13: 1
... A31: Lundi | B31: 44165 | C31: 1 | D31: 1 | E31: 0 | F31: 0 | G31: 1 | H31: 1 | I31: 1 | J31: 1
B32: Total | C32: =SUM(C2:C31) -> 24 | D32: =SUM(D2:D31) -> 26 | E32: =SUM(E2:E31) -> 0 | F32: =SUM(F2:F31) -> 5.5 | G32: =SUM(G2:G31) -> 26 | H32: =SUM(H2:H31) -> 29 | I32: =SUM(I2:I31) -> 28 | J32: =SUM(J2:J31) -> 25.5
B33: Salaire/jour | C33: 2000 | D33: 1200 | E33: 1000 | F33: 1000 | G33: 1000 | H33: 600 | I33: 1000 | J33: 1200 | K33: =SUM(C33:J33) -> 9000
B34: SALAIRES | C34: =C33*C32 -> 48000 | D34: =D33*D32 -> 31200 | E34: =E33*E32 -> 0 | F34: =F33*F32 -> 5500 | G34: =G33*G32 -> 26000 | H34: =H33*H32 -> 17400 | I34: =I33*I32 -> 28000 | J34: =J32*J33 -> 30600 | K34: =SUM(C34:J34) -> 186700

Sheet Salaires
H12: Nom | I12: Salaire | J12: Avance
G13: 1 | H13: Zehor | I13: =Pointage!C34*1 -> 48000 | L13: Zehor | M13: 48000
G14: 2 | H14: Amel | I14: =Pointage!G34*1 -> 26000 | J14: 3000 | L14: Amel | M14: 22000
G15: 3 | H15: Nowara | I15: =Pointage!I34*1 -> 28000 | L15: Nowara | M15: 27000
G16: 4 | H16: karima | I16: =Pointage!H34*1 -> 17400 | L16: karima | M16: 20000
G17: 5 | H17: Nadjet | I17: =Pointage!E34*1 -> 0 | L17: Nadjet
G18: 6 | H18: Hadjer | I18: =Pointage!F34*1 -> 5500 | J18: 1500 | L18: Hadjer | M18: 4000
G19: 7 | H19: Zoubida | I19: =Pointage!D34*1 -> 31200 | L19: Zoubida | M19: 30000
G20: 8 | H20: Zahida | I20: =Pointage!J34*1 -> 30600 | J20: 2000 | L20: Zahida | M20: 30000
H21: salaire de septembre | I21: 2400 | M21: =SUM(M13:M20) -> 181000
H22: TOTAL | I22: =SUM(I13:I21) -> 189100 | J22: =SUM(J13:J20) -> 6500
I23: =I22-J22 -> 182600
