Workbook

Sheet RECAP
B1: Date | C1: Recette Juillet 2025 | D1: Recette | E1: Charges | F1: Salaire | G1: Che7i7a | H1: Loyer | I1: Net Profit | J1: Nb de jours | L1: Objectif | M1: Mois de Juillet 2025
A2: Vendredi | B2: 45870 | C2: 43000 | D2: 71000 | G2: 2000 | J2: 1 | M2: 43000
A3: Samedi | B3: 45871 | C3: 66000 | D3: 60000 | G3: 2000 | J3: 1 | M3: 66000 | N3: Bénéfice Moyen par jour | O3: Moyenne | P3: Moyenne salaire | Q3: pourcentage du salaire vis à vis la recettte
A4: Dimanche | B4: 45872 | C4: 82000 | D4: 78000 | G4: 2000 | J4: 1 | M4: 82000 | N4: =I33/J33 -> 22179.663 | O4: =D33/J33 -> 77043.478 | Q4: =P4/O4 -> 0
A5: Lundi | B5: 45873 | C5: 87000 | D5: 50000 | G5: 2000 | J5: 1 | M5: 87000
A6: Mardi | B6: 45874 | C6: 148000 | D6: 52000 | G6: 2000 | J6: 1 | M6: 148000 | N6: Moyenne des charges par jour | O6: Objectif
A7: Mercredi | B7: 45875 | C7: 63000 | D7: 48000 | G7: 2000 | J7: 1 | M7: 63000 | N7: =E33/J33 -> 28807.739 | O7: 100000
A8: Jeudi | B8: 45876 | C8: 30000 | D8: 70000 | G8: 2000 | J8: 1 | M8: 30000 | N8: ² | S8: "
A9: Vendredi | B9: 45877 | C9: 39000 | D9: 45000 | G9: 2000 | J9: 1 | M9: 39000
A10: Samedi | B10: 45878 | C10: 32000 | D10: 102000 | G10: 2000 | J10: 1 | M10: 32000 | N10: Cash restant | O10: Magasin | P10: Cash réel | Q10: Mes dettes pour le magasin
A11: Dimanche | B11: 45879 | C11: 32000 | D11: 64000 | G11: 2000 | J11: 1 | M11: 32000 | N11: =D33+N14-O11-E33-'Les Salaires'!J32-G33 -> 559422 | O11: 459000 | P11: 540000 | Q11: =N11-P11 -> 19422
A12: Lundi | B12: 45880 | C12: 62000 | D12: 64000 | G12: 2000 | J12: 1 | M12: 62000
A13: Mardi | B13: 45881 | C13: 112000 | D13: 55000 | G13: 2000 | J13: 1 | M13: 112000 | N13: Fond de Roulement
A14: Mercredi | B14: 45882 | C14: 77000 | D14: 50000 | G14: 2000 | J14: 1 | M14: 77000 | N14: 330000
A15: Jeudi | B15: 45883 | C15: 43000 | D15: 124000 | G15: 2000 | J15: 1 | M15: 43000 | Q15: La caisse :16000DA
A16: Vendredi | B16: 45884 | C16: 53000 | D16: 0 | G16: 0 | J16: 0 | K16: 1 | M16: 53000 | Q16: CCP:100000Da
A17: Samedi | B17: 45885 | C17: 68000 | D17: 0 | G17: 0 | J17: 0 | K17: 1 | M17: 68000 | Q17: Dus Non payés: 115000Da
A18: Dimanche | B18: 45886 | C18: 64000 | D18: 0 | G18: 0 | J18: 0 | M18: 64000 | Q18: Facture Toufik DZ Event: 117000Da
A19: Lundi | B19: 45887 | C19: 89000 | D19: 0 | G19: 0 | J19: 0 | M19: 89000 | N19: Différence mois de Décembre | Q19: chahrazed Baraki: 40600 Da
A20: Mardi | B20: 45888 | C20: 69000 | D20: 0 | G20: 0 | J20: 0 | M20: 69000 | N20: =D33-C33 -> -225000 | Q20: Sofiane Wise: 43euro =11000Da
A21: Mercredi | B21: 45889 | C21: 62000 | D21: 0 | G21: 0 | J21: 0 | M21: 62000 | N21: Différence objectif | Q21: Cash PorteFeuille : 60000Da
A22: Jeudi | B22: 45890 | C22: 50000 | D22: 0 | G22: 0 | J22: 0 | M22: 50000 | N22: =L36-E36 -> 0
A23: Vendredi | B23: 45891 | C23: 47000 | D23: 4000 | G23: 0 | J23: 0 | M23: 47000 | N23: Différence du Totale
A24: Samedi | B24: 45892 | C24: 48000 | D24: 104000 | G24: 2000 | J24: 1 | M24: 48000 | N24: =D33-C33 -> -225000
A25: Dimanche | B25: 45893 | C25: 68000 | D25: 34000 | G25: 2000 | J25: 1 | M25: 68000 | N25: Les vendredis
A26: Lundi | B26: 45894 | C26: 29000 | D26: 78000 | G26: 2000 | J26: 1 | M26: 29000 | N26: =D9+D16+D23+D30 -> 142000
A27: Mardi | B27: 45895 | C27: 161000 | D27: 63000 | G27: 2000 | J27: 1 | M27: 161000
A28: Mercredi | B28: 45896 | C28: 57000 | D28: 59000 | G28: 2000 | J28: 1 | M28: 57000 | N28: Cash réel
A29: Jeudi | B29: 45897 | C29: 53000 | D29: 62000 | G29: 2000 | J29: 1 | M29: 53000 | N29: 51000
A30: Vendredi | B30: 45898 | C30: 32000 | D30: 93000 | G30: 2000 | J30: 1 | M30: 32000 | N30: rest à payer
A31: Samedi | B31: 45899 | C31: 58000 | D31: 300000 | G31: 2000 | J31: 1 | M31: 58000
A32: Dimanche | B32: 45900 | C32: 73000 | D32: 42000 | G32: 2000 | J32: 1 | M32: 73000
C33: =SUM(C2:C32) -> 1997000 | D33: =SUM(D2:D32) -> 1772000 | E33: ='Les Charges '!H360 -> 662578 | F33: ='Les Salaires'!I32 -> 373289.75 | G33: =SUM(G2:G32) -> 46000 | H33: 180000 | I33: =D33-E33-F33-G33-H33 -> 510132.25 | J33: =SUM(J2:J32) -> 23 | M33: =SUM(M2:M32) -> 1997000
G34: Loyer Magasin | H34: 55000
G35: Loyer Locale | H35: 40000 | N35: =N11-N29-N34 -> 508422
D36: 200000 | G36: Sofiane Maison | H36: 45000 | P36: Papa | Q36: 40000
G37: Dette Papa | H37: 40000
D38: -
C49: 1

Sheet Les Charges 
E1: Produit | F1: Quantité | G1: Prix unitaire | H1: Prix | I1: Date d'achat
E2: Canette Hamoud Annanas | F2: 29 | G2: 44 | H2: =F2*G2 -> 1276 | I2: Boissons
E3: Canette Hamoud Orange | F3: 23 | G3: 44 | H3: =F3*G3 -> 1012
E4: Canette Hamoud Pomme | F4: 26 | G4: 44 | H4: =F4*G4 -> 1144
E5: Canette Hamoud citron | F5: 17 | G5: 44 | H5: =F5*G5 -> 748
E6: Canette Hamoud poire | F6: 6 | G6: 44 | H6: =F6*G6 -> 264
E7: Canette Hamoud pèche | F7: 6 | G7: 44 | H7: =F7*G7 -> 264
E8: Canette Hamoud Litchi | F8: 7 | G8: 44 | H8: =F8*G8 -> 308
E9: Canette Hamoud Blanc | F9: 5 | G9: 44 | H9: =F9*G9 -> 220
E10: Canette Hamoud Selecto | F10: 21 | G10: 44 | H10: =F10*G10 -> 924
E11: Canette Hamoud Cola | F11: 8 | G11: 44 | H11: =F11*G11 -> 352
E12: Canette Shwepess Grenadine | F12: 1 | G12: 73 | H12: =F12*G12 -> 73
E13: canette Shwepess Citron | F13: 4 | G13: 73 | H13: =F13*G13 -> 292
E14: Canette Shwepes Gold | F14: 10 | G14: 73 | H14: =F14*G14 -> 730
... E29: Hamoud Bouteille pomme | F29: 31 | G29: 35 | H29: =F29*G29 -> 1085
E30: Semoule Fine 25kg | F30: 6 | G30: 1000 | H30: =F30*G30 -> 6000 | I30: Payée le 10/08/2025
E31: Transport et Manutention | F31: 1 | G31: 2000 | H31: =F31*G31 -> 2000
E32: Semoule Moula Gros 10kg | F32: 6 | G32: 850 | H32: =F32*G32 -> 5100
E33: Semoule Moula moyenne 10kg | F33: 7 | G33: 520 | H33: =F33*G33 -> 3640
E34: Faine Makam 10kg | F34: 1 | G34: 450 | H34: =F34*G34 -> 450
E35: Farine Sousimie 5kg | F35: 4 | G35: 320 | H35: =F35*G35 -> 1280
E36: Chocolat Wedjedane au Lait | F36: 3 | G36: 255 | H36: =F36*G36 -> 765
E37: Chocolat wedjedane au lait | F37: 0 | G37: 245 | H37: =F37*G37 -> 0
E38: Chocolat wedjedane Blanc | F38: 1 | G38: 245 | H38: =F38*G38 -> 245
E39: Chocolat wedjedane Noir | F39: 10 | G39: 245 | H39: =F39*G39 -> 2450
E40: Chocolat wedjedane Noisette | F40: 0 | G40: 200 | H40: =F40*G40 -> 0
E41: Margarine Feuilletage 500g | F41: 5 | G41: 154 | H41: =F41*G41 -> 770 | I41: 45876
E42: Sucre cristalisé 25kg | F42: 30 | G42: 99 | H42: =F42*G42 -> 2970
E43: Amande marron | F43: 2.5 | G43: 2220 | H43: =F43*G43 -> 5550
E44: Khel | F44: 1 | G44: 30 | H44: =F44*G44 -> 30
E45: avoine | F45: 5 | G45: 280 | H45: =F45*G45 -> 1400
E46: Pate d'arome Maa Zehar | F46: 0.5 | G46: 1150 | H46: =F46*G46 -> 575
E47: pate d'arome citron | F47: 0.5 | G47: 780 | H47: =F47*G47 -> 390
E48: pate d'arome beuure vanille | F48: 0.5 | G48: 950 | H48: =F48*G48 -> 475
E49: Amande moulu | F49: 2 | G49: 1700 | H49: =F49*G49 -> 3400 | I49: La commande de chebah Sofera annulée
E50: Levure Boulangère Staf Intense 500g | F50: 5 | G50: 420 | H50: =F50*G50 -> 2100
E51: pate à sucre | F51: 2 | G51: 150 | H51: =F51*G51 -> 300
E52: Crème chocolat Mordjane 700g | F52: 0.5 | G52: 850 | H52: =F52*G52 -> 425
E53: pate à tartiner Mordjane | F53: 0.5 | G53: 900 | H53: =F53*G53 -> 450
E54: Crème liquide 4 fromages | F54: 6 | G54: 351 | H54: =F54*G54 -> 2106
E55: Fromage spéciale pizza | F55: 2 | G55: 650 | H55: =F55*G55 -> 1300
E56: olive noir | F56: 1 | G56: 600 | H56: =F56*G56 -> 600
E57: Olive coupé | F57: 1 | G57: 650 | H57: =F57*G57 -> 650
E58: Olive dényauté | F58: 1 | G58: 650 | H58: =F58*G58 -> 650
E59: Maiizina | F59: 2.5 | G59: 220 | H59: =F59*G59 -> 550
E60: Huile 5 Litres | F60: 44 | G60: 600 | H60: =F60*G60 -> 26400
E61: Semen 1,8 | F61: 14 | G61: 790 | H61: =F61*G61 -> 11060
... E132: noix de coco | F132: 1 | G132: 900 | H132: =F132*G132 -> 900
E133: Nakkach | F133: 120 | G133: 60 | H133: =F133*G133 -> 7200 | I133: 45870
E134: rechta | F134: 10 | G134: 100 | H134: =F134*G134 -> 1000 | I134: 45875
E135: oeufs | F135: 4 | G135: 580 | H135: =F135*G135 -> 2320
E136: poivre+ poivron + tomate fraiche | F136: 3 | G136: 100 | H136: =F136*G136 -> 300
E137: barquettes | F137: 5 | G137: 30 | H137: =F137*G137 -> 150
E138: pomme de terre | F138: 3 | G138: 50 | H138: =F138*G138 -> 150
E139: deyoul | F139: 2 | G139: 100 | H139: =F139*G139 -> 200
E140: Hamissa | F140: 2 | G140: 450 | H140: =F140*G140 -> 900
E141: rechta | F141: 2 | G141: 100 | H141: =F141*G141 -> 200
E142: cuisses | F142: 7 | G142: 200 | H142: =F142*G142 -> 1400
E143: blanc de poulet + poulet haché+ escalope | F143: 12 | G143: 700 | H143: =F143*G143 -> 8400 | I143: 45871
E144: plateaux oeufs | F144: 4 | G144: 500 | H144: =F144*G144 -> 2000
E145: cuissses | F145: 15 | G145: 200 | H145: =F145*G145 -> 3000
E146: courgette | F146: 1.5 | G146: 200 | H146: =F146*G146 -> 300
E147: Navet | F147: 2 | G147: 300 | H147: =F147*G147 -> 600
E148: rechta | F148: 10 | G148: 100 | H148: =F148*G148 -> 1000
E149: viande morceaux | F149: 13 | G149: 400 | H149: =F149*G149 -> 5200
E150: coriandre + persil | F150: 6 | G150: 40 | H150: =F150*G150 -> 240
E151: rechta | F151: 11 | G151: 100 | H151: =F151*G151 -> 1100 | I151: samedi + dimanche
E152: viande hachée | F152: 1 | G152: 1200 | H152: =F152*G152 -> 1200
E153: pate feuilletée | F153: 1 | G153: 400 | H153: =F153*G153 -> 400
E154: les enveloppes | F154: 50 | G154: 15 | H154: =F154*G154 -> 750
E155: Poelle | F155: 1 | G155: 2000 | H155: =F155*G155 -> 2000 | I155: 45875
E156: cuillère + forchette | F156: 2 | G156: 150 | H156: =F156*G156 -> 300
E157: rechtaa | F157: 20 | G157: 100 | H157: =F157*G157 -> 2000 | I157: 45876
E158: salade | F158: 1 | G158: 150 | H158: =F158*G158 -> 150
E159: deyoul | F159: 4 | G159: 120 | H159: =F159*G159 -> 480
E160: blanc de poulet | F160: 2 | G160: 750 | H160: =F160*G160 -> 1500
E161: poivre | F161: 2 | G161: 150 | H161: =F161*G161 -> 300
E162: tomate fraiche | F162: 1.5 | G162: 70 | H162: =F162*G162 -> 105
E163: rechta | F163: 10 | G163: 100 | H163: =F163*G163 -> 1000
E164: Légumes | F164: 1 | G164: 600 | H164: =F164*G164 -> 600
E165: storm magasin | F165: 1 | G165: 1500 | H165: =F165*G165 -> 1500 | I165: 45872
E166: Tomate Fraiche | F166: 0.5 | G166: 60 | H166: =F166*G166 -> 30
E167: Poivre | F167: 2 | G167: 150 | H167: =F167*G167 -> 300
E168: Bons de Livraison | F168: 5 | G168: 150 | H168: =F168*G168 -> 750
E169: Rechta | F169: 10 | G169: 100 | H169: =F169*G169 -> 1000 | I169: 45877
E170: demie cuisses | F170: 12 | G170: 120 | H170: =F170*G170 -> 1440
E171: Cuisses | F171: 5 | G171: 130 | H171: =F171*G171 -> 650
E172: Navet | F172: 2 | G172: 300 | H172: =F172*G172 -> 600
E173: courgette | F173: 1 | G173: 200 | H173: =F173*G173 -> 200
E174: Bessel 164+147 | F174: 311 | G174: 50 | H174: =F174*G174 -> 15550 | I174: 45891
E175: Tomate Fraiche 20+20 | F175: 40 | G175: 50 | H175: =F175*G175 -> 2000
E176: Nakkach | F176: 380 | G176: 60 | H176: =F176*G176 -> 22800
E177: Salade | F177: 1 | G177: 100 | H177: =F177*G177 -> 100
E178: Heech Yasmine Vendredi | F178: 1 | G178: 780 | H178: =F178*G178 -> 780
E179: Livraison Sofiane + Thé | F179: 1 | G179: 350 | H179: =F179*G179 -> 350
E180: SOS CAFARDS Dette | F180: 1 | G180: 15000 | H180: =F180*G180 -> 15000 | I180: 45878
E181: cuisses de poulet | F181: 2 | G181: 200 | H181: =F181*G181 -> 400
E182: légumes navet + courgette | F182: 1 | G182: 110 | H182: =F182*G182 -> 110
E183: Salade | F183: 1 | G183: 90 | H183: =F183*G183 -> 90
E184: plateaux oeufs | F184: 2 | G184: 580 | H184: =F184*G184 -> 1160
...

Sheet Pointage
B1: Date | C1: Saida | D1: Fatiha | E1: Samira Z | F1: Souad | G1: Yasmine | H1: Zohra | I1: Lynda | J1: Amina | K1: Ahlem | L1: Samira | M1: Zahia | N1: Nacera | O1: Houda | P1: Israa | Q1: Ikram | R1: Fella | S1: Bacup
A2: Vendredi | B2: 45870 | C2: 1 | D2: 2 | E2: 1 | F2: 3 | G2: 2 | H2: 8 | I2: 2 | J2: 1 | K2: 2 | L2: 2 | M2: 2 | N2: 3.5 | P2: 0 | Q2: 0 | R2: 0 | T2: 8 jours Congé Pour Zohra Mois de Juillet souad over time minimum 1,5 heurs / jour et Nacera overtime+ 3 jours de juillet*
A3: Samedi | B3: 45871 | C3: 1 | D3: 1 | E3: 1 | F3: 0 | G3: 1 | H3: 1 | I3: 0 | J3: 1 | K3: 1 | L3: 0 | M3: 1 | N3: 1 | P3: 1 | Q3: 0 | R3: 1
A4: Dimanche | B4: 45872 | C4: 1 | D4: 1 | E4: 1 | F4: 0 | G4: 1 | H4: 0 | I4: 0 | J4: 1 | K4: 1 | L4: 0 | M4: 1 | N4: 1 | P4: 1 | Q4: 0 | R4: 0
A5: Lundi | B5: 45873 | C5: 1 | D5: 1 | E5: 1 | F5: 0 | G5: 1 | H5: 1 | I5: 0 | J5: 1 | K5: 1 | L5: 0 | M5: 1 | N5: 1 | P5: 1 | Q5: 0 | R5: 0
A6: Mardi | B6: 45874 | C6: 1 | D6: 1 | E6: 1 | F6: 1 | G6: 1 | H6: 0 | I6: 0 | J6: 1 | K6: 1 | L6: 0 | M6: 1 | N6: 1 | P6: 1 | Q6: 0 | R6: 0
A7: Mercredi | B7: 45875 | C7: 1 | D7: 1 | E7: 1 | F7: 1 | G7: 1 | H7: 1 | I7: 0 | J7: 1 | K7: 1 | L7: 0 | M7: 1 | N7: 1 | P7: 0 | Q7: 0 | R7: 0
A8: Jeudi | B8: 45876 | C8: 1 | D8: 1 | E8: 1 | F8: 1 | G8: 1 | H8: 0 | I8: 0 | J8: 1 | K8: 1 | L8: 0 | M8: 1 | N8: 1 | P8: 1 | Q8: 1 | R8: 0 | T8: Saida et Isrraa djaw à 09h30
A9: Vendredi | B9: 45877 | C9: 1 | D9: 2 | E9: 1 | F9: 2 | G9: 2 | H9: 2 | I9: 0 | J9: 1 | K9: 1 | L9: 0 | M9: 2 | N9: 1 | P9: 0 | Q9: 1 | R9: 1
A10: Samedi | B10: 45878 | C10: 1 | D10: 1 | E10: 1 | F10: 1 | G10: 1 | H10: 0 | I10: 0 | J10: 1 | K10: 1 | L10: 0 | M10: 1 | N10: 1 | P10: 1 | Q10: 1 | R10: 1
A11: Dimanche | B11: 45879 | C11: 1 | D11: 1 | E11: 1 | F11: 1 | G11: 1 | H11: 1 | I11: 0 | J11: 0 | K11: 1 | L11: 0 | M11: 1 | N11: 1 | P11: 1 | Q11: 1 | R11: 0
A12: Lundi | B12: 45880 | C12: 1 | D12: 1 | E12: 1 | F12: 1 | G12: 1 | H12: 0 | I12: 0 | J12: 0 | K12: 1 | L12: 0 | M12: 1 | N12: 1 | P12: 1 | Q12: 1 | R12: 0
A13: Mardi | B13: 45881 | C13: 1 | D13: 1 | E13: 1 | F13: 1 | G13: 0 | H13: 1 | I13: 0 | J13: 0 | K13: 1 | L13: 0 | M13: 1 | N13: 1 | P13: 1 | Q13: 1 | R13: 0
A14: Mercredi | B14: 45882 | C14: 1 | D14: 1 | E14: 1 | F14: 2 | G14: 1 | H14: 0 | I14: 0 | J14: 0 | K14: 1 | L14: 0 | M14: 2 | N14: 2 | P14: 1 | Q14: 2 | R14: 0 | S14: 1
A15: Jeudi | B15: 45883 | C15: 1 | D15: 1 | E15: 0.75 | F15: 1 | G15: 1 | H15: 0 | I15: 0 | J15: 0 | K15: 1 | L15: 0 | M15: 1 | N15: 1 | P15: 1 | Q15: 1 | R15: 1
A16: Vendredi | B16: 45884 | C16: 0 | D16: 1 | E16: 0 | F16: 0 | G16: 1 | H16: 1 | I16: 0 | J16: 0 | K16: 1 | L16: 0 | M16: 0 | N16: 0 | P16: 0 | Q16: 0 | R16: 0
A17: Samedi | B17: 45885 | C17: 1 | D17: 1 | E17: 0 | F17: 0 | G17: 1 | H17: 0 | I17: 0 | J17: 0 | K17: 1 | L17: 0 | M17: 0 | N17: 0 | P17: 0 | Q17: 0 | R17: 0
A18: Dimanche | B18: 45886 | C18: 1 | D18: 1 | E18: 0 | F18: 0 | G18: 1 | H18: 1 | I18: 0 | J18: 0 | K18: 1 | L18: 0 | M18: 0 | N18: 0 | P18: 0 | Q18: 0 | R18: 0
A19: Lundi | B19: 45887 | C19: 1 | D19: 1 | E19: 0 | F19: 0 | G19: 1 | H19: 0 | I19: 0 | J19: 0 | K19: 1 | L19: 0 | M19: 0 | N19: 0 | P19: 0 | Q19: 0 | R19: 0
A20: Mardi | B20: 45888 | C20: 0 | D20: 1 | E20: 0 | F20: 0 | G20: 1 | H20: 1 | I20: 0 | J20: 0 | K20: 1 | M20: 0 | N20: 0 | P20: 0 | Q20: 0 | R20: 0
A21: Mercredi | B21: 45889 | C21: 0 | D21: 1 | E21: 0 | F21: 0 | G21: 1 | H21: 0 | I21: 0 | J21: 0 | K21: 1 | L21: 0 | M21: 0 | N21: 0 | P21: 0 | Q21: 0 | R21: 0
A22: Jeudi | B22: 45890 | C22: 0 | D22: 1 | E22: 0 | F22: 1 | G22: 1 | H22: 1 | I22: 0 | J22: 0 | K22: 1 | L22: 0 | M22: 0 | N22: 1 | P22: 0 | Q22: 0 | R22: 0
A23: Vendredi | B23: 45891 | C23: 0 | D23: 2 | E23: 0 | F23: 2 | G23: 1 | H23: 2 | I23: 0 | J23: 0 | K23: 0 | L23: 0 | M23: 0 | N23: 1 | P23: 0 | Q23: 0 | R23: 0
A24: Samedi | B24: 45892 | C24: 1 | D24: 1 | E24: 0 | F24: 1 | G24: 1 | H24: 0 | I24: 0 | J24: 1 | K24: 1 | L24: 0 | M24: 0 | N24: 1 | P24: 1 | Q24: 0 | R24: 0 | S24: 1
A25: Dimanche | B25: 45893 | C25: 1 | D25: 1 | E25: 1 | F25: 1 | G25: 0 | H25: 1 | I25: 0 | J25: 0.5 | K25: 1 | L25: 0 | M25: 1 | N25: 1 | P25: 1 | Q25: 0 | R25: 0 | T25: overtilme
A26: Lundi | B26: 45894 | C26: 0 | D26: 1 | E26: 1 | F26: 1 | G26: 1 | H26: 0 | I26: 0 | J26: 1 | K26: 1 | L26: 0 | M26: 0 | N26: 1 | P26: 0 | Q26: 0 | R26: 0
A27: Mardi | B27: 45895 | C27: 0 | D27: 1 | E27: 1 | F27: 1 | G27: 0 | H27: 1 | I27: 0 | J27: 1 | K27: 1 | L27: 0 | M27: 0 | N27: 0.5 | O27: 1 | P27: 0 | Q27: 0 | R27: 0 | S27: 1 | T27: chiraz
A28: Mercredi | B28: 45896 | C28: 1 | D28: 1 | E28: 1 | F28: 1 | G28: 0 | H28: 0 | I28: 0 | J28: 1 | K28: 1 | L28: 0 | M28: 0 | N28: 1 | O28: 0 | P28: 1 | Q28: 0 | R28: 0 | S28: 1 | T28: chiraz
A29: Jeudi | B29: 45897 | C29: 1 | D29: 1 | E29: 1 | F29: 1 | G29: 1 | H29: 1 | I29: 0 | J29: 1 | K29: 1 | L29: 0 | M29: 0 | N29: 1 | O29: 0 | P29: 0 | Q29: 0 | R29: 0 | S29: 1
A30: Vendredi | B30: 45898 | C30: 1 | D30: 2 | E30: 1 | F30: 2 | G30: 2 | H30: 2 | I30: 0 | J30: 0 | K30: 1 | L30: 0 | M30: 0 | N30: 1 | O30: 0 | P30: 0 | Q30: 0 | R30: 0 | S30: 2
A31: Samedi | B31: 45899 | C31: 1 | D31: 1 | E31: 0 | F31: 1 | G31: 1 | H31: 2 | I31: 0 | J31: 0 | K31: 1 | L31: 0 | M31: 1 | N31: 1 | O31: 0 | P31: 0 | Q31: 0 | R31: 0 | S31: 1 | T31: zohra overtime
A32: Dimanche | B32: 45900 | C32: 1 | D32: 2 | E32: 0 | F32: 1 | G32: 1 | H32: 1 | I32: 0 | J32: 0 | K32: 1 | L32: 0 | M32: 1 | N32: 1 | O32: 1 | P32: 0 | Q32: 0 | R32: 0 | S32: 1 | T32: Fatiha sa journée + over time
C33: =SUM(C2:C32) -> 24 | D33: =SUM(D2:D32) -> 36 | E33: =SUM(E2:E32) -> 19.75 | F33: =SUM(F2:F32) -> 28 | G33: =SUM(G2:G32) -> 30 | H33: =SUM(H2:H32) -> 29 | I33: =SUM(I2:I32) -> 2 | J33: =SUM(J2:J32) -> 14.5 | ... S33: =SUM(S2:S32) -> 9
C34: 1032 | D34: 968 | E34: 1065 | F34: 1032 | G34: 968 | H34: 1000 | I34: 1400 | J34: 1200 | K34: 968 | L34: 968 | M34: 968 | N34: 1000 | O34: 1000 | P34: 1100 | Q34: 1000 | R34: 1000 | S34: 1200
C35: =C33*C34 -> 24768 | D35: =D33*D34 -> 34848 | E35: =E33*E34 -> 21033.75 | F35: =F33*F34 -> 28896 | G35: =G33*G34 -> 29040 | H35: =H33*H34 -> 29000 | I35: =I33*I34 -> 2800 | J35: =J33*J34 -> 17400 | ... P35: =P33*P34 -> 15400 | Q35: =Q34*Q33 -> 9000 | R35: =R33*R34 -> 4000 | S35: =S33*S34 -> 10800
B37: Salaires | C37: 32000 | D37: 30000 | E37: 33000 | F37: 35000 | G37: 30000 | H37: 30000 | J37: 37000 | K37: 30000 | L37: 30000 | M37: 30000
T40: Saida lui reste 3 jours non Payée de son congé
T41: Zohra c'est bon edate 8 jours
T42: Yasmine 8 jours elle lui reste 7 jours
T43: Fatiha lui reste une journéee de congé
B47: Date
A48: Vendredi | B48: 45870 | C48: 3.5 | D48: Heures Suplémentaires + 3 jours de juillets
A49: Samedi | B49: 45871 | C49: 1
A50: Dimanche | B50: 45872 | C50: 1
A51: Lundi | B51: 45873 | C51: 1
A52: Mardi | B52: 45874 | C52: 1
A53: Mercredi | B53: 45875 | C53: 1
A54: Jeudi | B54: 45876 | C54: 1
A55: Vendredi | B55: 45877 | C55: 1 | D55: OFF
A56: Samedi | B56: 45878 | C56: 1
A57: Dimanche | B57: 45879 | C57: 1
A58: Lundi | B58: 45880 | C58: 1
A59: Mardi | B59: 45881 | C59: 1
A60: Mercredi | B60: 45882 | C60: 2 | D60: Double journée
A61: Jeudi | B61: 45883 | C61: 1
A62: Vendredi | B62: 45884 | C62: 0
A63: Samedi | B63: 45885 | C63: 0
A64: Dimanche | B64: 45886 | C64: 0
A65: Lundi | B65: 45887 | C65: 0
A66: Mardi | B66: 45888 | C66: 0
A67: Mercredi | B67: 45889 | C67: 0
A68: Jeudi | B68: 45890 | C68: 1
A69: Vendredi | B69: 45891 | C69: 1 | D69: OFF
A70: Samedi | B70: 45892 | C70: 1
A71: Dimanche | B71: 45893 | C71: 1
A72: Lundi | B72: 45894 | C72: 1
A73: Mardi | B73: 45895 | C73: 0.5 | D73: Demie journée autorisée
A74: Mercredi | B74: 45896 | C74: 1
A75: Jeudi | B75: 45897 | C75: 1
A76: Vendredi | B76: 45898 | C76: 1 | D76: OFF
A77: Samedi | B77: 45899 | C77: 1
A78: Dimanche | B78: 45900 | C78: 1
C79: =SUM(C48:C78) -> 28
C80: 1000
B81: Totale | C81: =C79*C80 -> 28000
B82: Avance | C82: 6000
B83: Reste à payer | C83: =C81-C82 -> 22000
B88: Date | C88: Souad
A89: Vendredi | B89: 45870 | C89: 1 | D89: 8 heures suplémentaires
A90: Samedi | B90: 45871 | C90: 0
A91: Dimanche | B91: 45872 | C91: 0
A92: Lundi | B92: 45873 | C92: 0
A93: Mardi | B93: 45874 | C93: 1
A94: Mercredi | B94: 45875 | C94: 1
A95: Jeudi | B95: 45876 | C95: 1
A96: Vendredi | B96: 45877 | C96: 2
A97: Samedi | B97: 45878 | C97: 1
A98: Dimanche | B98: 45879 | C98: 1
A99: Lundi | B99: 45880 | C99: 1
A100: Mardi | B100: 45881 | C100: 1
A101: Mercredi | B101: 45882 | C101: 2 | D101: Double Journée
A102: Jeudi | B102: 45883 | C102: 1
A103: Vendredi | B103: 45884 | C103: 0
A104: Samedi | B104: 45885 | C104: 0
A105: Dimanche | B105: 45886 | C105: 0
A106: Lundi | B106: 45887 | C106: 0
A107: Mardi | B107: 45888 | C107: 0
A108: Mercredi | B108: 45889 | C108: 0
A109: Jeudi | B109: 45890 | C109: 1
A110: Vendredi | B110: 45891 | C110: 2
...

Sheet Les Salaires
H12: Nom | I12: Salaire | J12: Avance | K12: Salaire à payer
H13: Sofiane | I13: 30000 | J13: 30000 | K13: =I13-J13 -> 0 | L13: 45883
H14: Amel | I14: 30000 | J14: 30000 | K14: =I14-J14 -> 0
G15: 1 | H15: Saida | I15: =Pointage!C35 -> 24768 | J15: 25000 | K15: =I15-J15 -> -232 | L15: 8000+8000
G16: 2 | H16: Fatiha | I16: =Pointage!D35 -> 34848 | J16: 35000 | K16: =I16-J16 -> -152 | L16: 6000+1000+1000+3000+1000+
G17: 3 | H17: Samira z | I17: =Pointage!E35 -> 21033.75 | J17: 21000 | K17: 0 | L17: 25000+5000 reste -9000
G18: 4 | H18: Souad | I18: =Pointage!F35 -> 28896 | J18: 29000 | K18: =I18-J18 -> -104
G19: 5 | H19: Yasmine | I19: =Pointage!G35+L19 -> 34040 | J19: 34000 | K19: 0 | L19: 5000
G20: 6 | H20: Zohra | I20: =Pointage!H35 -> 29000 | J20: 29000 | K20: =I20-J20 -> 0 | L20: 8000
G21: 7 | H21: Lynda | I21: =Pointage!I35 -> 2800 | J21: 3000 | K21: =I21-J21 -> -200
G22: 8 | H22: Amina | I22: =Pointage!J35 -> 17400 | J22: 17500 | K22: =I22-J22 -> -100
G23: 9 | H23: Ahlem | I23: =Pointage!K35 -> 30008 | J23: 30000 | K23: 0
G24: 10 | H24: Samira | I24: =Pointage!L35 -> 1936 | J24: 2000 | K24: =I24-J24 -> -64
G25: 11 | H25: Zahia | I25: =Pointage!M35 -> 19360 | J25: 19500 | K25: =I25-J25 -> -140
G26: 12 | H26: Nacera | I26: =Pointage!N35 -> 28000 | J26: 28000 | K26: =I26-J26 -> 0 | L26: 6000+22000
G27: 13 | H27: Houda | I27: =Pointage!O35 -> 2000 | J27: 2000 | K27: =I27-J27 -> 0
G28: 14 | H28: Israa | I28: =Pointage!P35 -> 15400 | J28: 16000 | K28: =I28-J28 -> -600
G29: 15 | H29: Fella | I29: =Pointage!R35 -> 4000 | J29: 4000 | K29: =I29-J29 -> 0
G30: 16 | H30: Backup | I30: =Pointage!S35 -> 10800 | J30: 11000 | K30: =I30-J30 -> -200
G31: 17 | H31: Ikram | I31: =Pointage!Q35 -> 9000 | J31: 9000 | K31: =I31-J31 -> 0 | L31: 2000+7000
H32: TOTAL | I32: =SUM(I13:I31) -> 373289.75 | J32: =SUM(J13:J31) -> 375000 | K32: =I32-J32 -> -1710.25
K33: =I33-J33 -> 0

Sheet Comparaison entre les Mois 
C16: Mois de Janvier 2025 | D16: Mois de Février 2025 | E16: Mois de Mars 2025 | F16: Mois d'Avril 2025 | G16: Mois de Mai 2025 | H16: Mois de Juin 2025 | I16: Mois de Juillet 2025 | J16: Mois d'Aout 2025
B17: Recette | C17: 2033000 | D17: 1859000 | E17: 2094000 | F17: 1282000 | G17: 2077000 | H17: 2345000 | I17: 1997000 | J17: 1772000
B18: Charges | C18: 854000 | D18: 884000 | E18: 962000 | F18: 669000 | G18: 800000 | H18: 883000 | I18: 883000 | J18: 664000
B19: Salaires | C19: 427000 | D19: 409000 | E19: 439000 | F19: 338000 | G19: 385000 | H19: 365000 | I19: 392000 | J19: 370000
B20: Che7i7a | C20: 62000 | D20: 56000 | E20: 60000 | F20: 50000 | G20: 180000 | H20: 56000 | I20: 62000 | J20: 48000
B21: Loyer+Dettes | C21: 180000 | D21: 180000 | E21: 180000 | F21: 180000 | G21: 180000 | H21: 180000 | I21: 180000 | J21: 180000
B22: Profit Net | C22: =C17-C18-C19-C20-C21 -> 510000 | D22: =D17-D18-D19-D20-D21 -> 330000 | E22: =E17-E18-E19-E20-E21 -> 453000 | F22: =F17-F18-F19-F20-F21 -> 45000 | G22: =G17-G18-G19-G20-G21 -> 532000 | H22: =H17-H18-H19-H20-H21 -> 861000 | I22: =I17-I18-I19-I20-I21 -> 480000 | J22: =J17-J18-J19-J20-J21 -> 510000
F28: Mois d'Août 2025
E29: Recette | F29: 1772000
E30: Charges | F30: 664000
E31: Salaires | F31: 370000
E32: Che7i7a | F32: 48000
E33: Loyer+Dettes | F33: 180000
E34: Profit Net | F34: 510000
