Workbook

Sheet RECAP
B1: Date | C1: Recette | D1: Charges | E1: Salaire | F1: Loyer | G1: Net Profit
A2: Dimanche | B2: 43800 | C2: 15000
A3: Lundi | B3: 43801 | C3: 19000
A4: Mardi | B4: 43802 | C4: 19000
A5: Mercredi | B5: 43803 | C5: 30000
A6: Jeudi | B6: 43804 | C6: 35000
A7: Vendredi | B7: 43805 | C7: 0
A8: Samedi | B8: 43806 | C8: 27000
A9: Dimanche | B9: 43807 | C9: 26000
A10: Lundi | B10: 43808 | C10: 21000
A11: Mardi | B11: 43809 | C11: 17000
A12: Mercredi | B12: 43810 | C12: 30000 | H12: -
A13: Jeudi | B13: 43811 | C13: 12000
A14: Vendredi | B14: 43812 | C14: 0
A15: Samedi | B15: 43813 | C15: 20000
A16: Dimanche | B16: 43814 | C16: 21000
A17: Lundi | B17: 43815 | C17: 26000
A18: Mardi | B18: 43816 | C18: 17000
A19: Mercredi | B19: 43817 | C19: 25000
A20: Jeudi | B20: 43818 | C20: 33000
A21: Vendredi | B21: 43819 | C21: 0
A22: Samedi | B22: 43820 | C22: 17000
A23: Dimanche | B23: 43821 | C23: 14000
A24: Lundi | B24: 43822 | C24: 16000
... A32: Mardi | B32: 43830 | C32: 25000
C33: =SUM(C2:C32) -> 573000 | D33: =Charges!F107*1 -> 187800 | E33: =Pointage!L35*1 -> 145200 | F33: 40000 | G33: =C33-D33-E33-F33 -> 200000 | J33: Cash restant | R33: =C33*1 -> 573000 | S33: =Pointage!K33*1 -> 29 | T33: =R33/S33 -> 19758.621
J34: =F33+G33+Charges!F108+'Salaires '!J24 -> 440900 | T34: 25000

Sheet Charges
D3: Produit | E3: Quantité | F3: Prix | G3: Date d'achat
D4: Sac en papier 23 | E4: 1 fardeau | F4: 780 | G4: 43800
D5: Sac en papier 12 | E5: 1 fardeau | F5: 450 | G5: 43800
D6: Sac en papier 05 | E6: 1 fardeau | F6: 330 | G6: 43800
D7: margarine Mani | E7: 2 cartons | F7: 5420 | G7: 43800
D8: Confiture | E8: 36 boites | F8: 7380 | G8: 43800
D9: bessel | E9: 50kg | F9: 2000 | G9: 43800
D10: Fromage spécial pizza | E10: 5.1kg | F10: 1670 | G10: 43800
D11: 7alewet taba3 | E11: 7 mesures | F11: 1430 | G11: 43800
D12: margarine Mani | E12: 4 boites | F12: 540 | G12: 43800
D13: semoule Amor Ben Amor | E13: 10 sachets de 10kg | F13: 6000 | G13: 43800
D14: ghress | E14: 31kg | F14: 5270 | G14: 43800
D15: epices 3akeri et persil | E15: 1.5kg | F15: 1500 | G15: 43800
... D22: Tissus | E22: 6 m | F22: 840 | G22: 43800
D23: Presseuse de galette en bois | E23: 2 | F23: 150 | G23: 43800
D24: Fromage spécial pizza | E24: 4.24 kg | F24: 1060 | G24: 43800
D25: Transport | E25: 1 | F25: 1000 | G25: 43800
D26: Gruyère | E26: 500g | F26: 500 | G26: 43800
D27: Gryère | E27: 1.5kg | F27: 1800 | G27: 43802
D28: Amina Baghrir | E28: 3 semaines | F28: 16550 | G28: 43802
D29: Yassir | E29: 1 | F29: 780 | G29: 43802
D30: Gryère | E30: 3.4kg | F30: 4310 | G30: 43803
D31: spécial pizza | E31: 43596 | F31: 2780 | G31: 43803
D32: Amor Ben Amor | E32: 90kg | F32: 5400 | G32: 43803
D33: spécial pizza | E33: 2.2kg | F33: 750 | G33: 43803
D34: herbes | E34: 5 | F34: 160 | G34: 43803
D35: na3ena3 yabess | E35: 1kg | F35: 900 | G35: 43803
D36: Semoule Bousmail extra fin | E36: 10kg | F36: 600 | G36: 43803
D37: Semoule Extra Ben Hamadi | E37: 15 sachets de 10gk | F37: 2900 | G37: 43804
D38: Semoule Extra Ben Hamadi | E38: 6 sachets de 5gk | F38: 1890 | G38: 43804
D39: Tableau acheté par Saida | E39: 1 | F39: 800 | G39: 43804
D40: Bessel | E40: 12kg | F40: 500 | G40: 43805
D41: Levure chimique | E41: 1 boite | F41: 360 | G41: 43805
D42: Herbes | E42: 7 bouquets | F42: 250 | G42: 43806
D43: yassir | E43: 2 | F43: 1000 | G43: 43806
D44: Semoule Amor Ben Amor | E44: 5 sachets de 10kg | F44: 3000 | G44: 43807
D45: Trasport | E45: 2 | F45: 1000 | G45: 43807
D46: Gateaux taba3 | E46: 7 | F46: 1300 | G46: 43807
D47: papier aluminium | E47: 1 boite de 200m | F47: 1000 | G47: 43807
D48: Harrissa | E48: 10 boites de 500g | F48: 850 | G48: 43808
D49: Tomate conserve | E49: 12 boites de 1 kg | F49: 2640 | G49: 43808
D50: Fromage spécial pizza | E50: 9.3kg | F50: 2620 | G50: 43808
D51: Isis | E51: 1 | F51: 250 | G51: 43808
D52: sel | E52: 1 fardeau | F52: 370 | G52: 43808
D53: Semoule Amor Ben Amor | E53: 5 sachets de 10kg | F53: 3000 | G53: 43808
D54: 7abet 7elawa | E54: 1kg | F54: 880 | G54: 43808
D55: vanille | E55: / | F55: 200 | G55: 43808
D56: Boite 36/7 | E56: 1 Fardeau | F56: 850 | G56: 43808
D57: Coca 1/2litre | E57: 2 fardeaux | F57: 1400 | G57: 43808
D58: jus | E58: 4 fardeaux | F58: 1920 | G58: 43808
D59: Coriandre moulu | E59: 1kg | F59: 800 | G59: 43808
D60: Sanoudj | E60: 1kg | F60: 700 | G60: 43808
D61: Bessel | E61: 20kg | F61: 800 | G61: 43808
D62: Bessel | E62: 100kg | F62: 5000 | G62: 43808
D63: Baghrir | E63: 1 semaine | F63: 3500 | G63: 43808
... D66: Semoule Amor Ben Amor | E66: 20 Sachets de 10kg | F66: 11400 | G66: 43808
D67: Transport | E67: 1 | F67: 740 | G67: 43808
D68: eau | E68: 10 | F68: 300 | G68: 43810
D69: Yassir | E69: 2 | F69: 1500 | G69: 43810
D70: margarine Mani | E70: 3 | F70: 390 | G70: 43810
D71: Omo | E71: 1 | F71: 100 | G71: 43810
D72: Herbes | E72: 6 | F72: 300 | G72: 43810
D73: Storm | E73: 1 | F73: 1000 | G73: 43813
D74: margarine Mani | E74: 5 boites | F74: 650 | G74: 43813
D75: arome citron | E75: 2 bouteilles | F75: 200 | G75: 43813
D76: rouleau papier | E76: 1 | F76: 600 | G76: 43813
D77: herbes | E77: 4 | F77: 100 | G77: 43813
D78: Farine | E78: 1kg | F78: 50 | G78: 43813
D79: margarine Mani | E79: 3 boites | F79: 390 | G79: 43814
D80: Mrgarine Mani | E80: 1 carton | F80: 2800 | G80: 42720
D81: 3akeri | E81: 1kg | F81: 750 | G81: 43815
D82: Tomate fraiche | E82: 11kg | F82: 1200 | G82: 43815
D83: Baghrir | E83: 1 semaine | F83: 5370 | G83: 43815
D84: margarine Mani | E84: 3 boites | F84: 400 | G84: 43815
D85: Yassir | E85: 1 | F85: 500 | G85: 43815
D86: Herbes | E86: 7 bouquets | F86: 250 | G86: 43815
D87: sacs poubelle | E87: 2 paquets | F87: 400 | G87: 43816
D88: Yassir | E88: 1 | F88: 500 | G88: 43816
D89: Huiles Bidons de 5litres | E89: 2 | F89: 1170 | G89: 43817
D90: Yassir | E90: 2 | F90: 1000 | G90: 43817
D91: Huile Fridor | E91: 5 bidons de 10 litres | F91: 5275 | G91: 43818
D92: herbes | E92: 5 | F92: 250 | G92: 43818
D93: Détergeants | E93: 5 | F93: 500 | G93: 43819
D94: herbes | E94: 7 | F94: 300 | G94: 43820
D95: Semoule Extra Fin Amor Ben Amor | E95: 9 | F95: 5220 | G95: 43822
D96: Boites 48/10 08/07 | E96: 2 cartons | F96: 2200 | G96: 43822
D97: margarine Mani | E97: 1 carton | F97: 2800 | G97: 43822
D98: Transport | E98: 2 | F98: 1500 | G98: 43822
D99: Recheta | E99: 7kg | F99: 700 | G99: 43825
D100: bessel | E100: 15kg | F100: 900 | G100: 43825
D101: Baghrir | E101: 1 semaine | F101: 3000 | G101: 43825
D102: gheress | E102: 11.4kg | F102: 1935 | G102: 43825
D103: Recheta + herbes | E103: 3kg+5 bouquets | F103: 400 | G103: 43827
D104: Semoule Amor Ben Amor | E104: 50kg | F104: 2500 | G104: 44193
D107: Totale | F107: =SUM(F4:F106) -> 187800
D108: Somme initiale | F108: 80000
D109: Rest | F109: =F108-F107 -> -107800

Sheet Pointage
B1: Date | C1: Zehor | D1: Sanaa | E1: Sabrina | F1: Souad | G1: Wahuba2 | H1: Naima | I1: Wahiba | J1: Loubna | K1: Zahida | L1: Remarque | M1: Reste à payer
A2: Dimanche | B2: 43800 | C2: 1 | D2: 1 | E2: 1 | F2: 1 | G2: 0 | H2: 0 | I2: 1 | J2: 0 | K2: 1
A3: Lundi | B3: 43801 | C3: 1 | D3: 1 | E3: 1 | F3: 1 | G3: 0 | H3: 0 | I3: 1 | J3: 1 | K3: 1
A4: Mardi | B4: 43802 | C4: 1 | D4: 1 | E4: 0 | F4: 1 | G4: 0 | H4: 0 | I4: 1 | J4: 0 | K4: 1
A5: Mercredi | B5: 43803 | C5: 1 | D5: 1 | E5: 0 | F5: 1 | G5: 0 | H5: 0 | I5: 1 | J5: 1 | K5: 1
A6: Jeudi | B6: 43804 | C6: 1 | D6: 1 | E6: 0 | F6: 1 | G6: 0 | H6: 0 | I6: 1 | J6: 0 | K6: 1
A7: Vendredi | B7: 43805 | C7: 0 | D7: 0 | E7: 0 | F7: 0 | G7: 0 | H7: 0 | I7: 0 | J7: 0 | K7: 0
A8: Samedi | B8: 43806 | C8: 1 | D8: 1 | E8: 0 | F8: 1 | G8: 0 | H8: 0 | I8: 1 | J8: 1 | K8: 1
A9: Dimanche | B9: 43807 | C9: 1 | D9: 1 | E9: 0 | F9: 1 | G9: 0 | H9: 0 | I9: 1 | J9: 0 | K9: 1
A10: Lundi | B10: 43808 | C10: 1 | D10: 1 | E10: 0 | F10: 1 | G10: 0 | H10: 0 | I10: 1 | J10: 1 | K10: 1
A11: Mardi | B11: 43809 | C11: 1 | D11: 1 | E11: 0 | F11: 1 | G11: 0 | H11: 0 | I11: 1 | J11: 0 | K11: 1
A12: Mercredi | B12: 43810 | C12: 1 | D12: 1 | E12: 0 | F12: 1 | G12: 0 | H12: 0 | I12: 1 | J12: 1 | K12: 1
A13: Jeudi | B13: 43811 | C13: 1 | D13: 1 | E13: 0 | F13: 1 | G13: 0 | H13: 0 | I13: 1 | J13: 0 | K13: 1
... A32: Mardi | B32: 43830 | C32: 1 | D32: 1 | E32: 0 | F32: 0 | G32: 0 | H32: 0 | I32: 0 | J32: 0 | K32: 1
B33: TOTAL | C33: =SUM(C2:C32) -> 20 | D33: =SUM(D2:D32) -> 28 | E33: =SUM(E2:E32) -> 2 | F33: =SUM(F2:F32) -> 13 | G33: =SUM(G2:G32) -> 1 | H33: =SUM(H2:H32) -> 1 | I33: =SUM(I2:I32) -> 25 | J33: =SUM(J2:J32) -> 11 | K33: =SUM(K2:K32) -> 29
B34: Salaire/jour | C34: 2000 | D34: 1000 | E34: 1000 | F34: 1400 | G34: 1000 | H34: 1000 | I34: 600 | J34: 1000 | K34: 1000 | L34: =SUM(C34:K34) -> 10000
B35: SALAIRES | C35: =C33*C34 -> 40000 | D35: =D34*D33 -> 28000 | E35: =E34*E33 -> 2000 | F35: =F33*F34 -> 18200 | G35: =G34*G33 -> 1000 | H35: =H34*H33 -> 1000 | I35: =I34*I33 -> 15000 | J35: =J34*J33 -> 11000 | K35: =K33*K34 -> 29000 | L35: =SUM(C35:K35) -> 145200

Sheet Salaires 
I13: Nom | J13: Salaire | K13: Avance
H14: 1 | I14: Zehor | J14: =Pointage!C35*1 -> 40000 | K14: 2300
H15: 2 | I15: Souad | J15: =Pointage!F35*1 -> 18200
H16: 3 | I16: Loubna | J16: =Pointage!J35*1 -> 11000
H17: 4 | I17: Sanaa | J17: =Pointage!D35*1 -> 28000 | K17: 5000
H18: 5 | I18: Wahiba2 | J18: =Pointage!G35*1 -> 1000
H19: 6 | I19: Naima | J19: =Pointage!H35*1 -> 1000
H20: 7 | I20: Sabrina | J20: 2000 | K20: 2000
H21: 8 | I21: Wahiba | J21: =Pointage!I35*1 -> 15000
H22: 9 | I22: Zahida | J22: =Pointage!K35*1 -> 29000 | K22: 15000
I23: TOTAL | J23: =SUM(J14:J22) -> 145200 | K23: =SUM(K14:K22) -> 24300
I24: RESTE | J24: =J23-K23 -> 120900

Sheet Magasin

Sheet Objectif
H6: Objectif | I6: Real | J6: Manque | K6: Bénéfice Prévu | L6: Bénéfice réel
H7: =RECAP!T34*RECAP!S33 -> 725000 | I7: =RECAP!C33*1 -> 573000 | J7: =H7-I7 -> 152000 | K7: =J7+L7 -> 352000 | L7: =RECAP!G33*1 -> 200000
