Workbook

Sheet RECAP
B1: Date | C1: Recette | D1: Charges | E1: Salaire | F1: Loyer | G1: Net Profit
A2: Mercredi | B2: 43831 | C2: 0
A3: Jeudi | B3: 43832 | C3: 25000
A4: Vendredi | B4: 43833 | C4: 0
A5: Samedi | B5: 43834 | C5: 15000
A6: Dimanche | B6: 43835 | C6: 16000
A7: Lundi | B7: 43836 | C7: 23000
A8: Mardi | B8: 43837 | C8: 19000
A9: Mercredi | B9: 43838 | C9: 28000
A10: Jeudi | B10: 43839 | C10: 46000
A11: Vendredi | B11: 43840 | C11: 0
A12: Samedi | B12: 43841 | C12: 53000
A13: Dimanche | B13: 43842 | C13: 25000
... A31: Jeudi | B31: 43860 | C31: 25000
A32: Vendredi | B32: 43861 | C32: 0 | Q32: =C33*1 -> 604000 | R32: =Pointage!C33*1 -> 25 | S32: =Q32/R32 -> 24160
C33: =SUM(C2:C32) -> 604000 | D33: =Charges!E78*1 -> 212000 | E33: =Pointage!I35*1 -> 155000 | F33: 45000 | G33: =C33-D33-E33-F33 -> 192000 | S33: 25000
C37: 100 | D37: =(D33/C33)*100 -> 35.099338 | E37: =(E33/C33)*100 -> 25.662252 | F37: =(F33/C33)*100 -> 7.4503311 | G37: =(G33/C33)*100 -> 31.788079

Sheet Pointage
B1: Date | C1: Zehor | D1: Hadjer | E1: Sanaa | F1: Zoubida | G1: Wahiba | H1: Zahida | I1: Remarque | J1: Reste à payer
A2: Mercredi | B2: 43831 | C2: 0 | D2: 0 | E2: 0 | F2: 0 | G2: 0 | H2: 0
A3: Jeudi | B3: 43832 | C3: 1 | D3: 0 | E3: 1 | F3: 0 | G3: 0 | H3: 1
A4: Vendredi | B4: 43833 | C4: 0 | D4: 0 | E4: 0 | F4: 0 | G4: 0 | H4: 0
A5: Samedi | B5: 43834 | C5: 1 | D5: 0 | E5: 0 | F5: 0 | G5: 1 | H5: 1
A6: Dimanche | B6: 43835 | C6: 1 | D6: 0 | E6: 1 | F6: 0 | G6: 1 | H6: 1
A7: Lundi | B7: 43836 | C7: 1 | D7: 0 | E7: 1 | F7: 0 | G7: 1 | H7: 1
A8: Mardi | B8: 43837 | C8: 1 | D8: 0 | E8: 1 | F8: 0 | G8: 1 | H8: 1
A9: Mercredi | B9: 43838 | C9: 1 | D9: 0 | E9: 1 | F9: 0 | G9: 1 | H9: 1
A10: Jeudi | B10: 43839 | C10: 1 | D10: 0 | E10: 1 | F10: 1 | G10: 1 | H10: 2
A11: Vendredi | B11: 43840 | C11: 0 | D11: 0 | E11: 1 | F11: 0 | G11: 1 | H11: 1
A12: Samedi | B12: 43841 | C12: 1 | D12: 0 | E12: 0 | F12: 1 | G12: 0 | H12: 2
A13: Dimanche | B13: 43842 | C13: 1 | D13: 1 | E13: 1 | F13: 1 | G13: 1 | H13: 2
... A32: Vendredi | B32: 43861 | C32: 0 | D32: 0 | E32: 0 | F32: 0 | G32: 0 | H32: 0
B33: TOTAL | C33: =SUM(C2:C32) -> 25 | D33: =SUM(D2:D32) -> 17 | E33: =SUM(E2:E32) -> 19 | F33: =SUM(F2:F32) -> 19 | G33: =SUM(G2:G32) -> 24 | H33: =SUM(H2:H32) -> 29
B34: Salaire/jour | C34: 2000 | D34: 600 | E34: 1200 | F34: 1200 | G34: 600 | H34: 1200 | I34: =SUM(C34:H34) -> 6800
B35: SALAIRES | C35: =C33*C34 -> 50000 | D35: =D34*D33 -> 10200 | E35: =E34*E33 -> 22800 | F35: =F34*F33 -> 22800 | G35: =G34*G33 -> 14400 | H35: =H33*H34 -> 34800 | I35: =SUM(C35:H35) -> 155000

Sheet Charges
C3: Produit | D3: Quantité | E3: Prix | F3: Date d'achat
C4: Semoule Extra Ben Hamadi | D4: 200kg | E4: 10600 | F4: 43831
C5: Huile Fridor | D5: 5 bidons de 10 litres | E5: 5275 | F5: 43831
C6: Electricité | D6: 3 mois | E6: 10000 | F6: 43831
C7: gherss | D7: 10kg | E7: 1700 | F7: 43831
C8: Fromage gruyère | D8: 1.9kg | E8: 2660 | F8: 43831
C9: Fromage spéciale pizza | D9: 5.8kg | E9: 1460 | F9: 43831
C10: Sachets en papier moyen | D10: 1 | E10: 730 | F10: 43831
C11: sachets transparent | D11: 2 | E11: 2200 | F11: 43831
C12: Semoule Amor Ben Amor | D12: 5 sachets de 25kg | E12: 6500 | F12: 43831
C13: boite 36/7 | D13: 1 carton | E13: 860 | F13: 43831
C14: boite 36/10 | D14: 1 carton | E14: 1100 | F14: 43831
C15: boite 48/10 | D15: 2 cartons | E15: 2800 | F15: 43831
C16: sac 23 | D16: 2 fardeaux | E16: 2200 | F16: 43831
C17: isis | D17: 2 bouteilles | E17: 500 | F17: 43831
C18: eau de javel | D18: 1 bidon de 5 litres | E18: 250 | F18: 43831
C19: levure chimique | D19: 1 boite | E19: 390 | F19: 43831
C20: sel | D20: 2 fardeaux | E20: 760 | F20: 43831
C21: gruyère | D21: 2.5kg | E21: 3600 | F21: 43831
C22: coca 1/2 litres | D22: 2 fardeaux | E22: 1400 | F22: 43831
C23: jus ifruit | D23: 3 fardeaux | E23: 1470 | F23: 43831
... C35: Huile Fridor | D35: 15 bidons de 10 litres | E35: 15825 | F35: 43838
C36: transport yassir | D36: 1 | E36: 700 | F36: 43839
C37: 3akeri | D37: 1kg | E37: 900 | F37: 43840
C38: felfel driss | D38: 1kg | E38: 900 | F38: 43840
C39: bessele | D39: 20kg | E39: 1000 | F39: 43840
C40: Recheta | D40: 30kg | E40: 3000 | F40: 43841
C41: semoule Habour | D41: 75kg | E41: 3500 | F41: 43841
C42: Taxi transport personel | D42: 1 | E42: 1000 | F42: 43841
C43: semoule haboure +livraison | D43: 15 sachets de 25gk | E43: 18250 | F43: 43842
C44: boites 36/7 | D44: 1 carton | E44: 780 | F44: 43843
C45: boites36/10 | D45: 1 carton | E45: 1050 | F45: 43843
C46: bessele | D46: 50kg | E46: 3000 | F46: 43843
C47: felefel guenawa | D47: 05kg | E47: 1000 | F47: 43843
C48: Storm | D48: 1 mois Maxi | E48: 1000 | F48: 43843
C49: Briquets | D49: 2 | E49: 360 | F49: 43844
C50: bessele | D50: 100kg | E50: 6000 | F50: 43845
C51: Margarine Mani | D51: 5 boites | E51: 650 | F51: 43848
C52: Recheta | D52: 10kg | E52: 1000 | F52: 43845
C53: transport yassir | D53: 1 | E53: 500 | F53: 43845
C54: Baghrir | D54: 2 semaines | E54: 11000 | F54: 43848
C55: Boites 08/07 | D55: 40 pièces | E55: 600 | F55: 43849
C56: Margarine Mani | D56: 5 boites | E56: 650 | F56: 43850
C57: Herbes | D57: 8 | E57: 270 | F57: 43850
C58: Ghress | D58: 4.3kg | E58: 730 | F58: 43850
C59: Décapant | D59: 7 | E59: 650 | F59: 43851
C60: Margarine Mani | D60: 1 carton | E60: 2850 | F60: 43851
C61: lait en poudre | D61: 2kg | E61: 1350 | F61: 43851
C62: vanille | D62: / | E62: 200 | F62: 43851
C63: felefel guenawa | D63: 05kg | E63: 800 | F63: 43851
C64: Recheta | D64: 10kg | E64: 1000 | F64: 43852
C65: Herebes | D65: 8 | E65: 300 | F65: 43852
C66: transport yassir | D66: 1 | E66: 500 | F66: 43852
C67: Recheta | D67: 15kg | E67: 1500 | F67: 43853
C68: détergeants pour le ménage de demain | D68: 7 | E68: 1350 | F68: 43853
C69: gheress | D69: 6.5kg | E69: 1100 | F69: 43853
C70: transport yassir | D70: 2 | E70: 850 | F70: 43853
C71: bessele | D71: 100kg | E71: 5500 | F71: 43855
C72: Refiss | D72: 98 pièces | E72: 4000 | F72: 43857
C73: Baghrir | D73: 2 semaines | E73: 21200 | F73: 43857
C74: Recheta | D74: 5kg | E74: 500 | F74: 43858
C75: Herbes | D75: 7 boquts | E75: 200 | F75: 43858
C76: Facebook | D76: 1 | E76: 6100 | F76: 43861
C77: Recheta | D77: 5 kg | E77: 500 | F77: 43860
C78: TOTALE | E78: =SUM(E4:E77) -> 212000
C79: Somme initiale | E79: 80000
C80: Rest | E80: =E79-E78 -> -132000

Sheet Salaires
H13: Nom | I13: Salaire | J13: Avance
G14: 1 | H14: Zehor | I14: =Pointage!C35*1 -> 50000
G15: 2 | H15: Sanaa | I15: =Pointage!E35*1 -> 22800
G16: 3 | H16: Wahiba | I16: =Pointage!G35*1 -> 14400
G17: 4 | H17: Hadjer | I17: =Pointage!D35*1 -> 10200 | J17: 4000
G18: 5 | H18: Zoubida | I18: =Pointage!F35*1 -> 22800
G19: 6 | H19: Zahida | I19: =Pointage!H35*1 -> 34800
H20: TOTAL | I20: =SUM(I14:I19) -> 155000 | J20: =SUM(J14:J19) -> 4000
I21: =I20-J20 -> 151000

Sheet Magasin

Sheet Objectif
G6: Objectif | H6: Real | I6: Manque | J6: Bénéfice Prévu | K6: Bénéfice réel
G7: =RECAP!S33*RECAP!R32 -> 625000 | H7: =RECAP!C33*1 -> 604000 | I7: =G7-H7 -> 21000 | J7: =G7-RECAP!D33-RECAP!E33-RECAP!F33 -> 213000 | K7: =RECAP!C33-RECAP!D33-RECAP!E33-RECAP!F33 -> 192000
